Workbook
Name actual2m: actual2[[#All],[Month]:[Primary Deficit]]

Sheet Dashboard
C6: Financial Year | D6: 2025-26
C8: As at the end of | D8: Dec-25 | F8: =Sheet5!E9 -> 2525156 | I8: =IF(MONTH(D8)<4,Sheet5!N9,Sheet5!M9) -> 0.72221413 | J8: =Sheet5!K9 -> 0.089366071 | K8: =Sheet5!L9 -> 0.089366071 | M8: =Sheet5!E11 -> 3380998 | Q8: =IF(MONTH(D8)<4,Sheet5!N11,Sheet5!M11) -> 0.66747635 | R8: =Sheet5!K11 -> 0.046070442 | S8: =Sheet5!L11 -> 0.046070442 | U8: =Sheet5!E13 -> 855842
I9: =CONCATENATE("of ",B58) -> of BE | J9: YoY Growth | Q9: =CONCATENATE("of ",B58) -> of BE | R9: YoY Growth
U10: =IF(MONTH(D8)<4,Sheet5!N13,Sheet5!M13) -> 0.54549198 | W10: =CONCATENATE("of ",B58) -> of BE
U11: =Sheet5!O13 -> 0.023963844 | W11: of GDP
U12: =Sheet5!K13 -> -0.063721366 | W12: =Sheet5!L13 -> -0.063721366
U13: YoY Growth
F14: =Sheet5!E15 -> 1939254 | M14: =Sheet5!E21 -> 2593063
F15: =IF(MONTH(D8)<4,Sheet5!N15,Sheet5!M15) -> 0.68345945 | G15: =CONCATENATE("of ",B58) -> of BE | M15: =IF(MONTH(D8)<4,Sheet5!N21,Sheet5!M21) -> 0.65742783 | N15: =CONCATENATE("of ",B58) -> of BE
F16: =Sheet5!K15 -> 0.052196546 | H16: =Sheet5!L15 -> 0.052196546 | M16: =Sheet5!K21 -> 0.018182339 | O16: =Sheet5!L21 -> 0.018182339
F17: YoY Growth | M17: YoY Growth
U18: =Sheet5!E37 -> 113954
F20: Non Tax Revenue | U20: =IF(MONTH(D8)<4,Sheet5!N37,Sheet5!M37) -> 0.2175334 | W20: =CONCATENATE("of ",B58) -> of BE
U21: =Sheet5!O37 -> 0.0031907477 | W21: of GDP
F22: =Sheet5!E17 -> 539855 | U22: =Sheet5!K37 -> -0.5549489 | W22: =Sheet5!L37 -> -0.5549489
F23: =IF(MONTH(D8)<4,Sheet5!N17,Sheet5!M17) -> 0.92599485 | G23: =CONCATENATE("of ",B58) -> of BE | U23: YoY Growth
F24: =Sheet5!K17 -> 0.20595679 | H24: =Sheet5!L17 -> 0.20595679
F25: YoY Growth
U29: =Sheet5!E41 -> -55217
F31: =Sheet5!E19 -> 46047 | M31: =Sheet5!E23 -> 787935 | U31: =IF(MONTH(D8)<4,Sheet5!N41,Sheet5!M41) -> -0.18871284 | W31: =CONCATENATE("of ",B58) -> of BE
F32: =IF(MONTH(D8)<4,Sheet5!N19,Sheet5!M19) -> 0.60588158 | G32: =CONCATENATE("of ",B58) -> of BE | M32: =IF(MONTH(D8)<4,Sheet5!N23,Sheet5!M23) -> 0.70282939 | N32: =CONCATENATE("of ",B58) -> of BE | U32: =Sheet5!O41 -> -0.0015460933 | W32: of GDP
F33: =Sheet5!K19 -> 0.68701227 | H33: =Sheet5!L19 -> 0.68701227 | M33: =Sheet5!K23 -> 0.14970445 | O33: =Sheet5!L23 -> 0.14970445 | U33: =Sheet5!K41 -> -1.5220182 | W33: =Sheet5!L41 -> -1.5220182
F34: YoY Growth | M34: YoY Growth | U34: YoY Growth
B38: Disclaimer :
A39: 1. | B39: All content included in the dashboard is for informative purposes only. Information herein contains both original Budget, Expenditure, GDP data and estimates and is subject to updation, correction and revision with more information available.
A40: 2. | B40: The presentation of the graphical information herein does not imply the expression of any opinion concerning the performance, error, omission etc. of any institution or authorities.
A41: 3. | B41: Discrepancies between information contained in this dashboard and other documents, analysis, articles and publication may exist due to the different timing and presentation of information in accordance to various purposes.
A42: 4. | B42: This disclaimer of liability applies to all claims for damages, including, but not limited to: failure of performance, error, omission, deletion, defect, computer virus or unauthorized access to or alteration of data.
B43: Queries and feedback may be addressed to dama-cga@nic.in or vpthomas.17@gov.in
J53: =INDEX(actual!B:B,COUNTA(actual!B:B)) -> Dec-25 | M53: =DATEVALUE(J53)+1 -> 45993
B58: =IF(MONTH(D8)<4,"RE","BE") -> BE | D58: Row Labels | J58: =CONCATENATE("Apr-",MID($D$6,3,2)) -> Apr-25 | Q58: =IF(IF(DATEVALUE(CONCATENATE("Apr-",MID($D$6,3,2)))<$M$53,DATEVALUE(CONCATENATE("Apr-",MID($D$6,3,2))),0)>0,CONCATENATE("Apr-",MID($D$6,3,2))," ") -> Apr-25
D59: 2014-15 | J59: =CONCATENATE("May-",MID($D$6,3,2)) -> May-25 | Q59: =IF(IF(DATEVALUE(CONCATENATE("May-",MID($D$6,3,2)))<$M$53,DATEVALUE(CONCATENATE("May-",MID($D$6,3,2))),0)>0,CONCATENATE("May-",MID($D$6,3,2))," ") -> May-25
D60: 2015-16 | J60: =CONCATENATE("Jun-",MID($D$6,3,2)) -> Jun-25 | Q60: =IF(IF(DATEVALUE(CONCATENATE("Jun-",MID($D$6,3,2)))<$M$53,DATEVALUE(CONCATENATE("Jun-",MID($D$6,3,2))),0)>0,CONCATENATE("Jun-",MID($D$6,3,2))," ") -> Jun-25
D61: 2016-17 | J61: =CONCATENATE("Jul-",MID($D$6,3,2)) -> Jul-25 | Q61: =IF(IF(DATEVALUE(CONCATENATE("Jul-",MID($D$6,3,2)))<$M$53,DATEVALUE(CONCATENATE("Jul-",MID($D$6,3,2))),0)>0,CONCATENATE("Jul-",MID($D$6,3,2))," ") -> Jul-25
D62: 2017-18 | J62: =CONCATENATE("Aug-",MID($D$6,3,2)) -> Aug-25 | Q62: =IF(IF(DATEVALUE(CONCATENATE("Aug-",MID($D$6,3,2)))<$M$53,DATEVALUE(CONCATENATE("Aug-",MID($D$6,3,2))),0)>0,CONCATENATE("Aug-",MID($D$6,3,2))," ") -> Aug-25
D63: 2018-19 | J63: =CONCATENATE("Sep-",MID($D$6,3,2)) -> Sep-25 | Q63: =IF(IF(DATEVALUE(CONCATENATE("Sep-",MID($D$6,3,2)))<$M$53,DATEVALUE(CONCATENATE("Sep-",MID($D$6,3,2))),0)>0,CONCATENATE("Sep-",MID($D$6,3,2))," ") -> Sep-25
D64: 2019-20 | J64: =CONCATENATE("Oct-",MID($D$6,3,2)) -> Oct-25 | Q64: =IF(IF(DATEVALUE(CONCATENATE("Oct-",MID($D$6,3,2)))<$M$53,DATEVALUE(CONCATENATE("Oct-",MID($D$6,3,2))),0)>0,CONCATENATE("Oct-",MID($D$6,3,2))," ") -> Oct-25
D65: 2020-21 | J65: =CONCATENATE("Nov-",MID($D$6,3,2)) -> Nov-25 | Q65: =IF(IF(DATEVALUE(CONCATENATE("Nov-",MID($D$6,3,2)))<$M$53,DATEVALUE(CONCATENATE("Nov-",MID($D$6,3,2))),0)>0,CONCATENATE("Nov-",MID($D$6,3,2))," ") -> Nov-25
D66: 2021-22 | J66: =CONCATENATE("Dec-",MID($D$6,3,2)) -> Dec-25 | Q66: =IF(IF(DATEVALUE(CONCATENATE("Dec-",MID($D$6,3,2)))<$M$53,DATEVALUE(CONCATENATE("Dec-",MID($D$6,3,2))),0)>0,CONCATENATE("Dec-",MID($D$6,3,2))," ") -> Dec-25
D67: 2022-23 | J67: =CONCATENATE("Jan-",MID($D$6,6,2)) -> Jan-26 | Q67: =IF(IF(DATEVALUE(CONCATENATE("Jan-",MID($D$6,6,2)))<$M$53,DATEVALUE(CONCATENATE("Jan-",MID($D$6,6,2))),0)>0,CONCATENATE("Jan-",MID($D$6,6,2))," ")
D68: 2023-24 | J68: =CONCATENATE("Feb-",MID($D$6,6,2)) -> Feb-26 | Q68: =IF(IF(DATEVALUE(CONCATENATE("Feb-",MID($D$6,6,2)))<$M$53,DATEVALUE(CONCATENATE("Feb-",MID($D$6,6,2))),0)>0,CONCATENATE("Feb-",MID($D$6,6,2))," ")
D69: 2024-25 | J69: =CONCATENATE("Mar-",MID($D$6,6,2)) -> Mar-26 | Q69: =IF(IF(DATEVALUE(CONCATENATE("Mar-",MID($D$6,6,2)))<$M$53,DATEVALUE(CONCATENATE("Mar-",MID($D$6,6,2))),0)>0,CONCATENATE("Mar-",MID($D$6,6,2))," ")
D70: 2025-26
D71: (blank)

Sheet Receipts

Sheet Expenditure

Sheet Deficit

Sheet actual
A1: FY | B1: Month | C1: Corporation Tax | D1: Income Tax | E1: Securities Transcation Tax | F1: CGST | G1: IGST | H1: UTGST | I1: Compensation Cess | J1: Customs | K1: Union Excise | L1: Service Tax | M1: Other Taxes | N1: Surcharge for financing of NCCF | O1: Devolution to State | P1: Interest receipts | Q1: Dividends and Profits | R1: Other Non Tax Receipts | S1: Recovery of Loans & Advances | T1: Disinvestment Receipts | U1: Revenue Expenditure | V1: Interest Payments | W1: Defence Services | X1: Grants in Aid to States & UTs | Y1: Pensions | Z1: Major Subsidies | AA1: Grants for Creation of Capital Assets | AB1: Capital Expenditure | AE1: Revenue Deficit | AF1: Effective revenue Deficit | AG1: Fiscal Deficit | AH1: Primary Deficit
A2: 2014-15 | B2: Apr-14 | C2: -5845 | D2: 20348 | E2: 168 | J2: 11754 | K2: -2817 | L2: 4876 | M2: 310 | N2: 122 | O2: 27695 | P2: 514 | Q2: 825 | R2: 4613 | S2: 144 | T2: 0 | U2: 108084 | V2: 23284 | W2: 19381 | X2: 962 | Y2: 5507 | Z2: 31779 | AA2: 10112 | AB2: 12443 | AD2: =SUM(actual1[[#This Row],[Corporation Tax]:[Other Taxes]])-actual1[[#This Row],[Surcharge for financing of NCCF]]-actual1[[#This Row],[Devolution to State]]+SUM(P2:R2)+SUM(S2:T2) -> 7073 | AE2: =actual1[[#This Row],[Revenue Expenditure]]-(SUM(actual1[[#This Row],[Corporation Tax]:[Other Taxes]])-actual1[[#This Row],[Surcharge for financing of NCCF]]-actual1[[#This Row],[Devolution to State]]+SUM(P2:R2)) -> 101155 | AF2: =AE2-actual1[[#This Row],[Grants for Creation of Capital Assets]] -> 91043 | AG2: =U2+AB2-(SUM(actual1[[#This Row],[Corporation Tax]:[Other Taxes]])-actual1[[#This Row],[Surcharge for financing of NCCF]]-actual1[[#This Row],[Devolution to State]]+SUM(P2:R2)+SUM(S2:T2)) -> 113454 | AH2: =AG2-actual1[[#This Row],[Interest Payments]] -> 90170
A3: 2014-15 | B3: May-14 | C3: 2980 | D3: 35449 | E3: 626 | J3: 24800 | K3: 5569 | L3: 14431 | M3: 661 | N3: 474 | O3: 55391 | P3: 645 | Q3: 837 | R3: 8372 | S3: 997 | T3: 0 | U3: 243585 | V3: 54857 | W3: 35705 | X3: 2122 | Y3: 14766 | Z3: 71250 | AA3: 21456 | AB3: 36754 | AD3: =U2+AB2 -> 120527 | AE3: =actual1[[#This Row],[Revenue Expenditure]]-(SUM(actual1[[#This Row],[Corporation Tax]:[Other Taxes]])-actual1[[#This Row],[Surcharge for financing of NCCF]]-actual1[[#This Row],[Devolution to State]]+SUM(P3:R3)) -> 205080 | AF3: =AE3-actual1[[#This Row],[Grants for Creation of Capital Assets]] -> 183624 | AG3: =U3+AB3-(SUM(actual1[[#This Row],[Corporation Tax]:[Other Taxes]])-actual1[[#This Row],[Surcharge for financing of NCCF]]-actual1[[#This Row],[Devolution to State]]+SUM(P3:R3)+SUM(S3:T3)) -> 240837 | AH3: =AG3-actual1[[#This Row],[Interest Payments]] -> 185980
A4: 2014-15 | B4: Jun-14 | C4: 50447 | D4: 46398 | E4: 1374 | J4: 38649 | K4: 18403 | L4: 26628 | M4: 1129 | N4: 856 | O4: 83086 | P4: 2005 | Q4: 2195 | R4: 11140 | S4: 1208 | T4: 109 | U4: 363785 | V4: 90694 | W4: 49351 | X4: 5501 | Y4: 22449 | Z4: 81443 | AA4: 32274 | AB4: 49818 | AE4: =actual1[[#This Row],[Revenue Expenditure]]-(SUM(actual1[[#This Row],[Corporation Tax]:[Other Taxes]])-actual1[[#This Row],[Surcharge for financing of NCCF]]-actual1[[#This Row],[Devolution to State]]+SUM(P4:R4)) -> 249359 | AF4: =AE4-actual1[[#This Row],[Grants for Creation of Capital Assets]] -> 217085 | AG4: =U4+AB4-(SUM(actual1[[#This Row],[Corporation Tax]:[Other Taxes]])-actual1[[#This Row],[Surcharge for financing of NCCF]]-actual1[[#This Row],[Devolution to State]]+SUM(P4:R4)+SUM(S4:T4)) -> 297860 | AH4: =AG4-actual1[[#This Row],[Interest Payments]] -> 207166
A5: 2014-15 | B5: Jul-14 | C5: 62518 | D5: 64905 | E5: 2067 | J5: 53881 | K5: 32264 | L5: 41628 | M5: 1610 | N5: 1227 | O5: 110781 | P5: 3546 | Q5: 3721 | R5: 21500 | S5: 3262 | T5: 122 | U5: 442051 | V5: 118615 | W5: 65913 | X5: 11908 | Y5: 29129 | Z5: 83557 | AA5: 36213 | AB5: 61889 | AE5: =actual1[[#This Row],[Revenue Expenditure]]-(SUM(actual1[[#This Row],[Corporation Tax]:[Other Taxes]])-actual1[[#This Row],[Surcharge for financing of NCCF]]-actual1[[#This Row],[Devolution to State]]+SUM(P5:R5)) -> 266419 | AF5: =AE5-actual1[[#This Row],[Grants for Creation of Capital Assets]] -> 230206 | AG5: =U5+AB5-(SUM(actual1[[#This Row],[Corporation Tax]:[Other Taxes]])-actual1[[#This Row],[Surcharge for financing of NCCF]]-actual1[[#This Row],[Devolution to State]]+SUM(P5:R5)+SUM(S5:T5)) -> 324924 | AH5: =AG5-actual1[[#This Row],[Interest Payments]] -> 206309
A6: 2014-15 | B6: Aug-14 | C6: 73569 | D6: 78535 | E6: 2717 | J6: 69838 | K6: 45453 | L6: 52817 | M6: 2009 | N6: 1555 | O6: 137924 | P6: 4440 | Q6: 56274 | R6: 24282 | S6: 4212 | T6: 122 | U6: 595219 | V6: 153876 | W6: 82049 | X6: 18024 | Y6: 38354 | Z6: 125762 | AA6: 53551 | AB6: 77499 | AE6: =actual1[[#This Row],[Revenue Expenditure]]-(SUM(actual1[[#This Row],[Corporation Tax]:[Other Taxes]])-actual1[[#This Row],[Surcharge for financing of NCCF]]-actual1[[#This Row],[Devolution to State]]+SUM(P6:R6)) -> 324764 | AF6: =AE6-actual1[[#This Row],[Grants for Creation of Capital Assets]] -> 271213 | AG6: =U6+AB6-(SUM(actual1[[#This Row],[Corporation Tax]:[Other Taxes]])-actual1[[#This Row],[Surcharge for financing of NCCF]]-actual1[[#This Row],[Devolution to State]]+SUM(P6:R6)+SUM(S6:T6)) -> 397929 | AH6: =AG6-actual1[[#This Row],[Interest Payments]] -> 244053
A7: 2014-15 | B7: Sep-14 | C7: 162269 | D7: 109412 | E7: 3223 | J7: 87408 | K7: 60547 | L7: 65201 | M7: 2558 | N7: 2012 | O7: 165415 | P7: 6347 | Q7: 61388 | R7: 26970 | S7: 5210 | T7: 121 | U7: 762949 | V7: 185670 | W7: 102021 | X7: 24324 | Y7: 46206 | Z7: 160133 | AA7: 66269 | AB7: 99104 | AE7: =actual1[[#This Row],[Revenue Expenditure]]-(SUM(actual1[[#This Row],[Corporation Tax]:[Other Taxes]])-actual1[[#This Row],[Surcharge for financing of NCCF]]-actual1[[#This Row],[Devolution to State]]+SUM(P7:R7)) -> 345053 | AF7: =AE7-actual1[[#This Row],[Grants for Creation of Capital Assets]] -> 278784 | AG7: =U7+AB7-(SUM(actual1[[#This Row],[Corporation Tax]:[Other Taxes]])-actual1[[#This Row],[Surcharge for financing of NCCF]]-actual1[[#This Row],[Devolution to State]]+SUM(P7:R7)+SUM(S7:T7)) -> 438826 | AH7: =AG7-actual1[[#This Row],[Interest Payments]] -> 253156
A8: 2014-15 | B8: Oct-14 | C8: 173381 | D8: 124972 | E8: 3876 | J8: 104104 | K8: 73105 | L8: 81213 | M8: 2947 | N8: 2515 | O8: 192211 | P8: 10651 | Q8: 63856 | R8: 36694 | S8: 6142 | T8: 122 | U8: 852707 | V8: 205974 | W8: 119070 | X8: 28317 | Y8: 53737 | Z8: 178105 | AA8: 73705 | AB8: 109382 | AE8: =actual1[[#This Row],[Revenue Expenditure]]-(SUM(actual1[[#This Row],[Corporation Tax]:[Other Taxes]])-actual1[[#This Row],[Surcharge for financing of NCCF]]-actual1[[#This Row],[Devolution to State]]+SUM(P8:R8)) -> 372634 | AF8: =AE8-actual1[[#This Row],[Grants for Creation of Capital Assets]] -> 298929 | AG8: =U8+AB8-(SUM(actual1[[#This Row],[Corporation Tax]:[Other Taxes]])-actual1[[#This Row],[Surcharge for financing of NCCF]]-actual1[[#This Row],[Devolution to State]]+SUM(P8:R8)+SUM(S8:T8)) -> 475752 | AH8: =AG8-actual1[[#This Row],[Interest Payments]] -> 269778
A9: 2014-15 | B9: Nov-14 | C9: 188553 | D9: 140150 | E9: 4357 | J9: 120225 | K9: 85925 | L9: 92903 | M9: 3470 | N9: 2918 | O9: 219355 | P9: 11629 | Q9: 63959 | R9: 52755 | S9: 7174 | T9: 222 | U9: 952728 | V9: 232650 | W9: 135526 | X9: 33124 | Y9: 61316 | Z9: 195504 | AA9: 81584 | AB9: 121455 | AE9: =actual1[[#This Row],[Revenue Expenditure]]-(SUM(actual1[[#This Row],[Corporation Tax]:[Other Taxes]])-actual1[[#This Row],[Surcharge for financing of NCCF]]-actual1[[#This Row],[Devolution to State]]+SUM(P9:R9)) -> 411075 | AF9: =AE9-actual1[[#This Row],[Grants for Creation of Capital Assets]] -> 329491 | AG9: =U9+AB9-(SUM(actual1[[#This Row],[Corporation Tax]:[Other Taxes]])-actual1[[#This Row],[Surcharge for financing of NCCF]]-actual1[[#This Row],[Devolution to State]]+SUM(P9:R9)+SUM(S9:T9)) -> 525134 | AH9: =AG9-actual1[[#This Row],[Interest Payments]] -> 292484
A10: 2014-15 | B10: Dec-14 | C10: 277620 | D10: 166556 | E10: 4939 | J10: 135596 | K10: 101859 | L10: 105196 | M10: 3920 | N10: 3362 | O10: 246610 | P10: 15808 | Q10: 69674 | R10: 62577 | S10: 8282 | T10: 1952 | U10: 1095548 | V10: 275220 | W10: 157318 | X10: 34598 | Y10: 68104 | Z10: 212418 | AA10: 97863 | AB10: 140840 | AE10: =actual1[[#This Row],[Revenue Expenditure]]-(SUM(actual1[[#This Row],[Corporation Tax]:[Other Taxes]])-actual1[[#This Row],[Surcharge for financing of NCCF]]-actual1[[#This Row],[Devolution to State]]+SUM(P10:R10)) -> 401775 | AF10: =AE10-actual1[[#This Row],[Grants for Creation of Capital Assets]] -> 303912 | AG10: =U10+AB10-(SUM(actual1[[#This Row],[Corporation Tax]:[Other Taxes]])-actual1[[#This Row],[Surcharge for financing of NCCF]]-actual1[[#This Row],[Devolution to State]]+SUM(P10:R10)+SUM(S10:T10)) -> 532381 | AH10: =AG10-actual1[[#This Row],[Interest Payments]] -> 257161
A11: 2014-15 | B11: Jan-15 | C11: 287720 | D11: 182077 | E11: 5556 | J11: 151849 | K11: 118109 | L11: 122450 | M11: 4323 | N11: 3645 | O11: 273642 | P11: 17236 | Q11: 70019 | R11: 71055 | S11: 9954 | T11: 7068 | U11: 1194613 | V11: 312260 | W11: 174307 | X11: 37023 | Y11: 76133 | Z11: 231788 | AA11: 102208 | AB11: 143655 | AE11: =actual1[[#This Row],[Revenue Expenditure]]-(SUM(actual1[[#This Row],[Corporation Tax]:[Other Taxes]])-actual1[[#This Row],[Surcharge for financing of NCCF]]-actual1[[#This Row],[Devolution to State]]+SUM(P11:R11)) -> 441506 | AF11: =AE11-actual1[[#This Row],[Grants for Creation of Capital Assets]] -> 339298 | AG11: =U11+AB11-(SUM(actual1[[#This Row],[Corporation Tax]:[Other Taxes]])-actual1[[#This Row],[Surcharge for financing of NCCF]]-actual1[[#This Row],[Devolution to State]]+SUM(P11:R11)+SUM(S11:T11)) -> 568139 | AH11: =AG11-actual1[[#This Row],[Interest Payments]] -> 255879
A12: 2014-15 | B12: Feb-15 | C12: 301761 | D12: 199496 | E12: 6280 | J12: 167492 | K12: 140322 | L12: 134889 | M12: 4713 | N12: 4035 | O12: 299499 | P12: 18561 | Q12: 72397 | R12: 73861 | S12: 11063 | T12: 29701 | U12: 1299492 | V12: 346256 | W12: 193989 | X12: 46673 | Y12: 80321 | Z12: 237878 | AA12: 114070 | AB12: 160044 | AE12: =actual1[[#This Row],[Revenue Expenditure]]-(SUM(actual1[[#This Row],[Corporation Tax]:[Other Taxes]])-actual1[[#This Row],[Surcharge for financing of NCCF]]-actual1[[#This Row],[Devolution to State]]+SUM(P12:R12)) -> 483254 | AF12: =AE12-actual1[[#This Row],[Grants for Creation of Capital Assets]] -> 369184 | AG12: =U12+AB12-(SUM(actual1[[#This Row],[Corporation Tax]:[Other Taxes]])-actual1[[#This Row],[Surcharge for financing of NCCF]]-actual1[[#This Row],[Devolution to State]]+SUM(P12:R12)+SUM(S12:T12)) -> 602534 | AH12: =AG12-actual1[[#This Row],[Interest Payments]] -> 256278
A13: 2014-15 | B13: Mar-15 | C13: 428925 | D13: 258334 | E13: 7398 | J13: 188016 | K13: 189953 | L13: 167969 | M13: 4289 | N13: 3461 | O13: 337808 | P13: 23734 | Q13: 89861 | R13: 84171 | S13: 13738 | T13: 37737 | U13: 1466992 | V13: 402444 | W13: 218694 | X13: 77198 | Y13: 93611 | Z13: 249220 | AA13: 130760 | AB13: 196681 | AE13: =actual1[[#This Row],[Revenue Expenditure]]-(SUM(actual1[[#This Row],[Corporation Tax]:[Other Taxes]])-actual1[[#This Row],[Surcharge for financing of NCCF]]-actual1[[#This Row],[Devolution to State]]+SUM(P13:R13)) -> 365611 | AF13: =AE13-actual1[[#This Row],[Grants for Creation of Capital Assets]] -> 234851 | AG13: =U13+AB13-(SUM(actual1[[#This Row],[Corporation Tax]:[Other Taxes]])-actual1[[#This Row],[Surcharge for financing of NCCF]]-actual1[[#This Row],[Devolution to State]]+SUM(P13:R13)+SUM(S13:T13)) -> 510817 | AH13: =AG13-actual1[[#This Row],[Interest Payments]] -> 108373
A14: 2015-16 | B14: Apr-15 | C14: -4319 | D14: 19878 | E14: 268 | J14: 14452 | K14: -2696 | L14: 6874 | M14: 359 | N14: 208 | O14: 37421 | P14: 768 | Q14: 1 | R14: 27357 | S14: 173 | T14: 1608 | U14: 128408 | V14: 16994 | W14: 18512 | X14: 4856 | Y14: 9031 | Z14: 41130 | AA14: 18367 | AB14: 26209 | AE14: =actual1[[#This Row],[Revenue Expenditure]]-(SUM(actual1[[#This Row],[Corporation Tax]:[Other Taxes]])-actual1[[#This Row],[Surcharge for financing of NCCF]]-actual1[[#This Row],[Devolution to State]]+SUM(P14:R14)) -> 103095 | AF14: =AE14-actual1[[#This Row],[Grants for Creation of Capital Assets]] -> 84728 | AG14: =U14+AB14-(SUM(actual1[[#This Row],[Corporation Tax]:[Other Taxes]])-actual1[[#This Row],[Surcharge for financing of NCCF]]-actual1[[#This Row],[Devolution to State]]+SUM(P14:R14)+SUM(S14:T14)) -> 127523 | AH14: =AG14-actual1[[#This Row],[Interest Payments]] -> 110529
A15: 2015-16 | B15: May-15 | C15: 1047 | D15: 31604 | E15: 939 | J15: 29907 | K15: 13649 | L15: 17411 | M15: 775 | N15: 596 | O15: 74847 | P15: 1535 | Q15: 5 | R15: 30932 | S15: 238 | T15: 1608 | U15: 225088 | V15: 48447 | W15: 34670 | X15: 13137 | Y15: 15671 | Z15: 49557 | AA15: 22138 | AB15: 37743 | AE15: =actual1[[#This Row],[Revenue Expenditure]]-(SUM(actual1[[#This Row],[Corporation Tax]:[Other Taxes]])-actual1[[#This Row],[Surcharge for financing of NCCF]]-actual1[[#This Row],[Devolution to State]]+SUM(P15:R15)) -> 172727 | AF15: =AE15-actual1[[#This Row],[Grants for Creation of Capital Assets]] -> 150589 | AG15: =U15+AB15-(SUM(actual1[[#This Row],[Corporation Tax]:[Other Taxes]])-actual1[[#This Row],[Surcharge for financing of NCCF]]-actual1[[#This Row],[Devolution to State]]+SUM(P15:R15)+SUM(S15:T15)) -> 208624 | AH15: =AG15-actual1[[#This Row],[Interest Payments]] -> 160177
... A28: 2016-17 | B28: Jun-16 | C28: 54110 | D28: 69140 | E28: 1438 | J28: 55528 | K28: 60273 | L28: 39086 | M28: 1278 | N28: 1339 | O28: 122211 | P28: 1868 | Q28: 4221 | R28: 17395 | S28: 1743 | T28: 2979 | U28: 462836 | V28: 108802 | W28: 40230 | X28: 95327 | Y28: 27863 | Z28: 92287 | AA28: 53773 | AB28: 48996 | AE28: =actual1[[#This Row],[Revenue Expenditure]]-(SUM(actual1[[#This Row],[Corporation Tax]:[Other Taxes]])-actual1[[#This Row],[Surcharge for financing of NCCF]]-actual1[[#This Row],[Devolution to State]]+SUM(P28:R28)) -> 282049 | AF28: =AE28-actual1[[#This Row],[Grants for Creation of Capital Assets]] -> 228276 | AG28: =U28+AB28-(SUM(actual1[[#This Row],[Corporation Tax]:[Other Taxes]])-actual1[[#This Row],[Surcharge for financing of NCCF]]-actual1[[#This Row],[Devolution to State]]+SUM(P28:R28)+SUM(S28:T28)) -> 326323 | AH28: =AG28-actual1[[#This Row],[Interest Payments]] -> 217521
A29: 2016-17 | B29: Jul-16 | C29: 67061 | D29: 91834 | E29: 1952 | F29: 0 | G29: 0 | H29: 0 | I29: 0 | J29: 72153 | K29: 90328 | L29: 61195 | M29: 1916 | N29: 1822 | O29: 162949 | P29: 2866 | Q29: 4522 | R29: 26710 | S29: 4251 | T29: 3183 | U29: 585404 | V29: 140479 | W29: 52565 | X29: 119808 | Y29: 36867 | Z29: 105879 | AA29: 63211 | AB29: 71283 | AE29: =actual1[[#This Row],[Revenue Expenditure]]-(SUM(actual1[[#This Row],[Corporation Tax]:[Other Taxes]])-actual1[[#This Row],[Surcharge for financing of NCCF]]-actual1[[#This Row],[Devolution to State]]+SUM(P29:R29)) -> 329638 | AF29: =AE29-actual1[[#This Row],[Grants for Creation of Capital Assets]] -> 266427 | AG29: =U29+AB29-(SUM(actual1[[#This Row],[Corporation Tax]:[Other Taxes]])-actual1[[#This Row],[Surcharge for financing of NCCF]]-actual1[[#This Row],[Devolution to State]]+SUM(P29:R29)+SUM(S29:T29)) -> 393487 | AH29: =AG29-actual1[[#This Row],[Interest Payments]] -> 253008
A30: 2016-17 | B30: Aug-16 | C30: 80464 | D30: 109918 | E30: 2812 | F30: 0 | G30: 0 | H30: 0 | I30: 0 | J30: 90774 | K30: 120935 | L30: 79039 | M30: 2414 | N30: 2413 | O30: 203688 | P30: 3891 | Q30: 70678 | R30: 30499 | S30: 5335 | T30: 3183 | U30: 710329 | V30: 174472 | W30: 65949 | X30: 147192 | Y30: 48052 | Z30: 115219 | AA30: 70380 | AB30: 91332 | AE30: =actual1[[#This Row],[Revenue Expenditure]]-(SUM(actual1[[#This Row],[Corporation Tax]:[Other Taxes]])-actual1[[#This Row],[Surcharge for financing of NCCF]]-actual1[[#This Row],[Devolution to State]]+SUM(P30:R30)) -> 325006 | AF30: =AE30-actual1[[#This Row],[Grants for Creation of Capital Assets]] -> 254626 | AG30: =U30+AB30-(SUM(actual1[[#This Row],[Corporation Tax]:[Other Taxes]])-actual1[[#This Row],[Surcharge for financing of NCCF]]-actual1[[#This Row],[Devolution to State]]+SUM(P30:R30)+SUM(S30:T30)) -> 407820 | AH30: =AG30-actual1[[#This Row],[Interest Payments]] -> 233348
A31: 2016-17 | B31: Sep-16 | C31: 186789 | D31: 144233 | E31: 3607 | F31: 0 | G31: 0 | H31: 0 | I31: 0 | J31: 109087 | K31: 152347 | L31: 96673 | M31: 2957 | N31: 3111 | O31: 244427 | P31: 6223 | Q31: 79046 | R31: 33499 | S31: 6802 | T31: 6015 | U31: 892803 | V31: 213229 | W31: 78764 | X31: 188886 | Y31: 59643 | Z31: 142643 | AA31: 100762 | AB31: 134925 | AE31: =actual1[[#This Row],[Revenue Expenditure]]-(SUM(actual1[[#This Row],[Corporation Tax]:[Other Taxes]])-actual1[[#This Row],[Surcharge for financing of NCCF]]-actual1[[#This Row],[Devolution to State]]+SUM(P31:R31)) -> 325880 | AF31: =AE31-actual1[[#This Row],[Grants for Creation of Capital Assets]] -> 225118 | AG31: =U31+AB31-(SUM(actual1[[#This Row],[Corporation Tax]:[Other Taxes]])-actual1[[#This Row],[Surcharge for financing of NCCF]]-actual1[[#This Row],[Devolution to State]]+SUM(P31:R31)+SUM(S31:T31)) -> 447988 | AH31: =AG31-actual1[[#This Row],[Interest Payments]] -> 234759
A32: 2016-17 | B32: Oct-16 | C32: 207334 | D32: 169891 | E32: 4416 | F32: 0 | G32: 0 | H32: 0 | I32: 0 | J32: 127971 | K32: 180663 | L32: 124912 | M32: 3697 | N32: 3703 | O32: 285166 | P32: 7581 | Q32: 83225 | R32: 77167 | S32: 7938 | T32: 21410 | U32: 1025884 | V32: 226807 | W32: 99185 | X32: 207331 | Y32: 70097 | Z32: 192395 | AA32: 105256 | AB32: 124959 | AE32: =actual1[[#This Row],[Revenue Expenditure]]-(SUM(actual1[[#This Row],[Corporation Tax]:[Other Taxes]])-actual1[[#This Row],[Surcharge for financing of NCCF]]-actual1[[#This Row],[Devolution to State]]+SUM(P32:R32)) -> 327896 | AF32: =AE32-actual1[[#This Row],[Grants for Creation of Capital Assets]] -> 222640 | AG32: =U32+AB32-(SUM(actual1[[#This Row],[Corporation Tax]:[Other Taxes]])-actual1[[#This Row],[Surcharge for financing of NCCF]]-actual1[[#This Row],[Devolution to State]]+SUM(P32:R32)+SUM(S32:T32)) -> 423507 | AH32: =AG32-actual1[[#This Row],[Interest Payments]] -> 196700
A33: 2016-17 | B33: Nov-16 | C33: 222258 | D33: 186675 | E33: 5109 | F33: 0 | G33: 0 | H33: 0 | I33: 0 | J33: 148501 | K33: 213584 | L33: 146839 | M33: 10314 | N33: 4294 | O33: 307814 | P33: 9007 | Q33: 86460 | R33: 79484 | S33: 9033 | T33: 23529 | U33: 1144334 | V33: 266678 | W33: 111244 | X33: 221296 | Y33: 81111 | Z33: 197791 | AA33: 112921 | AB33: 142347 | AE33: =actual1[[#This Row],[Revenue Expenditure]]-(SUM(actual1[[#This Row],[Corporation Tax]:[Other Taxes]])-actual1[[#This Row],[Surcharge for financing of NCCF]]-actual1[[#This Row],[Devolution to State]]+SUM(P33:R33)) -> 348211 | AF33: =AE33-actual1[[#This Row],[Grants for Creation of Capital Assets]] -> 235290 | AG33: =U33+AB33-(SUM(actual1[[#This Row],[Corporation Tax]:[Other Taxes]])-actual1[[#This Row],[Surcharge for financing of NCCF]]-actual1[[#This Row],[Devolution to State]]+SUM(P33:R33)+SUM(S33:T33)) -> 457996 | AH33: =AG33-actual1[[#This Row],[Interest Payments]] -> 191318
A34: 2016-17 | B34: Dec-16 | C34: 320280 | D34: 224241 | E34: 5931 | F34: 0 | G34: 0 | H34: 0 | I34: 0 | J34: 167294 | K34: 246335 | L34: 163646 | M34: 11360 | N34: 4864 | O34: 382107 | P34: 10787 | Q34: 86908 | R34: 84755 | S34: 10403 | T34: 23529 | U34: 1288862 | V34: 325684 | W34: 126595 | X34: 251796 | Y34: 93394 | Z34: 214320 | AA34: 125523 | AB34: 180886 | AE34: =actual1[[#This Row],[Revenue Expenditure]]-(SUM(actual1[[#This Row],[Corporation Tax]:[Other Taxes]])-actual1[[#This Row],[Surcharge for financing of NCCF]]-actual1[[#This Row],[Devolution to State]]+SUM(P34:R34)) -> 354296 | AF34: =AE34-actual1[[#This Row],[Grants for Creation of Capital Assets]] -> 228773 | AG34: =U34+AB34-(SUM(actual1[[#This Row],[Corporation Tax]:[Other Taxes]])-actual1[[#This Row],[Surcharge for financing of NCCF]]-actual1[[#This Row],[Devolution to State]]+SUM(P34:R34)+SUM(S34:T34)) -> 501250 | AH34: =AG34-actual1[[#This Row],[Interest Payments]] -> 175566
A35: 2016-17 | B35: Jan-17 | C35: 327303 | D35: 245413 | E35: 6523 | F35: 0 | G35: 0 | H35: 0 | I35: 0 | J35: 186291 | K35: 278330 | L35: 188752 | M35: 12058 | N35: 5470 | O35: 422846 | P35: 12842 | Q35: 88325 | R35: 91873 | S35: 13057 | T35: 31014 | U35: 1414220 | V35: 368592 | W35: 140910 | X35: 275458 | Y35: 113148 | Z35: 216266 | AA35: 135063 | AB35: 203437 | AE35: =actual1[[#This Row],[Revenue Expenditure]]-(SUM(actual1[[#This Row],[Corporation Tax]:[Other Taxes]])-actual1[[#This Row],[Surcharge for financing of NCCF]]-actual1[[#This Row],[Devolution to State]]+SUM(P35:R35)) -> 404826 | AF35: =AE35-actual1[[#This Row],[Grants for Creation of Capital Assets]] -> 269763 | AG35: =U35+AB35-(SUM(actual1[[#This Row],[Corporation Tax]:[Other Taxes]])-actual1[[#This Row],[Surcharge for financing of NCCF]]-actual1[[#This Row],[Devolution to State]]+SUM(P35:R35)+SUM(S35:T35)) -> 564192 | AH35: =AG35-actual1[[#This Row],[Interest Payments]] -> 195600
A36: 2016-17 | B36: Feb-17 | C36: 343945 | D36: 268313 | E36: 7218 | F36: 0 | G36: 0 | H36: 0 | I36: 0 | J36: 203880 | K36: 312241 | L36: 206673 | M36: 12672 | N36: 6085 | O36: 463585 | P36: 13775 | Q36: 96957 | R36: 98179 | S36: 14180 | T36: 39043 | U36: 1538224 | V36: 403984 | W36: 154043 | X36: 295708 | Y36: 123174 | Z36: 226746 | AA36: 145377 | AB36: 214796 | AE36: =actual1[[#This Row],[Revenue Expenditure]]-(SUM(actual1[[#This Row],[Corporation Tax]:[Other Taxes]])-actual1[[#This Row],[Surcharge for financing of NCCF]]-actual1[[#This Row],[Devolution to State]]+SUM(P36:R36)) -> 444041 | AF36: =AE36-actual1[[#This Row],[Grants for Creation of Capital Assets]] -> 298664 | AG36: =U36+AB36-(SUM(actual1[[#This Row],[Corporation Tax]:[Other Taxes]])-actual1[[#This Row],[Surcharge for financing of NCCF]]-actual1[[#This Row],[Devolution to State]]+SUM(P36:R36)+SUM(S36:T36)) -> 605614 | AH36: =AG36-actual1[[#This Row],[Interest Payments]] -> 201630
A37: 2016-17 | B37: Mar-17 | C37: 484924 | D37: 340592 | E37: 8998 | F37: 0 | G37: 0 | H37: 0 | I37: 0 | J37: 225370 | K37: 380496 | L37: 254499 | M37: 20943 | N37: 6450 | O37: 608000 | P37: 16264 | Q37: 123021 | R37: 135299 | S37: 17770 | T37: 47743 | U37: 1692986 | V37: 480714 | W37: 165410 | X37: 285876 | Y37: 131401 | Z37: 206666 | AA37: 166560 | AB37: 286282 | AE37: =actual1[[#This Row],[Revenue Expenditure]]-(SUM(actual1[[#This Row],[Corporation Tax]:[Other Taxes]])-actual1[[#This Row],[Surcharge for financing of NCCF]]-actual1[[#This Row],[Devolution to State]]+SUM(P37:R37)) -> 317030 | AF37: =AE37-actual1[[#This Row],[Grants for Creation of Capital Assets]] -> 150470 | AG37: =U37+AB37-(SUM(actual1[[#This Row],[Corporation Tax]:[Other Taxes]])-actual1[[#This Row],[Surcharge for financing of NCCF]]-actual1[[#This Row],[Devolution to State]]+SUM(P37:R37)+SUM(S37:T37)) -> 537799 | AH37: =AG37-actual1[[#This Row],[Interest Payments]] -> 57085
A38: 2017-18 | B38: Apr-17 | C38: 6266 | D38: 33310 | E38: 410 | F38: 0 | G38: 0 | H38: 0 | I38: 0 | J38: 20574 | K38: 1323 | L38: 8901 | M38: 613 | N38: 187 | O38: 48178 | P38: 426 | Q38: 15 | R38: 11608 | S38: 255 | T38: 1193 | U38: 213464 | V38: 19422 | W38: 17828 | X38: 35733 | Y38: 17855 | Z38: 79480 | AA38: 24666 | AB38: 28687 | AE38: =actual1[[#This Row],[Revenue Expenditure]]-(SUM(actual1[[#This Row],[Corporation Tax]:[Other Taxes]])-actual1[[#This Row],[Surcharge for financing of NCCF]]-actual1[[#This Row],[Devolution to State]]+SUM(P38:R38)) -> 178383 | AF38: =AE38-actual1[[#This Row],[Grants for Creation of Capital Assets]] -> 153717 | AG38: =U38+AB38-(SUM(actual1[[#This Row],[Corporation Tax]:[Other Taxes]])-actual1[[#This Row],[Surcharge for financing of NCCF]]-actual1[[#This Row],[Devolution to State]]+SUM(P38:R38)+SUM(S38:T38)) -> 205622 | AH38: =AG38-actual1[[#This Row],[Interest Payments]] -> 186200
A39: 2017-18 | B39: May-17 | C39: 13482 | D39: 50275 | E39: 1189 | F39: 0 | G39: 0 | H39: 0 | I39: 0 | J39: 43058 | K39: 30778 | L39: 24958 | M39: 1093 | N39: 804 | O39: 96361 | P39: 696 | Q39: 16 | R39: 14632 | S39: 398 | T39: 2255 | U39: 406490 | V39: 69014 | W39: 39548 | X39: 63029 | Y39: 36027 | Z39: 117215 | AA39: 42805 | AB39: 52536 | AE39: =actual1[[#This Row],[Revenue Expenditure]]-(SUM(actual1[[#This Row],[Corporation Tax]:[Other Taxes]])-actual1[[#This Row],[Surcharge for financing of NCCF]]-actual1[[#This Row],[Devolution to State]]+SUM(P39:R39)) -> 323478 | AF39: =AE39-actual1[[#This Row],[Grants for Creation of Capital Assets]] -> 280673 | AG39: =U39+AB39-(SUM(actual1[[#This Row],[Corporation Tax]:[Other Taxes]])-actual1[[#This Row],[Surcharge for financing of NCCF]]-actual1[[#This Row],[Devolution to State]]+SUM(P39:R39)+SUM(S39:T39)) -> 373361 | AH39: =AG39-actual1[[#This Row],[Interest Payments]] -> 304347
A40: 2017-18 | B40: Jun-17 | C40: 67259 | D40: 76497 | E40: 2147 | F40: 0 | G40: 0 | H40: 0 | I40: 0 | J40: 63859 | K40: 64673 | L40: 47048 | M40: 1937 | N40: 1538 | O40: 144545 | P40: 1487 | Q40: 1297 | R40: 19181 | S40: 2054 | T40: 7690 | U40: 582403 | V40: 133410 | W40: 56447 | X40: 95816 | Y40: 48090 | Z40: 135450 | AA40: 55515 | AB40: 68328 | AE40: =actual1[[#This Row],[Revenue Expenditure]]-(SUM(actual1[[#This Row],[Corporation Tax]:[Other Taxes]])-actual1[[#This Row],[Surcharge for financing of NCCF]]-actual1[[#This Row],[Devolution to State]]+SUM(P40:R40)) -> 383101 | AF40: =AE40-actual1[[#This Row],[Grants for Creation of Capital Assets]] -> 327586 | AG40: =U40+AB40-(SUM(actual1[[#This Row],[Corporation Tax]:[Other Taxes]])-actual1[[#This Row],[Surcharge for financing of NCCF]]-actual1[[#This Row],[Devolution to State]]+SUM(P40:R40)+SUM(S40:T40)) -> 441685 | AH40: =AG40-actual1[[#This Row],[Interest Payments]] -> 308275
... A120: 2023-24 | B120: Feb-24 | C120: 752718 | D120: 812371 | E120: 29804 | F120: 747515 | G120: -43291 | H120: 4336 | I120: 128727 | J120: 196352 | K120: 253835 | L120: 467 | M120: 7017 | N120: 6966 | O120: 1033433 | P120: 34036 | Q120: 157070 | R120: 169224 | S120: 23480 | T120: 12660 | U120: 2941674 | V120: 880788 | W120: 269224 | X120: 465234 | Y120: 232075 | Z120: 360997 | AA120: 254355 | AB120: 805613 | AE120: =actual1[[#This Row],[Revenue Expenditure]]-(SUM(actual1[[#This Row],[Corporation Tax]:[Other Taxes]])-actual1[[#This Row],[Surcharge for financing of NCCF]]-actual1[[#This Row],[Devolution to State]]+SUM(P120:R120)) -> 731892 | AF120: =AE120-actual1[[#This Row],[Grants for Creation of Capital Assets]] -> 477537 | AG120: =U120+AB120-(SUM(actual1[[#This Row],[Corporation Tax]:[Other Taxes]])-actual1[[#This Row],[Surcharge for financing of NCCF]]-actual1[[#This Row],[Devolution to State]]+SUM(P120:R120)+SUM(S120:T120)) -> 1501365 | AH120: =AG120-actual1[[#This Row],[Interest Payments]] -> 620577
A121: 2023-24 | B121: Mar-24 | C121: 911055 | D121: 1010948 | E121: 33778 | F121: 820622 | G121: -4850 | H121: 5497 | I121: 141436 | J121: 233119 | K121: 305362 | L121: 425 | M121: =8096+31 -> 8127 | N121: 8774 | O121: 1129494 | P121: 38283 | Q121: 170891 | R121: 192611 | S121: 26646 | T121: 33122 | U121: 3494252 | V121: 1063872 | W121: 290443 | X121: 609677 | Y121: 238328 | Z121: 413542 | AA121: 303916 | AB121: 949195 | AE121: =actual1[[#This Row],[Revenue Expenditure]]-(SUM(actual1[[#This Row],[Corporation Tax]:[Other Taxes]])-actual1[[#This Row],[Surcharge for financing of NCCF]]-actual1[[#This Row],[Devolution to State]]+SUM(P121:R121)) -> 765216 | AF121: =AE121-actual1[[#This Row],[Grants for Creation of Capital Assets]] -> 461300 | AG121: =U121+AB121-(SUM(actual1[[#This Row],[Corporation Tax]:[Other Taxes]])-actual1[[#This Row],[Surcharge for financing of NCCF]]-actual1[[#This Row],[Devolution to State]]+SUM(P121:R121)+SUM(S121:T121)) -> 1654643 | AH121: =AG121-actual1[[#This Row],[Interest Payments]] -> 590771
A122: 2024-25 | B122: Apr-24 | C122: 36189 | D122: 98951 | E122: 3504 | F122: 91188 | G122: -2645 | H122: 292 | I122: 13042 | J122: 13956 | K122: 70 | L122: -97 | M122: 556 | N122: 133 | O122: 69875 | P122: 3531 | Q122: 3637 | R122: 20127 | S122: 1041 | T122: 0 | U122: 324235 | V122: 128263 | W122: 30524 | X122: 10480 | Y122: 36908 | Z122: 19407 | AA122: 18206 | AB122: 99235 | AE122: =actual1[[#This Row],[Revenue Expenditure]]-(SUM(actual1[[#This Row],[Corporation Tax]:[Other Taxes]])-actual1[[#This Row],[Surcharge for financing of NCCF]]-actual1[[#This Row],[Devolution to State]]+SUM(P122:R122)) -> 111942 | AF122: =AE122-actual1[[#This Row],[Grants for Creation of Capital Assets]] -> 93736 | AG122: =U122+AB122-(SUM(actual1[[#This Row],[Corporation Tax]:[Other Taxes]])-actual1[[#This Row],[Surcharge for financing of NCCF]]-actual1[[#This Row],[Devolution to State]]+SUM(P122:R122)+SUM(S122:T122)) -> 210136 | AH122: =AG122-actual1[[#This Row],[Interest Payments]] -> 81873
A123: 2024-25 | B123: May-24 | C123: 45313 | D123: 180291 | E123: 7235 | F123: 158841 | G123: -10883 | H123: 598 | I123: 24828 | J123: 28090 | K123: 24317 | L123: -87 | M123: 1086 | N123: 842 | O123: 139751 | P123: 7924 | Q123: 215829 | R123: 27969 | S123: 2083 | T123: 4 | U123: 479835 | V123: 123810 | W123: 53032 | X123: 37881 | Y123: 60607 | Z123: 54688 | AA123: 46235 | AB123: 143625 | AE123: =actual1[[#This Row],[Revenue Expenditure]]-(SUM(actual1[[#This Row],[Corporation Tax]:[Other Taxes]])-actual1[[#This Row],[Surcharge for financing of NCCF]]-actual1[[#This Row],[Devolution to State]]+SUM(P123:R123)) -> -90923 | AF123: =AE123-actual1[[#This Row],[Grants for Creation of Capital Assets]] -> -137158 | AG123: =U123+AB123-(SUM(actual1[[#This Row],[Corporation Tax]:[Other Taxes]])-actual1[[#This Row],[Surcharge for financing of NCCF]]-actual1[[#This Row],[Devolution to State]]+SUM(P123:R123)+SUM(S123:T123)) -> 50615 | AH123: =AG123-actual1[[#This Row],[Interest Payments]] -> -73195
A124: 2024-25 | B124: Jun-24 | C124: 174774 | D124: 287336 | E124: 11606 | F124: 228328 | G124: -10176 | H124: 877 | I124: 37768 | J124: 47065 | K124: 51357 | L124: -38 | M124: 1900 | N124: 1662 | O124: 279502 | P124: 11715 | Q124: 224325 | R124: 44004 | S124: 4516 | T124: 4 | U124: 788858 | V124: 264052 | W124: 73712 | X124: 63299 | Y124: 82097 | Z124: 90174 | AA124: 58961 | AB124: 181051 | AE124: =actual1[[#This Row],[Revenue Expenditure]]-(SUM(actual1[[#This Row],[Corporation Tax]:[Other Taxes]])-actual1[[#This Row],[Surcharge for financing of NCCF]]-actual1[[#This Row],[Devolution to State]]+SUM(P124:R124)) -> -40819 | AF124: =AE124-actual1[[#This Row],[Grants for Creation of Capital Assets]] -> -99780 | AG124: =U124+AB124-(SUM(actual1[[#This Row],[Corporation Tax]:[Other Taxes]])-actual1[[#This Row],[Surcharge for financing of NCCF]]-actual1[[#This Row],[Devolution to State]]+SUM(P124:R124)+SUM(S124:T124)) -> 135712 | AH124: =AG124-actual1[[#This Row],[Interest Payments]] -> -128340
A125: 2024-25 | B125: Jul-24 | C125: 184574 | D125: 394488 | E125: 16635 | F125: 300616 | G125: -10659 | H125: 934 | I125: 50547 | J125: 67522 | K125: 76812 | L125: 13 | M125: 2747 | N125: 2375 | O125: 366630 | P125: 13840 | Q125: 228823 | R125: 59133 | S125: 6381 | T125: 5 | U125: 1039091 | V125: 327887 | W125: 98753 | X125: 91422 | Y125: 102506 | Z125: 125639 | AA125: 84957 | AB125: 261260 | AE125: =actual1[[#This Row],[Revenue Expenditure]]-(SUM(actual1[[#This Row],[Corporation Tax]:[Other Taxes]])-actual1[[#This Row],[Surcharge for financing of NCCF]]-actual1[[#This Row],[Devolution to State]]+SUM(P125:R125)) -> 22071 | AF125: =AE125-actual1[[#This Row],[Grants for Creation of Capital Assets]] -> -62886 | AG125: =U125+AB125-(SUM(actual1[[#This Row],[Corporation Tax]:[Other Taxes]])-actual1[[#This Row],[Surcharge for financing of NCCF]]-actual1[[#This Row],[Devolution to State]]+SUM(P125:R125)+SUM(S125:T125)) -> 276945 | AH125: =AG125-actual1[[#This Row],[Interest Payments]] -> -50942
A126: 2024-25 | B126: Aug-24 | C126: 224639 | D126: 452286 | E126: 21607 | F126: 371222 | G126: -2446 | H126: 1286 | I126: 62462 | J126: 94329 | K126: 104006 | L126: 32 | M126: 3299 | N126: 3160 | O126: 455717 | P126: 17530 | Q126: 239695 | R126: 77242 | S126: 8046 | T126: 820 | U126: 1351367 | V126: 400160 | W126: 120192 | X126: 182174 | Y126: 126598 | Z126: 178625 | AA126: 111066 | AB126: 300987 | AE126: =actual1[[#This Row],[Revenue Expenditure]]-(SUM(actual1[[#This Row],[Corporation Tax]:[Other Taxes]])-actual1[[#This Row],[Surcharge for financing of NCCF]]-actual1[[#This Row],[Devolution to State]]+SUM(P126:R126)) -> 143055 | AF126: =AE126-actual1[[#This Row],[Grants for Creation of Capital Assets]] -> 31989 | AG126: =U126+AB126-(SUM(actual1[[#This Row],[Corporation Tax]:[Other Taxes]])-actual1[[#This Row],[Surcharge for financing of NCCF]]-actual1[[#This Row],[Devolution to State]]+SUM(P126:R126)+SUM(S126:T126)) -> 435176 | AH126: =AG126-actual1[[#This Row],[Interest Payments]] -> 35016
A127: 2024-25 | B127: Sep-24 | C127: 461506 | D127: 564517 | E127: 26156 | F127: 441220 | G127: -846 | H127: 1624 | I127: 74323 | J127: 112959 | K127: 128466 | L127: 94 | M127: 3823 | N127: 3880 | O127: 544803 | P127: 20355 | Q127: 250633 | R127: 86226 | S127: 11434 | T127: 3167 | U127: 1696528 | V127: 515010 | W127: 145181 | X127: 239296 | Y127: 148989 | Z127: 214658 | AA127: 145208 | AB127: 414966 | AE127: =actual1[[#This Row],[Revenue Expenditure]]-(SUM(actual1[[#This Row],[Corporation Tax]:[Other Taxes]])-actual1[[#This Row],[Surcharge for financing of NCCF]]-actual1[[#This Row],[Devolution to State]]+SUM(P127:R127)) -> 74155 | AF127: =AE127-actual1[[#This Row],[Grants for Creation of Capital Assets]] -> -71053 | AG127: =U127+AB127-(SUM(actual1[[#This Row],[Corporation Tax]:[Other Taxes]])-actual1[[#This Row],[Surcharge for financing of NCCF]]-actual1[[#This Row],[Devolution to State]]+SUM(P127:R127)+SUM(S127:T127)) -> 474520 | AH127: =AG127-actual1[[#This Row],[Interest Payments]] -> -40490
A128: 2024-25 | B128: Oct-24 | C128: 487862 | D128: 626454 | E128: 30687 | F128: 521599 | G128: -10448 | H128: 1947 | I128: 86482 | J128: 132112 | K128: 151190 | L128: 87 | M128: 4662 | N128: 4685 | O128: 722976 | P128: 22701 | Q128: 264278 | R128: 112315 | S128: 13275 | T128: 5532 | U128: 2007353 | V128: 596347 | W128: 170571 | X128: 286362 | Y128: 170215 | Z128: 248670 | AA128: 163690 | AB128: 466545 | AE128: =actual1[[#This Row],[Revenue Expenditure]]-(SUM(actual1[[#This Row],[Corporation Tax]:[Other Taxes]])-actual1[[#This Row],[Surcharge for financing of NCCF]]-actual1[[#This Row],[Devolution to State]]+SUM(P128:R128)) -> 303086 | AF128: =AE128-actual1[[#This Row],[Grants for Creation of Capital Assets]] -> 139396 | AG128: =U128+AB128-(SUM(actual1[[#This Row],[Corporation Tax]:[Other Taxes]])-actual1[[#This Row],[Surcharge for financing of NCCF]]-actual1[[#This Row],[Devolution to State]]+SUM(P128:R128)+SUM(S128:T128)) -> 750824 | AH128: =AG128-actual1[[#This Row],[Interest Payments]] -> 154477
A129: 2024-25 | B129: Nov-24 | C129: 511636 | D129: 700775 | E129: 35932 | F129: 603873 | G129: -27854 | H129: 2427 | I129: 99598 | J129: 154142 | K129: 175100 | L129: 96 | M129: 5250 | N129: 5477 | O129: 812063 | P129: 26842 | Q129: 279061 | R129: 121117 | S129: 14972 | T129: 8981 | U129: 2227502 | V129: 658494 | W129: 194107 | X129: 306087 | Y129: 193346 | Z129: 279211 | AA129: 178614 | AB129: 513500 | AE129: =actual1[[#This Row],[Revenue Expenditure]]-(SUM(actual1[[#This Row],[Corporation Tax]:[Other Taxes]])-actual1[[#This Row],[Surcharge for financing of NCCF]]-actual1[[#This Row],[Devolution to State]]+SUM(P129:R129)) -> 357047 | AF129: =AE129-actual1[[#This Row],[Grants for Creation of Capital Assets]] -> 178433 | AG129: =U129+AB129-(SUM(actual1[[#This Row],[Corporation Tax]:[Other Taxes]])-actual1[[#This Row],[Surcharge for financing of NCCF]]-actual1[[#This Row],[Devolution to State]]+SUM(P129:R129)+SUM(S129:T129)) -> 846594 | AH129: =AG129-actual1[[#This Row],[Interest Payments]] -> 188100
A130: 2024-25 | B130: Dec-24 | C130: 740926 | D130: 837817 | E130: 40136 | F130: 673256 | G130: -31590 | H130: 2696 | I130: 111556 | J130: 170175 | K130: 199630 | L130: 36 | M130: 5790 | N130: 6225 | O130: 901150 | P130: 29903 | Q130: 284772 | R130: 132982 | S130: 18301 | T130: 8994 | U130: 2546757 | V130: 808313 | W130: 215520 | X130: 348245 | Y130: 215263 | Z130: 306994 | AA130: 199530 | AB130: 685337 | AE130: =actual1[[#This Row],[Revenue Expenditure]]-(SUM(actual1[[#This Row],[Corporation Tax]:[Other Taxes]])-actual1[[#This Row],[Surcharge for financing of NCCF]]-actual1[[#This Row],[Devolution to State]]+SUM(P130:R130)) -> 256047 | AF130: =AE130-actual1[[#This Row],[Grants for Creation of Capital Assets]] -> 56517 | AG130: =U130+AB130-(SUM(actual1[[#This Row],[Corporation Tax]:[Other Taxes]])-actual1[[#This Row],[Surcharge for financing of NCCF]]-actual1[[#This Row],[Devolution to State]]+SUM(P130:R130)+SUM(S130:T130)) -> 914089 | AH130: =AG130-actual1[[#This Row],[Interest Payments]] -> 105776
A131: 2024-25 | B131: Jan-25 | C131: 751319 | D131: 912792 | E131: 44541 | F131: 752514 | G131: -27610 | H131: 3560 | I131: 124971 | J131: 190176 | K131: 225902 | L131: 7 | M131: =6176+8 -> 6184 | N131: 6619 | O131: 1074179 | P131: 32162 | Q131: 285868 | R131: 149600 | S131: 20205 | T131: 9019 | U131: 2812595 | V131: 875461 | W131: 242924 | X131: 410867 | Y131: 237358 | Z131: 337733 | AA131: 218396 | AB131: 757359 | AE131: =actual1[[#This Row],[Revenue Expenditure]]-(SUM(actual1[[#This Row],[Corporation Tax]:[Other Taxes]])-actual1[[#This Row],[Surcharge for financing of NCCF]]-actual1[[#This Row],[Devolution to State]]+SUM(P131:R131)) -> 441407 | AF131: =AE131-actual1[[#This Row],[Grants for Creation of Capital Assets]] -> 223011 | AG131: =U131+AB131-(SUM(actual1[[#This Row],[Corporation Tax]:[Other Taxes]])-actual1[[#This Row],[Surcharge for financing of NCCF]]-actual1[[#This Row],[Devolution to State]]+SUM(P131:R131)+SUM(S131:T131)) -> 1169542 | AH131: =AG131-actual1[[#This Row],[Interest Payments]] -> 294081
A132: 2024-25 | B132: Feb-25 | C132: 767153 | D132: 991489 | E132: 49227 | F132: 830137 | G132: -37608 | H132: 3864 | I132: 138327 | J132: 204612 | K132: 250194 | L132: 9 | M132: =6813+9 -> 6822 | N132: 8060 | O132: 1180532 | P132: 35204 | Q132: 300086 | R132: 158029 | S132: 21655 | T132: 15709 | U132: 3081282 | V132: 952844 | W132: 268468 | X132: 444432 | Y132: 261414 | Z132: 363005 | AA132: 233921 | AB132: 811887 | AE132: =actual1[[#This Row],[Revenue Expenditure]]-(SUM(actual1[[#This Row],[Corporation Tax]:[Other Taxes]])-actual1[[#This Row],[Surcharge for financing of NCCF]]-actual1[[#This Row],[Devolution to State]]+SUM(P132:R132)) -> 572329 | AF132: =AE132-actual1[[#This Row],[Grants for Creation of Capital Assets]] -> 338408 | AG132: =U132+AB132-(SUM(actual1[[#This Row],[Corporation Tax]:[Other Taxes]])-actual1[[#This Row],[Surcharge for financing of NCCF]]-actual1[[#This Row],[Devolution to State]]+SUM(P132:R132)+SUM(S132:T132)) -> 1346852 | AH132: =AG132-actual1[[#This Row],[Interest Payments]] -> 394008
A133: 2024-25 | B133: Mar-25 | C133: 986767 | D133: 1182964 | E133: 52197 | F133: 908980 | G133: -32995 | H133: 5094 | I133: 150506 | J133: 232896 | K133: 300253 | L133: -16 | M133: =8570+9 -> 8579 | N133: 9455 | O133: 1286885 | P133: 41223 | Q133: 308423 | R133: 187898 | S133: 24616 | T133: 17202 | U133: 3603510 | V133: 1116343 | W133: 290769 | X133: 589239 | Y133: 273772 | Z133: 388036 | AA133: 272775 | AB133: 1052007 | AE133: =actual1[[#This Row],[Revenue Expenditure]]-(SUM(actual1[[#This Row],[Corporation Tax]:[Other Taxes]])-actual1[[#This Row],[Surcharge for financing of NCCF]]-actual1[[#This Row],[Devolution to State]]+SUM(P133:R133)) -> 567081 | AF133: =AE133-actual1[[#This Row],[Grants for Creation of Capital Assets]] -> 294306 | AG133: =U133+AB133-(SUM(actual1[[#This Row],[Corporation Tax]:[Other Taxes]])-actual1[[#This Row],[Surcharge for financing of NCCF]]-actual1[[#This Row],[Devolution to State]]+SUM(P133:R133)+SUM(S133:T133)) -> 1577270 | AH133: =AG133-actual1[[#This Row],[Interest Payments]] -> 460927
A134: 2025-26 | B134: Apr-25 | C134: 21461 | D134: 109626 | E134: 3786 | F134: 78240 | G134: 31097 | H134: 119 | I134: 12696 | J134: 13934 | K134: -39 | L134: -39 | M134: =2+595 -> 597 | N134: 74 | O134: 81735 | P134: 1433 | Q134: 1916 | R134: 63811 | S134: 1048 | T134: 21411 | U134: 305830 | V134: 93460 | W134: 32918 | X134: 15213 | Y134: 38704 | Z134: 28955 | AA134: 18578 | AB134: 159790 | AE134: =actual1[[#This Row],[Revenue Expenditure]]-(SUM(actual1[[#This Row],[Corporation Tax]:[Other Taxes]])-actual1[[#This Row],[Surcharge for financing of NCCF]]-actual1[[#This Row],[Devolution to State]]+SUM(P134:R134)) -> 49001 | AF134: =AE134-actual1[[#This Row],[Grants for Creation of Capital Assets]] -> 30423 | AG134: =U134+AB134-(SUM(actual1[[#This Row],[Corporation Tax]:[Other Taxes]])-actual1[[#This Row],[Surcharge for financing of NCCF]]-actual1[[#This Row],[Devolution to State]]+SUM(P134:R134)+SUM(S134:T134)) -> 186332 | AH134: =AG134-actual1[[#This Row],[Interest Payments]] -> 92872
A135: 2025-26 | B135: May-25 | C135: 44961 | D135: 191816 | E135: 8086 | F135: 154984 | G135: 33430 | H135: 491 | I135: 25006 | J135: 29254 | K135: 26399 | L135: -168 | M135: =968+4 -> 972 | N135: 898 | O135: 163471 | P135: 6634 | Q135: 278702 | R135: 71541 | S135: 2606 | T135: 22618 | U135: 524772 | V135: 147788 | W135: 60306 | X135: 33217 | Y135: 62361 | Z135: 51253 | AA135: 39084 | AB135: 221354 | AE135: =actual1[[#This Row],[Revenue Expenditure]]-(SUM(actual1[[#This Row],[Corporation Tax]:[Other Taxes]])-actual1[[#This Row],[Surcharge for financing of NCCF]]-actual1[[#This Row],[Devolution to State]]+SUM(P135:R135)) -> -182967 | AF135: =AE135-actual1[[#This Row],[Grants for Creation of Capital Assets]] -> -222051 | AG135: =U135+AB135-(SUM(actual1[[#This Row],[Corporation Tax]:[Other Taxes]])-actual1[[#This Row],[Surcharge for financing of NCCF]]-actual1[[#This Row],[Devolution to State]]+SUM(P135:R135)+SUM(S135:T135)) -> 13163 | AH135: =AG135-actual1[[#This Row],[Interest Payments]] -> -134625
A136: 2025-26 | B136: Jun-25 | C136: 172749 | D136: 285829 | E136: 13015 | F136: 231723 | G136: 27312 | H136: 779 | I136: 38325 | J136: 42414 | K136: 55605 | L136: -152 | M136: =1406+4 -> 1410 | N136: 1752 | O136: 326941 | P136: 9704 | Q136: 281745 | R136: 81612 | S136: 5395 | T136: 22623 | U136: 946995 | V136: 386037 | W136: 84495 | X136: 72283 | Y136: 84899 | Z136: 83554 | AA136: 75392 | AB136: 275132 | AE136: =actual1[[#This Row],[Revenue Expenditure]]-(SUM(actual1[[#This Row],[Corporation Tax]:[Other Taxes]])-actual1[[#This Row],[Surcharge for financing of NCCF]]-actual1[[#This Row],[Devolution to State]]+SUM(P136:R136)) -> 33618 | AF136: =AE136-actual1[[#This Row],[Grants for Creation of Capital Assets]] -> -41774 | AG136: =U136+AB136-(SUM(actual1[[#This Row],[Corporation Tax]:[Other Taxes]])-actual1[[#This Row],[Surcharge for financing of NCCF]]-actual1[[#This Row],[Devolution to State]]+SUM(P136:R136)+SUM(S136:T136)) -> 280732 | AH136: =AG136-actual1[[#This Row],[Interest Payments]] -> -105305
A137: 2025-26 | B137: Jul-25 | C137: 198589 | D137: 355315 | E137: 17882 | F137: 311625 | G137: 11907 | H137: 1115 | I137: 50305 | J137: 60530 | K137: 83963 | L137: -168 | M137: =1842+5 -> 1847 | N137: 2554 | O137: 428544 | P137: 11792 | Q137: 293621 | R137: 98195 | S137: 7138 | T137: 22651 | U137: 1216699 | V137: 446690 | W137: 111673 | X137: 105927 | Y137: 108610 | Z137: 113592 | AA137: 99250 | AB137: 346926 | AE137: =actual1[[#This Row],[Revenue Expenditure]]-(SUM(actual1[[#This Row],[Corporation Tax]:[Other Taxes]])-actual1[[#This Row],[Surcharge for financing of NCCF]]-actual1[[#This Row],[Devolution to State]]+SUM(P137:R137)) -> 151279 | AF137: =AE137-actual1[[#This Row],[Grants for Creation of Capital Assets]] -> 52029 | AG137: =U137+AB137-(SUM(actual1[[#This Row],[Corporation Tax]:[Other Taxes]])-actual1[[#This Row],[Surcharge for financing of NCCF]]-actual1[[#This Row],[Devolution to State]]+SUM(P137:R137)+SUM(S137:T137)) -> 468416 | AH137: =AG137-actual1[[#This Row],[Interest Payments]] -> 21726
A138: 2025-26 | B138: Aug-25 | C138: 229295 | D138: 441013 | E138: 22379 | F138: 390502 | G138: 370 | H138: 1487 | I138: 61960 | J138: 83062 | K138: 111927 | L138: -241 | M138: =2203+6 -> 2209 | N138: 3408 | O138: 530148 | P138: 14776 | Q138: 308769 | R138: 116787 | S138: 8553 | T138: 23417 | U138: 1449283 | V138: 528668 | W138: 134274 | X138: 125106 | Y138: 132876 | Z138: 150377 | AA138: 110636 | AB138: 431579 | AE138: =actual1[[#This Row],[Revenue Expenditure]]-(SUM(actual1[[#This Row],[Corporation Tax]:[Other Taxes]])-actual1[[#This Row],[Surcharge for financing of NCCF]]-actual1[[#This Row],[Devolution to State]]+SUM(P138:R138)) -> 198544 | AF138: =AE138-actual1[[#This Row],[Grants for Creation of Capital Assets]] -> 87908 | AG138: =U138+AB138-(SUM(actual1[[#This Row],[Corporation Tax]:[Other Taxes]])-actual1[[#This Row],[Surcharge for financing of NCCF]]-actual1[[#This Row],[Devolution to State]]+SUM(P138:R138)+SUM(S138:T138)) -> 598153 | AH138: =AG138-actual1[[#This Row],[Interest Payments]] -> 69485
A139: 2025-26 | B139: Sep-25 | C139: 466634 | D139: 591014 | E139: 26309 | F139: 466736 | G139: -8838 | H139: 2016 | I139: 73172 | J139: 107100 | K139: 138918 | L139: -269 | M139: =2554+8 -> 2562 | N139: 4233 | O139: 631751 | P139: 18015 | Q139: 321512 | R139: 126549 | S139: 11353 | T139: 23417 | U139: 1722593 | V139: 578182 | W139: 158443 | X139: 160125 | Y139: 155362 | Z139: 202367 | AA139: 129914 | AB139: 580746 | AE139: =actual1[[#This Row],[Revenue Expenditure]]-(SUM(actual1[[#This Row],[Corporation Tax]:[Other Taxes]])-actual1[[#This Row],[Surcharge for financing of NCCF]]-actual1[[#This Row],[Devolution to State]]+SUM(P139:R139)) -> 27147 | AF139: =AE139-actual1[[#This Row],[Grants for Creation of Capital Assets]] -> -102767 | AG139: =U139+AB139-(SUM(actual1[[#This Row],[Corporation Tax]:[Other Taxes]])-actual1[[#This Row],[Surcharge for financing of NCCF]]-actual1[[#This Row],[Devolution to State]]+SUM(P139:R139)+SUM(S139:T139)) -> 573123 | AH139: =AG139-actual1[[#This Row],[Interest Payments]] -> -5059
A140: 2025-26 | B140: Oct-25 | C140: 513137 | D140: 669631 | E140: 30935 | F140: 553607 | G140: -29806 | H140: 2538 | I140: 80503 | J140: 128821 | K140: 163206 | L140: -1137 | M140: =2947+8 -> 2955 | N140: 5132 | O140: 834957 | P140: 20642 | Q140: 324197 | R140: 144240 | S140: 13392 | T140: 23703 | U140: 2007876 | V140: 673715 | W140: 184998 | X140: 189798 | Y140: 179522 | Z140: 246575 | AA140: 146949 | AB140: 617743 | AE140: =actual1[[#This Row],[Revenue Expenditure]]-(SUM(actual1[[#This Row],[Corporation Tax]:[Other Taxes]])-actual1[[#This Row],[Surcharge for financing of NCCF]]-actual1[[#This Row],[Devolution to State]]+SUM(P140:R140)) -> 244496 | AF140: =AE140-actual1[[#This Row],[Grants for Creation of Capital Assets]] -> 97547 | AG140: =U140+AB140-(SUM(actual1[[#This Row],[Corporation Tax]:[Other Taxes]])-actual1[[#This Row],[Surcharge for financing of NCCF]]-actual1[[#This Row],[Devolution to State]]+SUM(P140:R140)+SUM(S140:T140)) -> 825144 | AH140: =AG140-actual1[[#This Row],[Interest Payments]] -> 151429
A141: 2025-26 | B141: Nov-25 | C141: 551468 | D141: 748299 | E141: 35718 | F141: 636473 | G141: -60520 | H141: 4235 | I141: 84404 | J141: 142864 | K141: 191297 | L141: -1157 | M141: =3341+8 -> 3349 | N141: 5923 | O141: 936561 | P141: 24531 | Q141: 339542 | R141: 152293 | S141: 15210 | T141: 23717 | U141: 2267700 | V141: 745765 | W141: 204786 | X141: 218703 | Y141: 202207 | Z141: 288333 | AA141: 161353 | AB141: 658210 | AE141: =actual1[[#This Row],[Revenue Expenditure]]-(SUM(actual1[[#This Row],[Corporation Tax]:[Other Taxes]])-actual1[[#This Row],[Surcharge for financing of NCCF]]-actual1[[#This Row],[Devolution to State]]+SUM(P141:R141)) -> 357388 | AF141: =AE141-actual1[[#This Row],[Grants for Creation of Capital Assets]] -> 196035 | AG141: =U141+AB141-(SUM(actual1[[#This Row],[Corporation Tax]:[Other Taxes]])-actual1[[#This Row],[Surcharge for financing of NCCF]]-actual1[[#This Row],[Devolution to State]]+SUM(P141:R141)+SUM(S141:T141)) -> 976671 | AH141: =AG141-actual1[[#This Row],[Interest Payments]] -> 230906
A142: 2025-26 | B142: Dec-25 | C142: 832766 | D142: 872696 | E142: 40220 | F142: 710615 | G142: 15641 | H142: 4698 | I142: 89777 | J142: 195719 | K142: 219410 | L142: -1186 | M142: =3902+9 -> 3911 | N142: 6849 | O142: 1038164 | P142: 27976 | Q142: 350269 | R142: 161610 | S142: 18226 | T142: 27821 | U142: 2593063 | V142: 911059 | W142: 233023 | X142: 247273 | Y142: 226030 | Z142: 317490 | AA142: 177599 | AB142: 787935 | AE142: =actual1[[#This Row],[Revenue Expenditure]]-(SUM(actual1[[#This Row],[Corporation Tax]:[Other Taxes]])-actual1[[#This Row],[Surcharge for financing of NCCF]]-actual1[[#This Row],[Devolution to State]]+SUM(P142:R142)) -> 113954 | AF142: =AE142-actual1[[#This Row],[Grants for Creation of Capital Assets]] -> -63645 | AG142: =U142+AB142-(SUM(actual1[[#This Row],[Corporation Tax]:[Other Taxes]])-actual1[[#This Row],[Surcharge for financing of NCCF]]-actual1[[#This Row],[Devolution to State]]+SUM(P142:R142)+SUM(S142:T142)) -> 855842 | AH142: =AG142-actual1[[#This Row],[Interest Payments]] -> -55217
AE143: =actual1[[#This Row],[Revenue Expenditure]]-(SUM(actual1[[#This Row],[Corporation Tax]:[Other Taxes]])-actual1[[#This Row],[Surcharge for financing of NCCF]]-actual1[[#This Row],[Devolution to State]]+SUM(P143:R143)) -> 0 | AF143: =AE143-actual1[[#This Row],[Grants for Creation of Capital Assets]] -> 0 | AG143: =U143+AB143-(SUM(actual1[[#This Row],[Corporation Tax]:[Other Taxes]])-actual1[[#This Row],[Surcharge for financing of NCCF]]-actual1[[#This Row],[Devolution to State]]+SUM(P143:R143)+SUM(S143:T143)) -> 0 | AH143: =AG143-actual1[[#This Row],[Interest Payments]] -> 0
AE144: =actual1[[#This Row],[Revenue Expenditure]]-(SUM(actual1[[#This Row],[Corporation Tax]:[Other Taxes]])-actual1[[#This Row],[Surcharge for financing of NCCF]]-actual1[[#This Row],[Devolution to State]]+SUM(P144:R144)) -> 0 | AF144: =AE144-actual1[[#This Row],[Grants for Creation of Capital Assets]] -> 0 | AG144: =U144+AB144-(SUM(actual1[[#This Row],[Corporation Tax]:[Other Taxes]])-actual1[[#This Row],[Surcharge for financing of NCCF]]-actual1[[#This Row],[Devolution to State]]+SUM(P144:R144)+SUM(S144:T144)) -> 0 | AH144: =AG144-actual1[[#This Row],[Interest Payments]] -> 0
AE145: =actual1[[#This Row],[Revenue Expenditure]]-(SUM(actual1[[#This Row],[Corporation Tax]:[Other Taxes]])-actual1[[#This Row],[Surcharge for financing of NCCF]]-actual1[[#This Row],[Devolution to State]]+SUM(P145:R145)) -> 0 | AF145: =AE145-actual1[[#This Row],[Grants for Creation of Capital Assets]] -> 0 | AG145: =U145+AB145-(SUM(actual1[[#This Row],[Corporation Tax]:[Other Taxes]])-actual1[[#This Row],[Surcharge for financing of NCCF]]-actual1[[#This Row],[Devolution to State]]+SUM(P145:R145)+SUM(S145:T145)) -> 0 | AH145: =AG145-actual1[[#This Row],[Interest Payments]] -> 0
AE146: =actual1[[#This Row],[Revenue Expenditure]]-(SUM(actual1[[#This Row],[Corporation Tax]:[Other Taxes]])-actual1[[#This Row],[Surcharge for financing of NCCF]]-actual1[[#This Row],[Devolution to State]]+SUM(P146:R146)) -> 0 | AF146: =AE146-actual1[[#This Row],[Grants for Creation of Capital Assets]] -> 0 | AG146: =U146+AB146-(SUM(actual1[[#This Row],[Corporation Tax]:[Other Taxes]])-actual1[[#This Row],[Surcharge for financing of NCCF]]-actual1[[#This Row],[Devolution to State]]+SUM(P146:R146)+SUM(S146:T146)) -> 0 | AH146: =AG146-actual1[[#This Row],[Interest Payments]] -> 0
AE147: =actual1[[#This Row],[Revenue Expenditure]]-(SUM(actual1[[#This Row],[Corporation Tax]:[Other Taxes]])-actual1[[#This Row],[Surcharge for financing of NCCF]]-actual1[[#This Row],[Devolution to State]]+SUM(P147:R147)) -> 0 | AF147: =AE147-actual1[[#This Row],[Grants for Creation of Capital Assets]] -> 0 | AG147: =U147+AB147-(SUM(actual1[[#This Row],[Corporation Tax]:[Other Taxes]])-actual1[[#This Row],[Surcharge for financing of NCCF]]-actual1[[#This Row],[Devolution to State]]+SUM(P147:R147)+SUM(S147:T147)) -> 0 | AH147: =AG147-actual1[[#This Row],[Interest Payments]] -> 0
AE148: =actual1[[#This Row],[Revenue Expenditure]]-(SUM(actual1[[#This Row],[Corporation Tax]:[Other Taxes]])-actual1[[#This Row],[Surcharge for financing of NCCF]]-actual1[[#This Row],[Devolution to State]]+SUM(P148:R148)) -> 0 | AF148: =AE148-actual1[[#This Row],[Grants for Creation of Capital Assets]] -> 0 | AG148: =U148+AB148-(SUM(actual1[[#This Row],[Corporation Tax]:[Other Taxes]])-actual1[[#This Row],[Surcharge for financing of NCCF]]-actual1[[#This Row],[Devolution to State]]+SUM(P148:R148)+SUM(S148:T148)) -> 0 | AH148: =AG148-actual1[[#This Row],[Interest Payments]] -> 0
AE149: =actual1[[#This Row],[Revenue Expenditure]]-(SUM(actual1[[#This Row],[Corporation Tax]:[Other Taxes]])-actual1[[#This Row],[Surcharge for financing of NCCF]]-actual1[[#This Row],[Devolution to State]]+SUM(P149:R149)) -> 0 | AF149: =AE149-actual1[[#This Row],[Grants for Creation of Capital Assets]] -> 0 | AG149: =U149+AB149-(SUM(actual1[[#This Row],[Corporation Tax]:[Other Taxes]])-actual1[[#This Row],[Surcharge for financing of NCCF]]-actual1[[#This Row],[Devolution to State]]+SUM(P149:R149)+SUM(S149:T149)) -> 0 | AH149: =AG149-actual1[[#This Row],[Interest Payments]] -> 0
AE150: =actual1[[#This Row],[Revenue Expenditure]]-(SUM(actual1[[#This Row],[Corporation Tax]:[Other Taxes]])-actual1[[#This Row],[Surcharge for financing of NCCF]]-actual1[[#This Row],[Devolution to State]]+SUM(P150:R150)) -> 0 | AF150: =AE150-actual1[[#This Row],[Grants for Creation of Capital Assets]] -> 0 | AG150: =U150+AB150-(SUM(actual1[[#This Row],[Corporation Tax]:[Other Taxes]])-actual1[[#This Row],[Surcharge for financing of NCCF]]-actual1[[#This Row],[Devolution to State]]+SUM(P150:R150)+SUM(S150:T150)) -> 0 | AH150: =AG150-actual1[[#This Row],[Interest Payments]] -> 0

Sheet BERE
A1: FY | B1: Month | C1: Corporation Tax | D1: Income Tax | E1: Securities Transcation Tax | F1: CGST | G1: IGST | H1: UTGST | I1: Compensation Cess | J1: Customs | K1: Union Excise | L1: Service Tax | M1: Other Taxes | N1: Surcharge for financing of NCCF | O1: Devolution to State | P1: Interest receipts | Q1: Dividends and Profits | R1: Other Non Tax Receipts | S1: Recovery of Loans & Advances | T1: Disinvestment Receipts | U1: Revenue Expenditure | V1: Interest Payments | W1: Defence Services | X1: Grants in Aid to States & UTs | Y1: Pensions | Z1: Major Subsidies | AA1: Grants for Creation of Capital Assets | AB1: Capital Expenditure | AG1: Other Non-Debt Capital Receipts
A2: 2014-15 | B2: BE | C2: 451005 | D2: 278275 | E2: 5991 | J2: 201819 | K2: 207110 | L2: 215973 | M2: 4351 | N2: 5050 | O2: 382216 | P2: 19751 | Q2: 90229 | R2: 102525 | S2: 10527 | T2: 63425 | U2: 1568111 | V2: 427011 | W2: 229000 | X2: 70019 | Y2: 81983 | Z2: 251397 | AA2: 168104 | AB2: 226781
A3: 2014-15 | B3: RE | C3: 426079 | D3: 272607 | E3: 5992 | J3: 188713 | K3: 185480 | L3: 168132 | M3: 4388 | N3: 5120 | O3: 337808 | P3: 22166 | Q3: 88781 | R3: 106884 | S3: 10886 | T3: 31350 | U3: 1488780 | V3: 411354 | W3: 222370 | X3: 80338 | Y3: 81705 | Z3: 253913 | AA3: 131898 | AB3: 192379
A4: 2015-16 | B4: BE | C4: 470628 | D4: 320836 | E4: 6531 | J4: 208336 | K4: 229808 | L4: 209774 | M4: 3577 | N4: 5690 | O4: 523958 | P4: 23600 | Q4: 100651 | R4: 97482 | S4: 10753 | T4: 69500 | U4: 1536047 | V4: 456145 | W4: 246727 | X4: 108630 | Y4: 88521 | Z4: 227388 | AA4: 110551 | AB4: 241430
A5: 2015-16 | B5: RE | C5: 452970 | D5: 291653 | E5: 7398 | J5: 209500 | K5: 284142 | L5: 210000 | M5: 3948 | N5: 5910 | O5: 506193 | P5: 23142 | Q5: 118271 | R5: 117163 | S5: 18905 | T5: 25312 | U5: 1547673 | V5: 442620 | W5: 224636 | X5: 108312 | Y5: 95731 | Z5: 257801 | AA5: 132004 | AB5: 237718
A6: 2016-17 | B6: BE | C6: 493924 | D6: 345776 | E6: 7398 | F6: 0 | G6: 0 | H6: 0 | I6: 0 | J6: 230000 | K6: 318669 | L6: 231000 | M6: 4121 | N6: 6450 | O6: 570337 | P6: 29620 | Q6: 123780 | R6: 169521 | S6: 10634 | T6: 56500 | U6: 1731535 | V6: 492670 | W6: 162759 | X6: 275116 | Y6: 123368 | Z6: 231782 | AA6: 166840 | AB6: 246525
A7: 2016-17 | B7: RE | C7: 493923 | D7: 345776 | E7: 7398 | F7: 0 | G7: 0 | H7: 0 | I7: 0 | J7: 217000 | K7: 387368 | L7: 247500 | M7: 4277 | N7: 6450 | O7: 608000 | P7: 18149 | Q7: 153222 | R7: 163399 | S7: 11071 | T7: 45500 | U7: 1735220 | V7: 483069 | W7: 168635 | X7: 280839 | Y7: 128166 | Z7: 229716 | AA7: 171472 | AB7: 279187
A8: 2017-18 | B8: BE | C8: 538745 | D8: 433487 | E8: 7768 | F8: 0 | G8: 0 | H8: 0 | I8: 0 | J8: 245000 | K8: 406900 | L8: 275000 | M8: 4679 | N8: 10000 | O8: 674565 | P8: 19021 | Q8: 142430 | R8: 127306 | S8: 11932 | T8: 72500 | U8: 1837505 | V8: 523078 | W8: 175861 | X8: 292968 | Y8: 131201 | Z8: 240339 | AA8: 195350 | AB8: 309230
A9: 2017-18 | B9: RE | C9: 563745 | D9: 433487 | E9: 7768 | F9: 221400 | G9: 161900 | H9: 1424 | I9: 61331 | J9: 135242 | K9: 276995 | L9: 79507 | M9: 3320 | N9: 3660 | O9: 673005 | P9: 13551 | Q9: 106433 | R9: 115990 | S9: 17473 | T9: 100000 | U9: 1944999 | V9: 530843 | W9: 180608 | X9: 369010 | Y9: 147387 | Z9: 229716 | AA9: 189245 | AB9: 272751
A10: 2018-19 | B10: BE | C10: 621000 | D10: 518000 | E10: 11000 | F10: 603900 | G10: 50000 | H10: 2530 | I10: 90000 | J10: 112500 | K10: 259600 | L10: 0 | M10: 2712 | N10: 2500 | O10: 788093 | P10: 15162 | Q10: 107312 | R10: 122615 | S10: 12199 | T10: 80000 | U10: 2142283 | V10: 575795 | W10: 188723 | X10: 420591 | Y10: 168466 | Z10: 264336 | AA10: 195345 | AB10: 299930
A11: 2018-19 | B11: RE | C11: 671000 | D11: 518000 | E11: 11000 | F11: 503900 | G11: 50000 | H11: 2530 | I11: 90000 | J11: 130038 | K11: 259612 | L11: 9283 | M11: 2812 | N11: 2315 | O11: 761454 | P11: 12047 | Q11: 119265 | R11: 113964 | S11: 13155 | T11: 80000 | U11: 2141351 | V11: 587570 | W11: 191431 | X11: 389212 | Y11: 166618 | Z11: 266206 | AA11: 200300 | AB11: 315884
A12: 2019-20 | B12: BE | C12: 766000 | D12: 556200 | E12: 12800 | F12: 526000 | G12: 28000 | H12: 2768 | I12: 109343 | J12: 155904 | K12: 300000 | L12: 0 | M12: 4180 | N12: 2480 | O12: 809133 | P12: 13711 | Q12: 163528 | R12: 135940 | S12: 14828 | T12: 105000 | U12: 2448264 | V12: 660471 | W12: 201902 | X12: 467339 | Y12: 174300 | Z12: 301694 | AA12: 207333 | AB12: 338085
A13: 2019-20 | B13: RE | C13: 610500 | D13: 547000 | E13: 12500 | F13: 514000 | G13: 0 | H13: 2704 | I13: 98327 | J13: 125000 | K13: 248012 | L13: 1200 | M13: 4180 | N13: 2790 | O13: 656046 | P13: 11027 | Q13: 199893 | R13: 134594 | S13: 16605 | T13: 65000 | U13: 2350438 | V13: 625105 | W13: 205902 | X13: 475152 | Y13: 184147 | Z13: 227255 | AA13: 191737 | AB13: 348114
A14: 2020-21 | B14: BE | C14: 681000 | D14: 625000 | E14: 13000 | F14: 580000 | G14: 0 | H14: 3000 | I14: 110500 | J14: 138000 | K14: 267000 | L14: 1020 | M14: 4500 | N14: 2930 | O14: 784181 | P14: 11042 | Q14: 155395 | R14: 218580 | S14: 14967 | T14: 210000 | U14: 2630221 | V14: 708203 | W14: 209319 | X14: 562046 | Y14: 210682 | Z14: 227794 | AA14: 206500 | AB14: 412009
A15: 2020-21 | B15: RE | C15: 446000 | D15: 447000 | E15: 12000 | F15: 431000 | G15: 0 | H15: 2720 | I15: 84100 | J15: 112000 | K15: 361000 | L15: 1400 | M15: 3060 | N15: 5820 | O15: 549959 | P15: 14005 | Q15: 96544 | R15: 100103 | S15: 14497 | T15: 32000 | U15: 3011916 | V15: 692900 | W15: 209312 | X15: 559025 | Y15: 204393 | Z15: 595620 | AA15: 230376 | AB15: 438389
A16: 2021-22 | B16: BE | C16: 547000 | D16: 548500 | E16: 12500 | F16: 530000 | G16: 0 | H16: 3327 | I16: 100000 | J16: 136000 | K16: 335000 | L16: 1000 | M16: 3732 | N16: 6100 | O16: 665563 | P16: 11541 | Q16: 103538 | R16: 127949 | S16: 13000 | T16: 175000 | U16: 2929128 | V16: 809701 | W16: 212028 | X16: 605812 | Y16: 190328 | Z16: 336439 | AA16: 219112 | AB16: 554108
A17: 2021-22 | B17: RE | C17: 635000 | D17: 595000 | E17: 20000 | F17: 570000 | G17: 0 | H17: 3327 | I17: 105000 | J17: 189000 | K17: 394000 | L17: 1000 | M17: 3732 | N17: 6130 | O17: 744784 | P17: 20894 | Q17: 147353 | R17: 145544 | S17: 21975 | T17: 78000 | U17: 3168067 | V17: 813791 | W17: 229567 | X17: 587918 | Y17: 198962 | Z17: 422108 | AA17: 237685 | AB17: 601933
... A22: 2024-25 | B22: BE | C22: 1020000 | D22: 1150000 | E22: 37000 | F22: 910890 | G22: 0 | H22: 4900 | I22: 151009 | J22: 237745 | K22: 319000 | L22: 100 | M22: 9526 | N22: 9460 | O22: 1247211 | P22: 38224 | Q22: 289134 | R22: 218343 | S22: 28000 | T22: 50000 | U22: 3709401 | V22: 1162940 | W22: 282773 | X22: 641460 | Y22: 243296 | Z22: 381175 | AA22: 390778 | AB22: 1111111
A23: 2024-25 | B23: RE | C23: 980000 | D23: 1199300 | E23: 55000 | F23: 908459 | G23: 0 | H23: 4940 | I23: 153440 | J23: 235000 | K23: 305000 | L23: 100 | M23: =9516+2700 -> 12216 | N23: 9610 | O23: 1286885 | P23: 34042 | Q23: 289285 | R23: 207673 | S23: 26000 | T23: 33000 | U23: 3698058 | V23: 1137940 | W23: 297222 | X23: 594207 | Y23: 275103 | Z23: 383419 | AA23: 299891 | AB23: 1018429
A24: 2025-26 | B24: BE | C24: 1082000 | D24: 1357000 | E24: 78000 | F24: 1010890 | G24: 0 | H24: 5355 | I24: 167110 | J24: 240000 | K24: 317000 | L24: 100 | M24: 12778 | N24: 10380 | O24: 1422444 | P24: 47738 | Q24: 325000 | R24: 210262 | S24: 29000 | T24: 47000 | U24: 3944255 | V24: 1276338 | W24: 311732 | X24: 720056 | Y24: 276618 | Z24: 383407 | AA24: 427192 | AB24: 1121090

Sheet GDP
A1: FY | B1: GDP
A2: 2014-15 | B2: 12467959
A3: 2015-16 | B3: 13771874
A4: 2016-17 | B4: 15391669
A5: 2017-18 | B5: 17090042
A6: 2018-19 | B6: 18899668
A7: 2019-20 | B7: 20103593
A8: 2020-21 | B8: 19854096
A9: 2021-22 | B9: 23597399
A10: 2022-23 | B10: 26949646
A11: 2023-24 | B11: 29535667
A12: 2024-25 | B12: 33068145
A13: 2025-26 | B13: 35713886

Sheet actual2
A1: FY | B1: Month | C1: Gross Tax Revenue | D1: Net Tax Revenue | E1: Non Tax Revenue | F1: Revenue Receipts | G1: Non Debt Capital Receipts | H1: Total Receipts | I1: Other Revenue Expenditure | J1: Total Expenditure | K1: Fiscal Deficit | L1: Revenue Deficit | M1: Effective Revenue Deficit | N1: Primary Deficit
A2: =actual!A2 -> 2014-15 | B2: =actual!B2 -> Apr-14 | C2: =SUM(actual!C2:M2) -> 28794 | D2: =C2-actual!N2-actual!O2 -> 977 | E2: =SUM(actual!P2:R2) -> 5952 | F2: =SUM(D2:E2) -> 6929 | G2: =SUM(actual!S2:T2) -> 144 | H2: =SUM(F2:G2) -> 7073 | I2: =actual!U2-actual!V2-actual!W2-actual!X2-actual!Y2-actual!Z2 -> 27171 | J2: =actual!U2+actual!AB2 -> 120527 | K2: =actual2!J2-actual2!H2 -> 113454 | L2: =actual!U2-actual2!F2 -> 101155 | M2: =L2-actual!AA2 -> 91043 | N2: =K2-actual!V2 -> 90170
A3: =actual!A3 -> 2014-15 | B3: =actual!B3 -> May-14 | C3: =SUM(actual!C3:M3) -> 84516 | D3: =C3-actual!N3-actual!O3 -> 28651 | E3: =SUM(actual!P3:R3) -> 9854 | F3: =SUM(D3:E3) -> 38505 | G3: =SUM(actual!S3:T3) -> 997 | H3: =SUM(F3:G3) -> 39502 | I3: =actual!U3-actual!V3-actual!W3-actual!X3-actual!Y3-actual!Z3 -> 64885 | J3: =actual!U3+actual!AB3 -> 280339 | K3: =actual2!J3-actual2!H3 -> 240837 | L3: =actual!U3-actual2!F3 -> 205080 | M3: =L3-actual!AA3 -> 183624 | N3: =K3-actual!V3 -> 185980
A4: =actual!A4 -> 2014-15 | B4: =actual!B4 -> Jun-14 | C4: =SUM(actual!C4:M4) -> 183028 | D4: =C4-actual!N4-actual!O4 -> 99086 | E4: =SUM(actual!P4:R4) -> 15340 | F4: =SUM(D4:E4) -> 114426 | G4: =SUM(actual!S4:T4) -> 1317 | H4: =SUM(F4:G4) -> 115743 | I4: =actual!U4-actual!V4-actual!W4-actual!X4-actual!Y4-actual!Z4 -> 114347 | J4: =actual!U4+actual!AB4 -> 413603 | K4: =actual2!J4-actual2!H4 -> 297860 | L4: =actual!U4-actual2!F4 -> 249359 | M4: =L4-actual!AA4 -> 217085 | N4: =K4-actual!V4 -> 207166
A5: =actual!A5 -> 2014-15 | B5: =actual!B5 -> Jul-14 | C5: =SUM(actual!C5:M5) -> 258873 | D5: =C5-actual!N5-actual!O5 -> 146865 | E5: =SUM(actual!P5:R5) -> 28767 | F5: =SUM(D5:E5) -> 175632 | G5: =SUM(actual!S5:T5) -> 3384 | H5: =SUM(F5:G5) -> 179016 | I5: =actual!U5-actual!V5-actual!W5-actual!X5-actual!Y5-actual!Z5 -> 132929 | J5: =actual!U5+actual!AB5 -> 503940 | K5: =actual2!J5-actual2!H5 -> 324924 | L5: =actual!U5-actual2!F5 -> 266419 | M5: =L5-actual!AA5 -> 230206 | N5: =K5-actual!V5 -> 206309
A6: =actual!A6 -> 2014-15 | B6: =actual!B6 -> Aug-14 | C6: =SUM(actual!C6:M6) -> 324938 | D6: =C6-actual!N6-actual!O6 -> 185459 | E6: =SUM(actual!P6:R6) -> 84996 | F6: =SUM(D6:E6) -> 270455 | G6: =SUM(actual!S6:T6) -> 4334 | H6: =SUM(F6:G6) -> 274789 | I6: =actual!U6-actual!V6-actual!W6-actual!X6-actual!Y6-actual!Z6 -> 177154 | J6: =actual!U6+actual!AB6 -> 672718 | K6: =actual2!J6-actual2!H6 -> 397929 | L6: =actual!U6-actual2!F6 -> 324764 | M6: =L6-actual!AA6 -> 271213 | N6: =K6-actual!V6 -> 244053
A7: =actual!A7 -> 2014-15 | B7: =actual!B7 -> Sep-14 | C7: =SUM(actual!C7:M7) -> 490618 | D7: =C7-actual!N7-actual!O7 -> 323191 | E7: =SUM(actual!P7:R7) -> 94705 | F7: =SUM(D7:E7) -> 417896 | G7: =SUM(actual!S7:T7) -> 5331 | H7: =SUM(F7:G7) -> 423227 | I7: =actual!U7-actual!V7-actual!W7-actual!X7-actual!Y7-actual!Z7 -> 244595 | J7: =actual!U7+actual!AB7 -> 862053 | K7: =actual2!J7-actual2!H7 -> 438826 | L7: =actual!U7-actual2!F7 -> 345053 | M7: =L7-actual!AA7 -> 278784 | N7: =K7-actual!V7 -> 253156
A8: =actual!A8 -> 2014-15 | B8: =actual!B8 -> Oct-14 | C8: =SUM(actual!C8:M8) -> 563598 | D8: =C8-actual!N8-actual!O8 -> 368872 | E8: =SUM(actual!P8:R8) -> 111201 | F8: =SUM(D8:E8) -> 480073 | G8: =SUM(actual!S8:T8) -> 6264 | H8: =SUM(F8:G8) -> 486337 | I8: =actual!U8-actual!V8-actual!W8-actual!X8-actual!Y8-actual!Z8 -> 267504 | J8: =actual!U8+actual!AB8 -> 962089 | K8: =actual2!J8-actual2!H8 -> 475752 | L8: =actual!U8-actual2!F8 -> 372634 | M8: =L8-actual!AA8 -> 298929 | N8: =K8-actual!V8 -> 269778
A9: =actual!A9 -> 2014-15 | B9: =actual!B9 -> Nov-14 | C9: =SUM(actual!C9:M9) -> 635583 | D9: =C9-actual!N9-actual!O9 -> 413310 | E9: =SUM(actual!P9:R9) -> 128343 | F9: =SUM(D9:E9) -> 541653 | G9: =SUM(actual!S9:T9) -> 7396 | H9: =SUM(F9:G9) -> 549049 | I9: =actual!U9-actual!V9-actual!W9-actual!X9-actual!Y9-actual!Z9 -> 294608 | J9: =actual!U9+actual!AB9 -> 1074183 | K9: =actual2!J9-actual2!H9 -> 525134 | L9: =actual!U9-actual2!F9 -> 411075 | M9: =L9-actual!AA9 -> 329491 | N9: =K9-actual!V9 -> 292484
A10: =actual!A10 -> 2014-15 | B10: =actual!B10 -> Dec-14 | C10: =SUM(actual!C10:M10) -> 795686 | D10: =C10-actual!N10-actual!O10 -> 545714 | E10: =SUM(actual!P10:R10) -> 148059 | F10: =SUM(D10:E10) -> 693773 | G10: =SUM(actual!S10:T10) -> 10234 | H10: =SUM(F10:G10) -> 704007 | I10: =actual!U10-actual!V10-actual!W10-actual!X10-actual!Y10-actual!Z10 -> 347890 | J10: =actual!U10+actual!AB10 -> 1236388 | K10: =actual2!J10-actual2!H10 -> 532381 | L10: =actual!U10-actual2!F10 -> 401775 | M10: =L10-actual!AA10 -> 303912 | N10: =K10-actual!V10 -> 257161
A11: =actual!A11 -> 2014-15 | B11: =actual!B11 -> Jan-15 | C11: =SUM(actual!C11:M11) -> 872084 | D11: =C11-actual!N11-actual!O11 -> 594797 | E11: =SUM(actual!P11:R11) -> 158310 | F11: =SUM(D11:E11) -> 753107 | G11: =SUM(actual!S11:T11) -> 17022 | H11: =SUM(F11:G11) -> 770129 | I11: =actual!U11-actual!V11-actual!W11-actual!X11-actual!Y11-actual!Z11 -> 363102 | J11: =actual!U11+actual!AB11 -> 1338268 | K11: =actual2!J11-actual2!H11 -> 568139 | L11: =actual!U11-actual2!F11 -> 441506 | M11: =L11-actual!AA11 -> 339298 | N11: =K11-actual!V11 -> 255879
A12: =actual!A12 -> 2014-15 | B12: =actual!B12 -> Feb-15 | C12: =SUM(actual!C12:M12) -> 954953 | D12: =C12-actual!N12-actual!O12 -> 651419 | E12: =SUM(actual!P12:R12) -> 164819 | F12: =SUM(D12:E12) -> 816238 | G12: =SUM(actual!S12:T12) -> 40764 | H12: =SUM(F12:G12) -> 857002 | I12: =actual!U12-actual!V12-actual!W12-actual!X12-actual!Y12-actual!Z12 -> 394375 | J12: =actual!U12+actual!AB12 -> 1459536 | K12: =actual2!J12-actual2!H12 -> 602534 | L12: =actual!U12-actual2!F12 -> 483254 | M12: =L12-actual!AA12 -> 369184 | N12: =K12-actual!V12 -> 256278
A13: =actual!A13 -> 2014-15 | B13: =actual!B13 -> Mar-15 | C13: =SUM(actual!C13:M13) -> 1244884 | D13: =C13-actual!N13-actual!O13 -> 903615 | E13: =SUM(actual!P13:R13) -> 197766 | F13: =SUM(D13:E13) -> 1101381 | G13: =SUM(actual!S13:T13) -> 51475 | H13: =SUM(F13:G13) -> 1152856 | I13: =actual!U13-actual!V13-actual!W13-actual!X13-actual!Y13-actual!Z13 -> 425825 | J13: =actual!U13+actual!AB13 -> 1663673 | K13: =actual2!J13-actual2!H13 -> 510817 | L13: =actual!U13-actual2!F13 -> 365611 | M13: =L13-actual!AA13 -> 234851 | N13: =K13-actual!V13 -> 108373
... A42: =actual!A42 -> 2017-18 | B42: =actual!B42 -> Aug-17 | C42: =SUM(actual!C42:M42) -> 583626 | D42: =C42-actual!N42-actual!O42 -> 340612 | E42: =SUM(actual!P42:R42) -> 69256 | F42: =SUM(D42:E42) -> 409868 | G42: =SUM(actual!S42:T42) -> 15534 | H42: =SUM(F42:G42) -> 425402 | I42: =actual!U42-actual!V42-actual!W42-actual!X42-actual!Y42-actual!Z42 -> 171053 | J42: =actual!U42+actual!AB42 -> 950447 | K42: =actual2!J42-actual2!H42 -> 525045 | L42: =actual!U42-actual2!F42 -> 430931 | M42: =L42-actual!AA42 -> 346131 | N42: =K42-actual!V42 -> 328652
A43: =actual!A42 -> 2017-18 | B43: =actual!B42 -> Aug-17 | C43: =SUM(actual!C42:M42) -> 583626 | D43: =C43-actual!N42-actual!O42 -> 340612 | E43: =SUM(actual!P42:R42) -> 69256 | F43: =SUM(D43:E43) -> 409868 | G43: =SUM(actual!S42:T42) -> 15534 | H43: =SUM(F43:G43) -> 425402 | I43: =actual!U42-actual!V42-actual!W42-actual!X42-actual!Y42-actual!Z42 -> 171053 | J43: =actual!U42+actual!AB42 -> 950447 | K43: =actual2!J43-actual2!H43 -> 525045 | L43: =actual!U42-actual2!F43 -> 430931 | M43: =L43-actual!AA42 -> 346131 | N43: =K43-actual!V42 -> 328652
A44: =actual!A43 -> 2017-18 | B44: =actual!B43 -> Sep-17 | C44: =SUM(actual!C43:M43) -> 833840 | D44: =C44-actual!N43-actual!O43 -> 542358 | E44: =SUM(actual!P43:R43) -> 80849 | F44: =SUM(D44:E44) -> 623207 | G44: =SUM(actual!S43:T43) -> 27042 | H44: =SUM(F44:G44) -> 650249 | I44: =actual!U43-actual!V43-actual!W43-actual!X43-actual!Y43-actual!Z43 -> 222931 | J44: =actual!U43+actual!AB43 -> 1149187 | K44: =actual2!J44-actual2!H44 -> 498938 | L44: =actual!U43-actual2!F44 -> 379591 | M44: =L44-actual!AA43 -> 272999 | N44: =K44-actual!V43 -> 273172
A45: =actual!A44 -> 2017-18 | B45: =actual!B44 -> Oct-17 | C45: =SUM(actual!C44:M44) -> 973412 | D45: =C45-actual!N44-actual!O44 -> 633617 | E45: =SUM(actual!P44:R44) -> 95151 | F45: =SUM(D45:E45) -> 728768 | G45: =SUM(actual!S44:T44) -> 38559 | H45: =SUM(F45:G45) -> 767327 | I45: =actual!U44-actual!V44-actual!W44-actual!X44-actual!Y44-actual!Z44 -> 253998 | J45: =actual!U44+actual!AB44 -> 1292648 | K45: =actual2!J45-actual2!H45 -> 525321 | L45: =actual!U44-actual2!F45 -> 401085 | M45: =L45-actual!AA44 -> 285231 | N45: =K45-actual!V44 -> 267412
A46: =actual!A45 -> 2017-18 | B46: =actual!B45 -> Nov-17 | C46: =SUM(actual!C45:M45) -> 1087302 | D46: =C46-actual!N45-actual!O45 -> 699392 | E46: =SUM(actual!P45:R45) -> 105469 | F46: =SUM(D46:E46) -> 804861 | G46: =SUM(actual!S45:T45) -> 61849 | H46: =SUM(F46:G46) -> 866710 | I46: =actual!U45-actual!V45-actual!W45-actual!X45-actual!Y45-actual!Z45 -> 284672 | J46: =actual!U45+actual!AB45 -> 1478815 | K46: =actual2!J46-actual2!H46 -> 612105 | L46: =actual!U45-actual2!F46 -> 489839 | M46: =L46-actual!AA45 -> 361405 | N46: =K46-actual!V45 -> 302306
A47: =actual!A46 -> 2017-18 | B47: =actual!B46 -> Dec-17 | C47: =SUM(actual!C46:M46) -> 1336566 | D47: =C47-actual!N46-actual!O46 -> 900124 | E47: =SUM(actual!P46:R46) -> 113498 | F47: =SUM(D47:E47) -> 1013622 | G47: =SUM(actual!S46:T46) -> 64384 | H47: =SUM(F47:G47) -> 1078006 | I47: =actual!U46-actual!V46-actual!W46-actual!X46-actual!Y46-actual!Z46 -> 319994 | J47: =actual!U46+actual!AB46 -> 1698955 | K47: =actual2!J47-actual2!H47 -> 620949 | L47: =actual!U46-actual2!F47 -> 448737 | M47: =L47-actual!AA46 -> 302488 | N47: =K47-actual!V46 -> 246993
A48: =actual!A47 -> 2017-18 | B48: =actual!B47 -> Jan-18 | C48: =SUM(actual!C47:M47) -> 1455846 | D48: =C48-actual!N47-actual!O47 -> 971323 | E48: =SUM(actual!P47:R47) -> 124364 | F48: =SUM(D48:E48) -> 1095687 | G48: =SUM(actual!S47:T47) -> 67699 | H48: =SUM(F48:G48) -> 1163386 | I48: =actual!U47-actual!V47-actual!W47-actual!X47-actual!Y47-actual!Z47 -> 341735 | J48: =actual!U47+actual!AB47 -> 1839945 | K48: =actual2!J48-actual2!H48 -> 676559 | L48: =actual!U47-actual2!F48 -> 480093 | M48: =L48-actual!AA47 -> 326357 | N48: =K48-actual!V47 -> 262321
A49: =actual!A48 -> 2017-18 | B49: =actual!B48 -> Feb-18 | C49: =SUM(actual!C48:M48) -> 1568391 | D49: =C49-actual!N48-actual!O48 -> 1035546 | E49: =SUM(actual!P48:R48) -> 142132 | F49: =SUM(D49:E49) -> 1177678 | G49: =SUM(actual!S48:T48) -> 105794 | H49: =SUM(F49:G49) -> 1283472 | I49: =actual!U48-actual!V48-actual!W48-actual!X48-actual!Y48-actual!Z48 -> 375779 | J49: =actual!U48+actual!AB48 -> 1999171 | K49: =actual2!J49-actual2!H49 -> 715699 | L49: =actual!U48-actual2!F49 -> 524407 | M49: =L49-actual!AA48 -> 359758 | N49: =K49-actual!V48 -> 264970
A50: =actual!A49 -> 2017-18 | B50: =actual!B49 -> Mar-18 | C50: =SUM(actual!C49:M49) -> 1919009 | D50: =C50-actual!N49-actual!O49 -> 1242487 | E50: =SUM(actual!P49:R49) -> 187917 | F50: =SUM(D50:E50) -> 1430404 | G50: =SUM(actual!S49:T49) -> 120356 | H50: =SUM(F50:G50) -> 1550760 | I50: =actual!U49-actual!V49-actual!W49-actual!X49-actual!Y49-actual!Z49 -> 450910 | J50: =actual!U49+actual!AB49 -> 2141822 | K50: =actual2!J50-actual2!H50 -> 591062 | L50: =actual!U49-actual2!F50 -> 448942 | M50: =L50-actual!AA49 -> 256422 | N50: =K50-actual!V49 -> 62110
A51: =actual!A50 -> 2018-19 | B51: =actual!B50 -> Apr-18 | C51: =SUM(actual!C50:M50) -> 113330 | D51: =C51-actual!N50-actual!O50 -> 57533 | E51: =SUM(actual!P50:R50) -> 13124 | F51: =SUM(D51:E51) -> 70657 | G51: =SUM(actual!S50:T50) -> 793 | H51: =SUM(F51:G51) -> 71450 | I51: =actual!U50-actual!V50-actual!W50-actual!X50-actual!Y50-actual!Z50 -> 39385 | J51: =actual!U50+actual!AB50 -> 223417 | K51: =actual2!J51-actual2!H51 -> 151967 | L51: =actual!U50-actual2!F51 -> 106057 | M51: =L51-actual!AA50 -> 83402 | N51: =K51-actual!V50 -> 136349
A52: =actual!A51 -> 2018-19 | B52: =actual!B51 -> May-18 | C52: =SUM(actual!C51:M51) -> 214098 | D52: =C52-actual!N51-actual!O51 -> 102408 | E52: =SUM(actual!P51:R51) -> 24049 | F52: =SUM(D52:E52) -> 126457 | G52: =SUM(actual!S51:T51) -> 1004 | H52: =SUM(F52:G52) -> 127461 | I52: =actual!U51-actual!V51-actual!W51-actual!X51-actual!Y51-actual!Z51 -> 95116 | J52: =actual!U51+actual!AB51 -> 472954 | K52: =actual2!J52-actual2!H52 -> 345493 | L52: =actual!U51-actual2!F52 -> 282706 | M52: =L52-actual!AA51 -> 236898 | N52: =K52-actual!V51 -> 271887
A53: =actual!A52 -> 2018-19 | B53: =actual!B52 -> Jun-18 | C53: =SUM(actual!C52:M52) -> 395038 | D53: =C53-actual!N52-actual!O52 -> 237170 | E53: =SUM(actual!P52:R52) -> 30601 | F53: =SUM(D53:E53) -> 267771 | G53: =SUM(actual!S52:T52) -> 10843 | H53: =SUM(F53:G53) -> 278614 | I53: =actual!U52-actual!V52-actual!W52-actual!X52-actual!Y52-actual!Z52 -> 136566 | J53: =actual!U52+actual!AB52 -> 707647 | K53: =actual2!J53-actual2!H53 -> 429033 | L53: =actual!U52-actual2!F53 -> 352888 | M53: =L53-actual!AA52 -> 289828 | N53: =K53-actual!V52 -> 284118
A54: =actual!A53 -> 2018-19 | B54: =actual!B53 -> Jul-18 | C54: =SUM(actual!C53:M53) -> 505484 | D54: =C54-actual!N53-actual!O53 -> 292611 | E54: =SUM(actual!P53:R53) -> 43125 | F54: =SUM(D54:E54) -> 335736 | G54: =SUM(actual!S53:T53) -> 13731 | H54: =SUM(F54:G54) -> 349467 | I54: =actual!U53-actual!V53-actual!W53-actual!X53-actual!Y53-actual!Z53 -> 169396 | J54: =actual!U53+actual!AB53 -> 889724 | K54: =actual2!J54-actual2!H54 -> 540257 | L54: =actual!U53-actual2!F54 -> 442651 | M54: =L54-actual!AA53 -> 363006 | N54: =K54-actual!V53 -> 359413
... A155: =actual!A154 -> 0 | B155: =actual!B154 -> 0 | C155: =SUM(actual!C154:M154) -> 0 | D155: =C155-actual!N154-actual!O154 -> 0 | E155: =SUM(actual!P154:R154) -> 0 | F155: =SUM(D155:E155) -> 0 | G155: =SUM(actual!S154:T154) -> 0 | H155: =SUM(F155:G155) -> 0 | I155: =actual!U154-actual!V154-actual!W154-actual!X154-actual!Y154-actual!Z154 -> 0 | J155: =actual!U154+actual!AB154 -> 0 | K155: =actual2!J155-actual2!H155 -> 0 | L155: =actual!U154-actual2!F155 -> 0 | M155: =L155-actual!AA154 -> 0 | N155: =K155-actual!V154 -> 0

Sheet BERE2
A1: FY | B1: Month | C1: Gross Tax Revenue | D1: Net Tax Revenue | E1: Non Tax Revenue | F1: Revenue Receipts | G1: Non Debt Capital Receipts | H1: Total Receipts | I1: Other Revenue Expenditure | J1: Total Expenditure | K1: Fiscal Deficit | L1: Revenue Deficit | M1: Effective Revenue Deficit | N1: Primary Deficit
A2: =BERE!A2 -> 2014-15 | B2: =BERE!B2 -> BE | C2: =SUM(BERE!C2:M2) -> 1364524 | D2: =C2-BERE!N2-BERE!O2 -> 977258 | E2: =SUM(BERE!P2:R2) -> 212505 | F2: =SUM(D2:E2) -> 1189763 | G2: =SUM(BERE!S2:T2) -> 73952 | H2: =SUM(F2:G2) -> 1263715 | I2: =BERE!U2-BERE!V2-BERE!W2-BERE!X2-BERE!Y2-BERE!Z2 -> 508701 | J2: =BERE!U2+BERE!AB2 -> 1794892 | K2: =BERE2!J2-BERE2!H2 -> 531177 | L2: =BERE!U2-BERE2!F2 -> 378348 | M2: =L2-BERE!AA2 -> 210244 | N2: =K2-BERE!V2 -> 104166
A3: =BERE!A3 -> 2014-15 | B3: =BERE!B3 -> RE | C3: =SUM(BERE!C3:M3) -> 1251391 | D3: =C3-BERE!N3-BERE!O3 -> 908463 | E3: =SUM(BERE!P3:R3) -> 217831 | F3: =SUM(D3:E3) -> 1126294 | G3: =SUM(BERE!S3:T3) -> 42236 | H3: =SUM(F3:G3) -> 1168530 | I3: =BERE!U3-BERE!V3-BERE!W3-BERE!X3-BERE!Y3-BERE!Z3 -> 439100 | J3: =BERE!U3+BERE!AB3 -> 1681159 | K3: =BERE2!J3-BERE2!H3 -> 512629 | L3: =BERE!U3-BERE2!F3 -> 362486 | M3: =L3-BERE!AA3 -> 230588 | N3: =K3-BERE!V3 -> 101275
A4: =BERE!A4 -> 2015-16 | B4: =BERE!B4 -> BE | C4: =SUM(BERE!C4:M4) -> 1449490 | D4: =C4-BERE!N4-BERE!O4 -> 919842 | E4: =SUM(BERE!P4:R4) -> 221733 | F4: =SUM(D4:E4) -> 1141575 | G4: =SUM(BERE!S4:T4) -> 80253 | H4: =SUM(F4:G4) -> 1221828 | I4: =BERE!U4-BERE!V4-BERE!W4-BERE!X4-BERE!Y4-BERE!Z4 -> 408636 | J4: =BERE!U4+BERE!AB4 -> 1777477 | K4: =BERE2!J4-BERE2!H4 -> 555649 | L4: =BERE!U4-BERE2!F4 -> 394472 | M4: =L4-BERE!AA4 -> 283921 | N4: =K4-BERE!V4 -> 99504
A5: =BERE!A5 -> 2015-16 | B5: =BERE!B5 -> RE | C5: =SUM(BERE!C5:M5) -> 1459611 | D5: =C5-BERE!N5-BERE!O5 -> 947508 | E5: =SUM(BERE!P5:R5) -> 258576 | F5: =SUM(D5:E5) -> 1206084 | G5: =SUM(BERE!S5:T5) -> 44217 | H5: =SUM(F5:G5) -> 1250301 | I5: =BERE!U5-BERE!V5-BERE!W5-BERE!X5-BERE!Y5-BERE!Z5 -> 418573 | J5: =BERE!U5+BERE!AB5 -> 1785391 | K5: =BERE2!J5-BERE2!H5 -> 535090 | L5: =BERE!U5-BERE2!F5 -> 341589 | M5: =L5-BERE!AA5 -> 209585 | N5: =K5-BERE!V5 -> 92470
A6: =BERE!A6 -> 2016-17 | B6: =BERE!B6 -> BE | C6: =SUM(BERE!C6:M6) -> 1630888 | D6: =C6-BERE!N6-BERE!O6 -> 1054101 | E6: =SUM(BERE!P6:R6) -> 322921 | F6: =SUM(D6:E6) -> 1377022 | G6: =SUM(BERE!S6:T6) -> 67134 | H6: =SUM(F6:G6) -> 1444156 | I6: =BERE!U6-BERE!V6-BERE!W6-BERE!X6-BERE!Y6-BERE!Z6 -> 445840 | J6: =BERE!U6+BERE!AB6 -> 1978060 | K6: =BERE2!J6-BERE2!H6 -> 533904 | L6: =BERE!U6-BERE2!F6 -> 354513 | M6: =L6-BERE!AA6 -> 187673 | N6: =K6-BERE!V6 -> 41234
A7: =BERE!A7 -> 2016-17 | B7: =BERE!B7 -> RE | C7: =SUM(BERE!C7:M7) -> 1703242 | D7: =C7-BERE!N7-BERE!O7 -> 1088792 | E7: =SUM(BERE!P7:R7) -> 334770 | F7: =SUM(D7:E7) -> 1423562 | G7: =SUM(BERE!S7:T7) -> 56571 | H7: =SUM(F7:G7) -> 1480133 | I7: =BERE!U7-BERE!V7-BERE!W7-BERE!X7-BERE!Y7-BERE!Z7 -> 444795 | J7: =BERE!U7+BERE!AB7 -> 2014407 | K7: =BERE2!J7-BERE2!H7 -> 534274 | L7: =BERE!U7-BERE2!F7 -> 311658 | M7: =L7-BERE!AA7 -> 140186 | N7: =K7-BERE!V7 -> 51205
A8: =BERE!A8 -> 2017-18 | B8: =BERE!B8 -> BE | C8: =SUM(BERE!C8:M8) -> 1911579 | D8: =C8-BERE!N8-BERE!O8 -> 1227014 | E8: =SUM(BERE!P8:R8) -> 288757 | F8: =SUM(D8:E8) -> 1515771 | G8: =SUM(BERE!S8:T8) -> 84432 | H8: =SUM(F8:G8) -> 1600203 | I8: =BERE!U8-BERE!V8-BERE!W8-BERE!X8-BERE!Y8-BERE!Z8 -> 474058 | J8: =BERE!U8+BERE!AB8 -> 2146735 | K8: =BERE2!J8-BERE2!H8 -> 546532 | L8: =BERE!U8-BERE2!F8 -> 321734 | M8: =L8-BERE!AA8 -> 126384 | N8: =K8-BERE!V8 -> 23454
A9: =BERE!A9 -> 2017-18 | B9: =BERE!B9 -> RE | C9: =SUM(BERE!C9:M9) -> 1946119 | D9: =C9-BERE!N9-BERE!O9 -> 1269454 | E9: =SUM(BERE!P9:R9) -> 235974 | F9: =SUM(D9:E9) -> 1505428 | G9: =SUM(BERE!S9:T9) -> 117473 | H9: =SUM(F9:G9) -> 1622901 | I9: =BERE!U9-BERE!V9-BERE!W9-BERE!X9-BERE!Y9-BERE!Z9 -> 487435 | J9: =BERE!U9+BERE!AB9 -> 2217750 | K9: =BERE2!J9-BERE2!H9 -> 594849 | L9: =BERE!U9-BERE2!F9 -> 439571 | M9: =L9-BERE!AA9 -> 250326 | N9: =K9-BERE!V9 -> 64006
A10: =BERE!A10 -> 2018-19 | B10: =BERE!B10 -> BE | C10: =SUM(BERE!C10:M10) -> 2271242 | D10: =C10-BERE!N10-BERE!O10 -> 1480649 | E10: =SUM(BERE!P10:R10) -> 245089 | F10: =SUM(D10:E10) -> 1725738 | G10: =SUM(BERE!S10:T10) -> 92199 | H10: =SUM(F10:G10) -> 1817937 | I10: =BERE!U10-BERE!V10-BERE!W10-BERE!X10-BERE!Y10-BERE!Z10 -> 524372 | J10: =BERE!U10+BERE!AB10 -> 2442213 | K10: =BERE2!J10-BERE2!H10 -> 624276 | L10: =BERE!U10-BERE2!F10 -> 416545 | M10: =L10-BERE!AA10 -> 221200 | N10: =K10-BERE!V10 -> 48481
A11: =BERE!A11 -> 2018-19 | B11: =BERE!B11 -> RE | C11: =SUM(BERE!C11:M11) -> 2248175 | D11: =C11-BERE!N11-BERE!O11 -> 1484406 | E11: =SUM(BERE!P11:R11) -> 245276 | F11: =SUM(D11:E11) -> 1729682 | G11: =SUM(BERE!S11:T11) -> 93155 | H11: =SUM(F11:G11) -> 1822837 | I11: =BERE!U11-BERE!V11-BERE!W11-BERE!X11-BERE!Y11-BERE!Z11 -> 540314 | J11: =BERE!U11+BERE!AB11 -> 2457235 | K11: =BERE2!J11-BERE2!H11 -> 634398 | L11: =BERE!U11-BERE2!F11 -> 411669 | M11: =L11-BERE!AA11 -> 211369 | N11: =K11-BERE!V11 -> 46828
A12: =BERE!A12 -> 2019-20 | B12: =BERE!B12 -> BE | C12: =SUM(BERE!C12:M12) -> 2461195 | D12: =C12-BERE!N12-BERE!O12 -> 1649582 | E12: =SUM(BERE!P12:R12) -> 313179 | F12: =SUM(D12:E12) -> 1962761 | G12: =SUM(BERE!S12:T12) -> 119828 | H12: =SUM(F12:G12) -> 2082589 | I12: =BERE!U12-BERE!V12-BERE!W12-BERE!X12-BERE!Y12-BERE!Z12 -> 642558 | J12: =BERE!U12+BERE!AB12 -> 2786349 | K12: =BERE2!J12-BERE2!H12 -> 703760 | L12: =BERE!U12-BERE2!F12 -> 485503 | M12: =L12-BERE!AA12 -> 278170 | N12: =K12-BERE!V12 -> 43289
A13: =BERE!A13 -> 2019-20 | B13: =BERE!B13 -> RE | C13: =SUM(BERE!C13:M13) -> 2163423 | D13: =C13-BERE!N13-BERE!O13 -> 1504587 | E13: =SUM(BERE!P13:R13) -> 345514 | F13: =SUM(D13:E13) -> 1850101 | G13: =SUM(BERE!S13:T13) -> 81605 | H13: =SUM(F13:G13) -> 1931706 | I13: =BERE!U13-BERE!V13-BERE!W13-BERE!X13-BERE!Y13-BERE!Z13 -> 632877 | J13: =BERE!U13+BERE!AB13 -> 2698552 | K13: =BERE2!J13-BERE2!H13 -> 766846 | L13: =BERE!U13-BERE2!F13 -> 500337 | M13: =L13-BERE!AA13 -> 308600 | N13: =K13-BERE!V13 -> 141741
... A44: =BERE!A44 -> 0 | B44: =BERE!B44 -> 0 | C44: =SUM(BERE!C44:M44) -> 0 | D44: =C44-BERE!N44-BERE!O44 -> 0 | E44: =SUM(BERE!P44:R44) -> 0 | F44: =SUM(D44:E44) -> 0 | G44: =SUM(BERE!S44:T44) -> 0 | H44: =SUM(F44:G44) -> 0 | I44: =BERE!U44-BERE!V44-BERE!W44-BERE!X44-BERE!Y44-BERE!Z44 -> 0 | J44: =BERE!U44+BERE!AB44 -> 0 | K44: =BERE2!J44-BERE2!H44 -> 0 | L44: =BERE!U44-BERE2!F44 -> 0 | M44: =L44-BERE!AA44 -> 0 | N44: =K44-BERE!V44 -> 0

Sheet Sheet4
B1: =I2 -> 2020-21 | C1: =J2 -> 2021-22 | D1: =K2 -> 2022-23 | E1: =L2 -> 2023-24 | F1: =M2 -> 2024-25 | G1: =N2 -> 2025-26
A2: =CONCATENATE("(Upto ",LEFT(B2,3),")") -> (Upto Dec) | B2: =Sheet5!S7 -> Dec-20 | C2: =Sheet5!R7 -> Dec-21 | D2: =Sheet5!Q7 -> Dec-22 | E2: =Sheet5!P7 -> Dec-23 | F2: =Sheet5!E6 -> Dec-24 | G2: =Sheet5!E4 -> Dec-25 | I2: =Sheet5!S6 -> 2020-21 | J2: =Sheet5!R6 -> 2021-22 | K2: =Sheet5!Q6 -> 2022-23 | L2: =Sheet5!P6 -> 2023-24 | M2: =Sheet5!D6 -> 2024-25 | N2: =Sheet5!D4 -> 2025-26
A3: =Sheet5!D15 -> Net Tax Revenue | B3: =Sheet5!S15 -> 962399 | C3: =Sheet5!R15 -> 1473809 | D3: =Sheet5!Q15 -> 1555692 | E3: =Sheet5!P15 -> 1729931 | F3: =Sheet5!F15 -> 1843053 | G3: =Sheet5!E15 -> 1939254 | H3: TRUE | I3: =B3/B$6 -> 0.85799935 | J3: =C3/C$6 -> 0.83658721 | K3: =D3/D$6 -> 0.85238727 | L3: =E3/E$6 -> 0.83493336 | M3: =F3/F$6 -> 0.79510312 | N3: =G3/G$6 -> 0.76797394 | P3: =IF(H3=TRUE,1,0) -> 1
A4: =Sheet5!D17 -> Non Tax Revenue | B4: =Sheet5!S17 -> 126181 | C4: =Sheet5!R17 -> 259414 | D4: =Sheet5!Q17 -> 214302 | E4: =Sheet5!P17 -> 312358 | F4: =Sheet5!F17 -> 447657 | G4: =Sheet5!E17 -> 539855 | H4: TRUE | I4: =B4/B$6 -> 0.11249307 | J4: =C4/C$6 -> 0.14725275 | K4: =D4/D$6 -> 0.11741932 | L4: =E4/E$6 -> 0.15075637 | M4: =F4/F$6 -> 0.19312167 | N4: =G4/G$6 -> 0.21379075 | P4: =IF(H4=TRUE,2,0) -> 2
A5: =Sheet5!D19 -> Non Debt Capital Receipts | B5: =Sheet5!S19 -> 33098 | C5: =Sheet5!R19 -> 28469 | D5: =Sheet5!Q19 -> 55106 | E5: =Sheet5!P19 -> 29650 | F5: =Sheet5!F19 -> 27295 | G5: =Sheet5!E19 -> 46047 | H5: TRUE | I5: =B5/B$6 -> 0.029507577 | J5: =C5/C$6 -> 0.016160033 | K5: =D5/D$6 -> 0.030193414 | L5: =E5/E$6 -> 0.014310267 | M5: =F5/F$6 -> 0.011775212 | N5: =G5/G$6 -> 0.018235309 | P5: =IF(H5=TRUE,4,0) -> 4
A6: =Sheet5!D9 -> Total Receipts | B6: =Sheet5!S9 -> 1121678 | C6: =Sheet5!R9 -> 1761692 | D6: =Sheet5!Q9 -> 1825100 | E6: =Sheet5!P9 -> 2071939 | F6: =Sheet5!F9 -> 2318005 | G6: =Sheet5!E9 -> 2525156 | P6: =SUM(P3:P5) -> 7 | Q6: =IF(P6=1,"Net Tax Revenue",IF(P6=2,"Non Tax Revenue",IF(P6=3,"Revenue Receipts",IF(P6=4,"Non Debt Capital Receipts",IF(P6=7,"Total Receipts"," "))))) -> Total Receipts
A8: Dev to States & NCCD | B8: =Sheet5!S63+Sheet5!S65 -> 375727 | C8: =Sheet5!R63+Sheet5!R65 -> 455186 | D8: =Sheet5!Q63+Sheet5!Q65 -> 615006 | E8: =Sheet5!P63+Sheet5!P65 -> 752568 | F8: =Sheet5!F63+Sheet5!F65 -> 907375 | G8: =Sheet5!E63+Sheet5!E65 -> 1045013 | H8: TRUE
A9: =A3 -> Net Tax Revenue | B9: =B3 -> 962399 | C9: =C3 -> 1473809 | D9: =D3 -> 1555692 | E9: =E3 -> 1729931 | F9: =F3 -> 1843053 | G9: =G3 -> 1939254 | H9: TRUE
A11: =Sheet5!D67 -> Interest receipts | B11: =Sheet5!S67 -> 11267 | C11: =Sheet5!R67 -> 16055 | D11: =Sheet5!Q67 -> 18870 | E11: =Sheet5!P67 -> 26959 | F11: =Sheet5!F67 -> 29903 | G11: =Sheet5!E67 -> 27976 | H11: TRUE
A12: =Sheet5!D69 -> Dividends and Profits | B12: =Sheet5!S69 -> 70848 | C12: =Sheet5!R69 -> 137068 | D12: =Sheet5!Q69 -> 76362 | E12: =Sheet5!P69 -> 147232 | F12: =Sheet5!F69 -> 284772 | G12: =Sheet5!E69 -> 350269 | H12: TRUE
A13: =Sheet5!D71 -> Other Non Tax Receipts | B13: =Sheet5!S71 -> 44066 | C13: =Sheet5!R71 -> 106291 | D13: =Sheet5!Q71 -> 119070 | E13: =Sheet5!P71 -> 138167 | F13: =Sheet5!F71 -> 132982 | G13: =Sheet5!E71 -> 161610 | H13: TRUE
A15: =Sheet5!D73 -> Recovery of Loans & Advances | B15: =Sheet5!S73 -> 14202 | C15: =Sheet5!R73 -> 19105 | D15: =Sheet5!Q73 -> 16435 | E15: =Sheet5!P73 -> 19597 | F15: =Sheet5!F73 -> 18301 | G15: =Sheet5!E73 -> 18226 | H15: TRUE
A16: =Sheet5!D75 -> Misc. Capital Receipts | B16: =Sheet5!S75 -> 18896 | C16: =Sheet5!R75 -> 9364 | D16: =Sheet5!Q75 -> 38671 | E16: =Sheet5!P75 -> 10053 | F16: =Sheet5!F75 -> 8994 | G16: =Sheet5!E75 -> 27821 | H16: TRUE
A18: =Sheet5!D21 -> Revenue Expenditure | B18: =Sheet5!S21 -> 1971173 | C18: =Sheet5!R21 -> 2129414 | D18: =Sheet5!Q21 -> 2328132 | E18: =Sheet5!P21 -> 2380587 | F18: =Sheet5!F21 -> 2546757 | G18: =Sheet5!E21 -> 2593063 | H18: TRUE
A19: =Sheet5!D23 -> Capital Expenditure | B19: =Sheet5!S23 -> 308974 | C19: =Sheet5!R23 -> 391644 | D19: =Sheet5!Q23 -> 489944 | E19: =Sheet5!P23 -> 673630 | F19: =Sheet5!F23 -> 685337 | G19: =Sheet5!E23 -> 787935 | H19: TRUE
A20: =IF(MONTH(Dashboard!$D$8)<4,"RE","BE") -> BE | B20: =SUM(B21:B22) -> 3042230 | C20: =SUM(C21:C22) -> 3483236 | D20: =SUM(D21:D22) -> 3944909 | E20: =SUM(E21:E22) -> 4503097 | F20: =SUM(F21:F22) -> 4820512 | G20: =SUM(G21:G22) -> 5065345
A21: =IF(MONTH(Dashboard!$D$8)<4,"RE","BE") -> BE | B21: =IF(MONTH(Dashboard!$D$8)<4,Sheet5!AB21,Sheet5!AA21) -> 2630221 | C21: =IF(MONTH(Dashboard!$D$8)<4,Sheet5!Z21,Sheet5!Y21) -> 2929128 | D21: =IF(MONTH(Dashboard!$D$8)<4,Sheet5!X21,Sheet5!W21) -> 3195257 | E21: =IF(MONTH(Dashboard!$D$8)<4,Sheet5!V21,Sheet5!U21) -> 3502724 | F21: =IF(MONTH(Dashboard!$D$8)<4,Sheet5!J21,Sheet5!I21) -> 3709401 | G21: =IF(MONTH(Dashboard!$D$8)<4,Sheet5!H21,Sheet5!G21) -> 3944255
A22: =IF(MONTH(Dashboard!$D$8)<4,"RE","BE") -> BE | B22: =IF(MONTH(Dashboard!$D$8)<4,Sheet5!AB23,Sheet5!AA23) -> 412009 | C22: =IF(MONTH(Dashboard!$D$8)<4,Sheet5!Z23,Sheet5!Y23) -> 554108 | D22: =IF(MONTH(Dashboard!$D$8)<4,Sheet5!X23,Sheet5!W23) -> 749652 | E22: =IF(MONTH(Dashboard!$D$8)<4,Sheet5!V23,Sheet5!U23) -> 1000373 | F22: =IF(MONTH(Dashboard!$D$8)<4,Sheet5!J23,Sheet5!I23) -> 1111111 | G22: =IF(MONTH(Dashboard!$D$8)<4,Sheet5!H23,Sheet5!G23) -> 1121090
A25: =Sheet5!D25 -> Interest Payments | B25: =Sheet5!S25 -> 472171 | C25: =Sheet5!R25 -> 565864 | D25: =Sheet5!Q25 -> 680853 | E25: =Sheet5!P25 -> 748207 | F25: =Sheet5!F25 -> 808313 | G25: =Sheet5!E25 -> 911059
A26: =Sheet5!D27 -> Defence Services | B26: =Sheet5!S27 -> 153857 | C26: =Sheet5!R27 -> 179859 | D26: =Sheet5!Q27 -> 184962 | E26: =Sheet5!P27 -> 215181 | F26: =Sheet5!F27 -> 215520 | G26: =Sheet5!E27 -> 233023
A27: =Sheet5!D29 -> Grants in Aid to States & UTs | B27: =Sheet5!S29 -> 439785 | C27: =Sheet5!R29 -> 426909 | D27: =Sheet5!Q29 -> 387918 | E27: =Sheet5!P29 -> 349946 | F27: =Sheet5!F29 -> 348245 | G27: =Sheet5!E29 -> 247273
A28: =Sheet5!D31 -> Pensions | B28: =Sheet5!S31 -> 159146 | C28: =Sheet5!R31 -> 146150 | D28: =Sheet5!Q31 -> 168439 | E28: =Sheet5!P31 -> 191905 | F28: =Sheet5!F31 -> 215263 | G28: =Sheet5!E31 -> 226030
A29: =Sheet5!D33 -> Major Subsidies | B29: =Sheet5!S33 -> 227352 | C29: =Sheet5!R33 -> 271374 | D29: =Sheet5!Q33 -> 350524 | E29: =Sheet5!P33 -> 276804 | F29: =Sheet5!F33 -> 306994 | G29: =Sheet5!E33 -> 317490
A30: =Sheet5!D35 -> Other Revenue Expenditure | B30: =Sheet5!S35 -> 518862 | C30: =Sheet5!R35 -> 539258 | D30: =Sheet5!Q35 -> 555436 | E30: =Sheet5!P35 -> 598544 | F30: =Sheet5!F35 -> 652422 | G30: =Sheet5!E35 -> 658188
A32: =A22 -> BE
A33: =A25 -> Interest Payments | B33: =IF(MONTH(Dashboard!$D$8)<4,Sheet5!AB25,Sheet5!AA25) -> 708203 | C33: =IF(MONTH(Dashboard!$D$8)<4,Sheet5!Z25,Sheet5!Y25) -> 809701 | D33: =IF(MONTH(Dashboard!$D$8)<4,Sheet5!X25,Sheet5!W25) -> 940651 | E33: =IF(MONTH(Dashboard!$D$8)<4,Sheet5!V25,Sheet5!U25) -> 1079971 | F33: =IF(MONTH(Dashboard!$D$8)<4,Sheet5!J25,Sheet5!I25) -> 1162940 | G33: =IF(MONTH(Dashboard!$D$8)<4,Sheet5!H25,Sheet5!G25) -> 1276338
A34: =A26 -> Defence Services | B34: =IF(MONTH(Dashboard!$D$8)<4,Sheet5!AB27,Sheet5!AA27) -> 209319 | C34: =IF(MONTH(Dashboard!$D$8)<4,Sheet5!Z27,Sheet5!Y27) -> 212028 | D34: =IF(MONTH(Dashboard!$D$8)<4,Sheet5!X27,Sheet5!W27) -> 233001 | E34: =IF(MONTH(Dashboard!$D$8)<4,Sheet5!V27,Sheet5!U27) -> 270120 | F34: =IF(MONTH(Dashboard!$D$8)<4,Sheet5!J27,Sheet5!I27) -> 282773 | G34: =IF(MONTH(Dashboard!$D$8)<4,Sheet5!H27,Sheet5!G27) -> 311732
A35: =A27 -> Grants in Aid to States & UTs | B35: =IF(MONTH(Dashboard!$D$8)<4,Sheet5!AB29,Sheet5!AA29) -> 562046 | C35: =IF(MONTH(Dashboard!$D$8)<4,Sheet5!Z29,Sheet5!Y29) -> 605812 | D35: =IF(MONTH(Dashboard!$D$8)<4,Sheet5!X29,Sheet5!W29) -> 617057 | E35: =IF(MONTH(Dashboard!$D$8)<4,Sheet5!V29,Sheet5!U29) -> 659736 | F35: =IF(MONTH(Dashboard!$D$8)<4,Sheet5!J29,Sheet5!I29) -> 641460 | G35: =IF(MONTH(Dashboard!$D$8)<4,Sheet5!H29,Sheet5!G29) -> 720056
A36: =A28 -> Pensions | B36: =IF(MONTH(Dashboard!$D$8)<4,Sheet5!AB31,Sheet5!AA31) -> 210682 | C36: =IF(MONTH(Dashboard!$D$8)<4,Sheet5!Z31,Sheet5!Y31) -> 190328 | D36: =IF(MONTH(Dashboard!$D$8)<4,Sheet5!X31,Sheet5!W31) -> 207132 | E36: =IF(MONTH(Dashboard!$D$8)<4,Sheet5!V31,Sheet5!U31) -> 234359 | F36: =IF(MONTH(Dashboard!$D$8)<4,Sheet5!J31,Sheet5!I31) -> 243296 | G36: =IF(MONTH(Dashboard!$D$8)<4,Sheet5!H31,Sheet5!G31) -> 276618
A37: =A29 -> Major Subsidies | B37: =IF(MONTH(Dashboard!$D$8)<4,Sheet5!AB33,Sheet5!AA33) -> 227794 | C37: =IF(MONTH(Dashboard!$D$8)<4,Sheet5!Z33,Sheet5!Y33) -> 336439 | D37: =IF(MONTH(Dashboard!$D$8)<4,Sheet5!X33,Sheet5!W33) -> 317866 | E37: =IF(MONTH(Dashboard!$D$8)<4,Sheet5!V33,Sheet5!U33) -> 374707 | F37: =IF(MONTH(Dashboard!$D$8)<4,Sheet5!J33,Sheet5!I33) -> 381175 | G37: =IF(MONTH(Dashboard!$D$8)<4,Sheet5!H33,Sheet5!G33) -> 383407
A38: =A30 -> Other Revenue Expenditure | B38: =IF(MONTH(Dashboard!$D$8)<4,Sheet5!AB35,Sheet5!AA35) -> 712177 | C38: =IF(MONTH(Dashboard!$D$8)<4,Sheet5!Z35,Sheet5!Y35) -> 774820 | D38: =IF(MONTH(Dashboard!$D$8)<4,Sheet5!X35,Sheet5!W35) -> 879550 | E38: =IF(MONTH(Dashboard!$D$8)<4,Sheet5!V35,Sheet5!U35) -> 883831 | F38: =IF(MONTH(Dashboard!$D$8)<4,Sheet5!J35,Sheet5!I35) -> 997757 | G38: =IF(MONTH(Dashboard!$D$8)<4,Sheet5!H35,Sheet5!G35) -> 976104
A40: =Sheet5!D13 -> Fiscal Deficit | B40: =Sheet5!S13 -> 1158469 | C40: =Sheet5!R13 -> 759366 | D40: =Sheet5!Q13 -> 992976 | E40: =Sheet5!P13 -> 982278 | F40: =Sheet5!F13 -> 914089 | G40: =Sheet5!E13 -> 855842
A41: =Sheet5!D37 -> Revenue Deficit | B41: =Sheet5!S37 -> 882593 | C41: =Sheet5!R37 -> 396191 | D41: =Sheet5!Q37 -> 558138 | E41: =Sheet5!P37 -> 338298 | F41: =Sheet5!F37 -> 256047 | G41: =Sheet5!E37 -> 113954
A42: =Sheet5!D41 -> Primary Deficit | B42: =Sheet5!S41 -> 686298 | C42: =Sheet5!R41 -> 193502 | D42: =Sheet5!Q41 -> 312123 | E42: =Sheet5!P41 -> 234071 | F42: =Sheet5!F41 -> 105776 | G42: =Sheet5!E41 -> -55217
A44: =A22 -> BE
A45: =A40 -> Fiscal Deficit | B45: =IF(MONTH(Dashboard!$D$8)<4,Sheet5!AB13,Sheet5!AA13) -> 796337 | C45: =IF(MONTH(Dashboard!$D$8)<4,Sheet5!Z13,Sheet5!Y13) -> 1506812 | D45: =IF(MONTH(Dashboard!$D$8)<4,Sheet5!X13,Sheet5!W13) -> 1661196 | E45: =IF(MONTH(Dashboard!$D$8)<4,Sheet5!V13,Sheet5!U13) -> 1786816 | F45: =IF(MONTH(Dashboard!$D$8)<4,Sheet5!J13,Sheet5!I13) -> 1613312 | G45: =IF(MONTH(Dashboard!$D$8)<4,Sheet5!H13,Sheet5!G13) -> 1568936
A46: =A41 -> Revenue Deficit | B46: =IF(MONTH(Dashboard!$D$8)<4,Sheet5!AB37,Sheet5!AA37) -> 609295 | C46: =IF(MONTH(Dashboard!$D$8)<4,Sheet5!Z37,Sheet5!Y37) -> 1140704 | D46: =IF(MONTH(Dashboard!$D$8)<4,Sheet5!X37,Sheet5!W37) -> 990835 | E46: =IF(MONTH(Dashboard!$D$8)<4,Sheet5!V37,Sheet5!U37) -> 870443 | F46: =IF(MONTH(Dashboard!$D$8)<4,Sheet5!J37,Sheet5!I37) -> 580201 | G46: =IF(MONTH(Dashboard!$D$8)<4,Sheet5!H37,Sheet5!G37) -> 523846
A47: =A42 -> Primary Deficit | B47: =IF(MONTH(Dashboard!$D$8)<4,Sheet5!AB41,Sheet5!AA41) -> 88134 | C47: =IF(MONTH(Dashboard!$D$8)<4,Sheet5!Z41,Sheet5!Y41) -> 697111 | D47: =IF(MONTH(Dashboard!$D$8)<4,Sheet5!X41,Sheet5!W41) -> 720545 | E47: =IF(MONTH(Dashboard!$D$8)<4,Sheet5!V41,Sheet5!U41) -> 706845 | F47: =IF(MONTH(Dashboard!$D$8)<4,Sheet5!J41,Sheet5!I41) -> 450372 | G47: =IF(MONTH(Dashboard!$D$8)<4,Sheet5!H41,Sheet5!G41) -> 292598
A59: % age to GDP | B59: =Sheet5!S4 -> 19854096 | C59: =Sheet5!R4 -> 23597399 | D59: =Sheet5!Q4 -> 26949646 | E59: =Sheet5!P4 -> 29535667 | F59: =Sheet5!O6 -> 33068145 | G59: =Sheet5!O4 -> 35713886
A60: =A3 -> Net Tax Revenue | B60: =B3/B$59 -> 0.048473574 | C60: =C3/C$59 -> 0.062456417 | D60: =D3/D$59 -> 0.057725879 | E60: =E3/E$59 -> 0.058570914 | F60: =F3/F$59 -> 0.055734998 | G60: =G3/G$59 -> 0.05429972
A61: =A4 -> Non Tax Revenue | B61: =B4/B$59 -> 0.006355414 | C61: =C4/C$59 -> 0.01099333 | D61: =D4/D$59 -> 0.0079519412 | E61: =E4/E$59 -> 0.01057562 | F61: =F4/F$59 -> 0.013537409 | G61: =G4/G$59 -> 0.015116109
A62: =A5 -> Non Debt Capital Receipts | B62: =B5/B$59 -> 0.0016670615 | C62: =C5/C$59 -> 0.0012064465 | D62: =D5/D$59 -> 0.0020447764 | E62: =E5/E$59 -> 0.001003871 | F62: =F5/F$59 -> 0.00082541673 | G62: =G5/G$59 -> 0.0012893304
A63: =A6 -> Total Receipts | B63: =B6/B$59 -> 0.05649605 | C63: =C6/C$59 -> 0.074656194 | D63: =D6/D$59 -> 0.067722596 | E63: =E6/E$59 -> 0.070150405 | F63: =F6/F$59 -> 0.070097824 | G63: =G6/G$59 -> 0.070705159
B75: =I2 -> 2020-21 | C75: =J2 -> 2021-22 | D75: =K2 -> 2022-23 | E75: =L2 -> 2023-24 | F75: =M2 -> 2024-25 | G75: =N2 -> 2025-26
A76: =A3 -> Net Tax Revenue | B76: =IF($H3=TRUE,B3,0) -> 962399 | C76: =IF($H3=TRUE,C3,0) -> 1473809 | D76: =IF($H3=TRUE,D3,0) -> 1555692 | E76: =IF($H3=TRUE,E3,0) -> 1729931 | F76: =IF($H3=TRUE,F3,0) -> 1843053 | G76: =IF($H3=TRUE,G3,0) -> 1939254
A77: =A4 -> Non Tax Revenue | B77: =IF($H4=TRUE,B4,0) -> 126181 | C77: =IF($H4=TRUE,C4,0) -> 259414 | D77: =IF($H4=TRUE,D4,0) -> 214302 | E77: =IF($H4=TRUE,E4,0) -> 312358 | F77: =IF($H4=TRUE,F4,0) -> 447657 | G77: =IF($H4=TRUE,G4,0) -> 539855
A78: =A5 -> Non Debt Capital Receipts | B78: =IF($H5=TRUE,B5,0) -> 33098 | C78: =IF($H5=TRUE,C5,0) -> 28469 | D78: =IF($H5=TRUE,D5,0) -> 55106 | E78: =IF($H5=TRUE,E5,0) -> 29650 | F78: =IF($H5=TRUE,F5,0) -> 27295 | G78: =IF($H5=TRUE,G5,0) -> 46047
B79: =SUM(B76:B78) -> 1121678 | C79: =SUM(C76:C78) -> 1761692 | D79: =SUM(D76:D78) -> 1825100 | E79: =SUM(E76:E78) -> 2071939 | F79: =SUM(F76:F78) -> 2318005 | G79: =SUM(G76:G78) -> 2525156
A81: =A76 -> Net Tax Revenue | B81: =IF(B76=0," ",B76/B$6) -> 0.85799935 | C81: =IF(C76=0," ",C76/C$6) -> 0.83658721 | D81: =IF(D76=0," ",D76/D$6) -> 0.85238727 | E81: =IF(E76=0," ",E76/E$6) -> 0.83493336 | F81: =IF(F76=0," ",F76/F$6) -> 0.79510312 | G81: =IF(G76=0," ",G76/G$6) -> 0.76797394
A82: =A77 -> Non Tax Revenue | B82: =IF(B77=0," ",B77/B$6) -> 0.11249307 | C82: =IF(C77=0," ",C77/C$6) -> 0.14725275 | D82: =IF(D77=0," ",D77/D$6) -> 0.11741932 | E82: =IF(E77=0," ",E77/E$6) -> 0.15075637 | F82: =IF(F77=0," ",F77/F$6) -> 0.19312167 | G82: =IF(G77=0," ",G77/G$6) -> 0.21379075
A83: =A78 -> Non Debt Capital Receipts | B83: =IF(B78=0," ",B78/B$6) -> 0.029507577 | C83: =IF(C78=0," ",C78/C$6) -> 0.016160033 | D83: =IF(D78=0," ",D78/D$6) -> 0.030193414 | E83: =IF(E78=0," ",E78/E$6) -> 0.014310267 | F83: =IF(F78=0," ",F78/F$6) -> 0.011775212 | G83: =IF(G78=0," ",G78/G$6) -> 0.018235309
B86: =B75 -> 2020-21 | C86: =C75 -> 2021-22 | D86: =D75 -> 2022-23 | E86: =E75 -> 2023-24 | F86: =F75 -> 2024-25 | G86: =G75 -> 2025-26
A87: =A8 -> Dev to States & NCCD | B87: =IF($H8=TRUE,B8," ") -> 375727 | C87: =IF($H8=TRUE,C8," ") -> 455186 | D87: =IF($H8=TRUE,D8," ") -> 615006 | E87: =IF($H8=TRUE,E8," ") -> 752568 | F87: =IF($H8=TRUE,F8," ") -> 907375 | G87: =IF($H8=TRUE,G8," ") -> 1045013 | H87: =IF(H8=TRUE,1,0) -> 1
A88: =A9 -> Net Tax Revenue | B88: =IF($H9=TRUE,B9," ") -> 962399 | C88: =IF($H9=TRUE,C9," ") -> 1473809 | D88: =IF($H9=TRUE,D9," ") -> 1555692 | E88: =IF($H9=TRUE,E9," ") -> 1729931 | F88: =IF($H9=TRUE,F9," ") -> 1843053 | G88: =IF($H9=TRUE,G9," ") -> 1939254 | H88: =IF(H9=TRUE,2,0) -> 2
A89: Gross Tax Revenue | B89: =IF($H$89=3,SUM(B87:B88)," ") -> 1338126 | C89: =IF($H$89=3,SUM(C87:C88)," ") -> 1928995 | D89: =IF($H$89=3,SUM(D87:D88)," ") -> 2170698 | E89: =IF($H$89=3,SUM(E87:E88)," ") -> 2482499 | F89: =IF($H$89=3,SUM(F87:F88)," ") -> 2750428 | G89: =IF($H$89=3,SUM(G87:G88)," ") -> 2984267 | H89: =SUM(H87:H88) -> 3 | I89: =IF(H89=1,"Devolution to States & Transfer to NCCD",IF(H89=2,"Net Tax Revenue",IF(H89=3,"Gross Tax Revenue"," " ))) -> Gross Tax Revenue
B91: =B86 -> 2020-21 | C91: =C86 -> 2021-22 | D91: =D86 -> 2022-23 | E91: =E86 -> 2023-24 | F91: =F86 -> 2024-25 | G91: =G86 -> 2025-26
A92: =A11 -> Interest receipts | B92: =IF($H11=TRUE,B11," ") -> 11267 | C92: =IF($H11=TRUE,C11," ") -> 16055 | D92: =IF($H11=TRUE,D11," ") -> 18870 | E92: =IF($H11=TRUE,E11," ") -> 26959 | F92: =IF($H11=TRUE,F11," ") -> 29903 | G92: =IF($H11=TRUE,G11," ") -> 27976 | H92: =IF(H11=TRUE,1,0) -> 1
A93: =A12 -> Dividends and Profits | B93: =IF($H12=TRUE,B12," ") -> 70848 | C93: =IF($H12=TRUE,C12," ") -> 137068 | D93: =IF($H12=TRUE,D12," ") -> 76362 | E93: =IF($H12=TRUE,E12," ") -> 147232 | F93: =IF($H12=TRUE,F12," ") -> 284772 | G93: =IF($H12=TRUE,G12," ") -> 350269 | H93: =IF(H12=TRUE,2,0) -> 2
A94: =A13 -> Other Non Tax Receipts | B94: =IF($H13=TRUE,B13," ") -> 44066 | C94: =IF($H13=TRUE,C13," ") -> 106291 | D94: =IF($H13=TRUE,D13," ") -> 119070 | E94: =IF($H13=TRUE,E13," ") -> 138167 | F94: =IF($H13=TRUE,F13," ") -> 132982 | G94: =IF($H13=TRUE,G13," ") -> 161610 | H94: =IF(H13=TRUE,4,0) -> 4
A95: Total Non Tax Revenue | B95: =SUM(B92:B94) -> 126181 | C95: =SUM(C92:C94) -> 259414 | D95: =SUM(D92:D94) -> 214302 | E95: =SUM(E92:E94) -> 312358 | F95: =SUM(F92:F94) -> 447657 | G95: =SUM(G92:G94) -> 539855 | H95: =SUM(H92:H94) -> 7 | I95: =IF(H95=1,"Interest Receipts",IF(H95=2,"Dividends and Profits",IF(H95=4,"Other Non Tax Receipts",IF(H95=7,"Total Non Tax Revenue"," ")))) -> Total Non Tax Revenue
B97: =B91 -> 2020-21 | C97: =C91 -> 2021-22 | D97: =D91 -> 2022-23 | E97: =E91 -> 2023-24 | F97: =F91 -> 2024-25 | G97: =G91 -> 2025-26
A98: =A15 -> Recovery of Loans & Advances | B98: =IF($H15=TRUE,B15," ") -> 14202 | C98: =IF($H15=TRUE,C15," ") -> 19105 | D98: =IF($H15=TRUE,D15," ") -> 16435 | E98: =IF($H15=TRUE,E15," ") -> 19597 | F98: =IF($H15=TRUE,F15," ") -> 18301 | G98: =IF($H15=TRUE,G15," ") -> 18226 | H98: =IF(H15=TRUE,1,0) -> 1
A99: =A16 -> Misc. Capital Receipts | B99: =IF($H16=TRUE,B16," ") -> 18896 | C99: =IF($H16=TRUE,C16," ") -> 9364 | D99: =IF($H16=TRUE,D16," ") -> 38671 | E99: =IF($H16=TRUE,E16," ") -> 10053 | F99: =IF($H16=TRUE,F16," ") -> 8994 | G99: =IF($H16=TRUE,G16," ") -> 27821 | H99: =IF(H16=TRUE,2,0) -> 2
A100: Non Debt Capital Receipts | B100: =SUM(B98:B99) -> 33098 | C100: =SUM(C98:C99) -> 28469 | D100: =SUM(D98:D99) -> 55106 | E100: =SUM(E98:E99) -> 29650 | F100: =SUM(F98:F99) -> 27295 | G100: =SUM(G98:G99) -> 46047 | H100: =SUM(H98:H99) -> 3 | I100: =IF(H100=1,"Rec. of Loans & Advances",IF(H100=2,"Misc. Capital Receipts",IF(H100=3,"Non Debt Capital Receipts"," " ))) -> Non Debt Capital Receipts
B102: =B97 -> 2020-21 | C102: =C97 -> 2021-22 | D102: =D97 -> 2022-23 | E102: =E97 -> 2023-24 | F102: =F97 -> 2024-25 | G102: =G97 -> 2025-26
A103: =A18 -> Revenue Expenditure | B103: =IF($H18=TRUE,B18," ") -> 1971173 | C103: =IF($H18=TRUE,C18," ") -> 2129414 | D103: =IF($H18=TRUE,D18," ") -> 2328132 | E103: =IF($H18=TRUE,E18," ") -> 2380587 | F103: =IF($H18=TRUE,F18," ") -> 2546757 | G103: =IF($H18=TRUE,G18," ") -> 2593063 | H103: =IF(H18=TRUE,1,0) -> 1
A104: =A19 -> Capital Expenditure | B104: =IF($H19=TRUE,B19," ") -> 308974 | C104: =IF($H19=TRUE,C19," ") -> 391644 | D104: =IF($H19=TRUE,D19," ") -> 489944 | E104: =IF($H19=TRUE,E19," ") -> 673630 | F104: =IF($H19=TRUE,F19," ") -> 685337 | G104: =IF($H19=TRUE,G19," ") -> 787935 | H104: =IF(H19=TRUE,2,0) -> 2
A105: Total Expenditure | B105: =SUM(B103:B104) -> 2280147 | C105: =SUM(C103:C104) -> 2521058 | D105: =SUM(D103:D104) -> 2818076 | E105: =SUM(E103:E104) -> 3054217 | F105: =SUM(F103:F104) -> 3232094 | G105: =SUM(G103:G104) -> 3380998 | H105: =SUM(H103:H104) -> 3 | I105: =IF(H105=1,"Revenue Expenditure",IF(H105=2,"Capital Expenditure",IF(H105=3,"Total Expenditure"," " ))) -> Total Expenditure
A108: % to GDP | B108: =B102 -> 2020-21 | C108: =C102 -> 2021-22 | D108: =D102 -> 2022-23 | E108: =E102 -> 2023-24 | F108: =F102 -> 2024-25 | G108: =G102 -> 2025-26
A109: =A103 -> Revenue Expenditure | B109: =IF($H$103=1,B103/B$59," ") -> 0.099282939 | C109: =IF($H$103=1,C103/C$59," ") -> 0.090239352 | D109: =IF($H$103=1,D103/D$59," ") -> 0.086388222 | E109: =IF($H$103=1,E103/E$59," ") -> 0.080600414 | F109: =IF($H$103=1,F103/F$59," ") -> 0.077015418 | G109: =IF($H$103=1,G103/G$59," ") -> 0.072606577
A110: =A104 -> Capital Expenditure | B110: =IF($H$104=2,B104/B$59," ") -> 0.01556223 | C110: =IF($H$104=2,C104/C$59," ") -> 0.016596914 | D110: =IF($H$104=2,D104/D$59," ") -> 0.018179979 | E110: =IF($H$104=2,E104/E$59," ") -> 0.02280734 | F110: =IF($H$104=2,F104/F$59," ") -> 0.020724991 | G110: =IF($H$104=2,G104/G$59," ") -> 0.022062427
A111: =A105 -> Total Expenditure | B111: =IF($H$105=3,B105/B$59," ") -> 0.11484517 | C111: =IF($H$105=3,C105/C$59," ") -> 0.10683627 | D111: =IF($H$105=3,D105/D$59," ") -> 0.1045682 | E111: =IF($H$105=3,E105/E$59," ") -> 0.10340775 | F111: =IF($H$105=3,F105/F$59," ") -> 0.097740408 | G111: =IF($H$105=3,G105/G$59," ") -> 0.094669004
A113: YoY Growth | C113: =C102 -> 2021-22 | D113: =D102 -> 2022-23 | E113: =E102 -> 2023-24 | F113: =F102 -> 2024-25 | G113: =G102 -> 2025-26
A114: =A109 -> Revenue Expenditure | C114: =C103/B103-1 -> 0.080277581 | D114: =D103/C103-1 -> 0.09332051 | E114: =E103/D103-1 -> 0.022530939 | F114: =F103/E103-1 -> 0.069802112 | G114: =G103/F103-1 -> 0.018182339
A115: =A110 -> Capital Expenditure | C115: =C104/B104-1 -> 0.26756297 | D115: =D104/C104-1 -> 0.25099325 | E115: =E104/D104-1 -> 0.37491223 | F115: =F104/E104-1 -> 0.017378977 | G115: =G104/F104-1 -> 0.14970445
A116: =A111 -> Total Expenditure | C116: =C105/B105-1 -> 0.10565591 | D116: =D105/C105-1 -> 0.11781482 | E116: =E105/D105-1 -> 0.083795114 | F116: =F105/E105-1 -> 0.058239804 | G116: =G105/F105-1 -> 0.046070442
B119: =B102 -> 2020-21 | C119: =C102 -> 2021-22 | D119: =D102 -> 2022-23 | E119: =E102 -> 2023-24 | F119: =F102 -> 2024-25 | G119: =G102 -> 2025-26
A120: =A103 -> Revenue Expenditure | B120: =B103 -> 1971173 | C120: =C103 -> 2129414 | D120: =D103 -> 2328132 | E120: =E103 -> 2380587 | F120: =F103 -> 2546757 | G120: =G103 -> 2593063
A121: =A104 -> Capital Expenditure | B121: =B104 -> 308974 | C121: =C104 -> 391644 | D121: =D104 -> 489944 | E121: =E104 -> 673630 | F121: =F104 -> 685337 | G121: =G104 -> 787935
A122: =A105 -> Total Expenditure | B122: =B105 -> 2280147 | C122: =C105 -> 2521058 | D122: =D105 -> 2818076 | E122: =E105 -> 3054217 | F122: =F105 -> 3232094 | G122: =G105 -> 3380998
A123: =A20 -> BE | B123: =SUM(B124:B125) -> 3042230 | C123: =SUM(C124:C125) -> 3483236 | D123: =SUM(D124:D125) -> 3944909 | E123: =SUM(E124:E125) -> 4503097 | F123: =SUM(F124:F125) -> 4820512 | G123: =SUM(G124:G125) -> 5065345
A124: =A21 -> BE | B124: =IF($H18=TRUE,B21," ") -> 2630221 | C124: =IF($H18=TRUE,C21," ") -> 2929128 | D124: =IF($H18=TRUE,D21," ") -> 3195257 | E124: =IF($H18=TRUE,E21," ") -> 3502724 | F124: =IF($H18=TRUE,F21," ") -> 3709401 | G124: =IF($H18=TRUE,G21," ") -> 3944255
A125: =A22 -> BE | B125: =IF($H19=TRUE,B22," ") -> 412009 | C125: =IF($H19=TRUE,C22," ") -> 554108 | D125: =IF($H19=TRUE,D22," ") -> 749652 | E125: =IF($H19=TRUE,E22," ") -> 1000373 | F125: =IF($H19=TRUE,F22," ") -> 1111111 | G125: =IF($H19=TRUE,G22," ") -> 1121090
B128: =B119 -> 2020-21 | C128: =C119 -> 2021-22 | D128: =D119 -> 2022-23 | E128: =E119 -> 2023-24 | F128: =F119 -> 2024-25 | G128: =G119 -> 2025-26
A129: =A25 -> Interest Payments | B129: =B25 -> 472171 | C129: =C25 -> 565864 | D129: =D25 -> 680853 | E129: =E25 -> 748207 | F129: =F25 -> 808313 | G129: =G25 -> 911059
A130: =A26 -> Defence Services | B130: =B26 -> 153857 | C130: =C26 -> 179859 | D130: =D26 -> 184962 | E130: =E26 -> 215181 | F130: =F26 -> 215520 | G130: =G26 -> 233023
A131: =A27 -> Grants in Aid to States & UTs | B131: =B27 -> 439785 | C131: =C27 -> 426909 | D131: =D27 -> 387918 | E131: =E27 -> 349946 | F131: =F27 -> 348245 | G131: =G27 -> 247273
A132: =A28 -> Pensions | B132: =B28 -> 159146 | C132: =C28 -> 146150 | D132: =D28 -> 168439 | E132: =E28 -> 191905 | F132: =F28 -> 215263 | G132: =G28 -> 226030
A133: =A29 -> Major Subsidies | B133: =B29 -> 227352 | C133: =C29 -> 271374 | D133: =D29 -> 350524 | E133: =E29 -> 276804 | F133: =F29 -> 306994 | G133: =G29 -> 317490
A134: =A30 -> Other Revenue Expenditure | B134: =B30 -> 518862 | C134: =C30 -> 539258 | D134: =D30 -> 555436 | E134: =E30 -> 598544 | F134: =F30 -> 652422 | G134: =G30 -> 658188
A135: Total | B135: =SUM(B129:B134) -> 1971173 | C135: =SUM(C129:C134) -> 2129414 | D135: =SUM(D129:D134) -> 2328132 | E135: =SUM(E129:E134) -> 2380587 | F135: =SUM(F129:F134) -> 2546757 | G135: =SUM(G129:G134) -> 2593063
B137: =B129/B$135 -> 0.23953808 | C137: =C129/C$135 -> 0.26573696 | D137: =D129/D$135 -> 0.29244605 | E137: =E129/E$135 -> 0.31429517 | F137: =F129/F$135 -> 0.31738913 | G137: =G129/G$135 -> 0.35134472
B138: =B130/B$135 -> 0.078053524 | C138: =C130/C$135 -> 0.084464083 | D138: =D130/D$135 -> 0.079446526 | E138: =E130/E$135 -> 0.090389891 | F138: =F130/F$135 -> 0.08462527 | G138: =G130/G$135 -> 0.089863995
B139: =B131/B$135 -> 0.22310827 | C139: =C131/C$135 -> 0.20048192 | D139: =D131/D$135 -> 0.166622 | E139: =E131/E$135 -> 0.14699988 | F139: =F131/F$135 -> 0.13674057 | G139: =G131/G$135 -> 0.095359426
B140: =B132/B$135 -> 0.080736698 | C140: =C132/C$135 -> 0.068633906 | D140: =D132/D$135 -> 0.07234942 | E140: =E132/E$135 -> 0.080612471 | F140: =F132/F$135 -> 0.084524358 | G140: =G132/G$135 -> 0.087167184
B141: =B133/B$135 -> 0.11533843 | C141: =C133/C$135 -> 0.12744069 | D141: =D133/D$135 -> 0.15056019 | E141: =E133/E$135 -> 0.11627552 | F141: =F133/F$135 -> 0.12054311 | G141: =G133/G$135 -> 0.12243821
B142: =B134/B$135 -> 0.26322499 | C142: =C134/C$135 -> 0.25324244 | D142: =D134/D$135 -> 0.23857582 | E142: =E134/E$135 -> 0.25142706 | F142: =F134/F$135 -> 0.25617756 | G142: =G134/G$135 -> 0.25382646
A144: =CONCATENATE("Actuals ", $A$2) -> Actuals (Upto Dec)
B147: =B128 -> 2020-21 | C147: =C128 -> 2021-22 | D147: =D128 -> 2022-23 | E147: =E128 -> 2023-24 | F147: =F128 -> 2024-25 | G147: =G128 -> 2025-26
A148: =A144 -> Actuals (Upto Dec) | B148: =B129 -> 472171 | C148: =C129 -> 565864 | D148: =D129 -> 680853 | E148: =E129 -> 748207 | F148: =F129 -> 808313 | G148: =G129 -> 911059
...

Sheet Sheet5
A3: Row Labels | D3: FY | E3: Month
A4: 2018-19 | C4: Current | D4: =Dashboard!D6 -> 2025-26 | E4: =Dashboard!D8 -> Dec-25 | H4: =MONTH(E4) -> 12 | J4: =MONTH(E4) -> 12 | O4: =VLOOKUP(D4,GDP[],2,0) -> 35713886 | P4: =VLOOKUP(P6,GDP[],2,0) -> 29535667 | Q4: =VLOOKUP(Q6,GDP[],2,0) -> 26949646 | R4: =VLOOKUP(R6,GDP[],2,0) -> 23597399 | S4: =VLOOKUP(S6,GDP[],2,0) -> 19854096
A5: 2019-20 | AG5: =CONCATENATE("Apr-",MID($D$4,3,2)) -> Apr-25 | AH5: =CONCATENATE("Apr-",MID($D$6,3,2)) -> Apr-24 | AI5: =CONCATENATE("Apr-",MID(P$6,3,2)) -> Apr-23 | AJ5: =CONCATENATE("Apr-",MID(Q$6,3,2)) -> Apr-22 | AK5: =CONCATENATE("Apr-",MID(R$6,3,2)) -> Apr-21
A6: 2020-21 | C6: COPPY | D6: =CONCATENATE(LEFT(D4,4)-1,"-",RIGHT(D4,2)-1) -> 2024-25 | E6: =CONCATENATE(LEFT(E4,4),RIGHT(E4,2)-1) -> Dec-24 | O6: =VLOOKUP(D6,GDP[],2,0) -> 33068145 | P6: =CONCATENATE(LEFT(D4,4)-2,"-",RIGHT(D4,2)-2) -> 2023-24 | Q6: =CONCATENATE(LEFT(D4,4)-3,"-",RIGHT(D4,2)-3) -> 2022-23 | R6: =CONCATENATE(LEFT(D4,4)-4,"-",RIGHT(D4,2)-4) -> 2021-22 | S6: =CONCATENATE(LEFT(D4,4)-5,"-",RIGHT(D4,2)-5) -> 2020-21 | U6: =P6 -> 2023-24 | W6: =Q6 -> 2022-23 | Y6: =R6 -> 2021-22 | AA6: =S6 -> 2020-21 | AG6: =CONCATENATE("May-",MID($D$4,3,2)) -> May-25 | AH6: =CONCATENATE("May-",MID($D$6,3,2)) -> May-24 | AI6: =CONCATENATE("May-",MID(P$6,3,2)) -> May-23 | AJ6: =CONCATENATE("May-",MID(Q$6,3,2)) -> May-22 | AK6: =CONCATENATE("May-",MID(R$6,3,2)) -> May-21
A7: 2014-15 | G7: Current | I7: COPPY | P7: =CONCATENATE(LEFT(E4,4),RIGHT(E4,2)-2) -> Dec-23 | Q7: =CONCATENATE(LEFT(E4,4),RIGHT(E4,2)-3) -> Dec-22 | R7: =CONCATENATE(LEFT(E4,4),RIGHT(E4,2)-4) -> Dec-21 | S7: =CONCATENATE(LEFT(E4,4),RIGHT(E4,2)-5) -> Dec-20 | AG7: =CONCATENATE("Jun-",MID($D$4,3,2)) -> Jun-25 | AH7: =CONCATENATE("Jun-",MID($D$6,3,2)) -> Jun-24 | AI7: =CONCATENATE("Jun-",MID(P$6,3,2)) -> Jun-23 | AJ7: =CONCATENATE("Jun-",MID(Q$6,3,2)) -> Jun-22 | AK7: =CONCATENATE("Jun-",MID(R$6,3,2)) -> Jun-21
A8: 2015-16 | E8: Current | F8: COPPY | G8: BE | H8: RE | I8: BE | J8: RE | K8: Growth | L8: ▲▼ | M8: % to BE | N8: % to RE | O8: % to GDP | U8: BE | V8: RE | W8: BE | X8: RE | Y8: BE | Z8: RE | AA8: BE | AB8: RE | AG8: =CONCATENATE("Jul-",MID($D$4,3,2)) -> Jul-25 | AH8: =CONCATENATE("Jul-",MID($D$6,3,2)) -> Jul-24 | AI8: =CONCATENATE("Jul-",MID(P$6,3,2)) -> Jul-23 | AJ8: =CONCATENATE("Jul-",MID(Q$6,3,2)) -> Jul-22 | AK8: =CONCATENATE("Jul-",MID(R$6,3,2)) -> Jul-21
A9: 2016-17 | D9: Total Receipts | E9: =INDEX(actual2[Total Receipts],MATCH($E$4,actual2[Month],0)) -> 2525156 | F9: =INDEX(actual2[Total Receipts],MATCH($E$6,actual2[Month],0)) -> 2318005 | G9: {=INDEX(BERE2[Total Receipts],MATCH($D$4&$G$8,BERE2[FY]&BERE2[Month],0))} -> 3496409 | H9: {=INDEX(BERE2[Total Receipts],MATCH($D$4&$H$8,BERE2[FY]&BERE2[Month],0))} -> #N/A | I9: {=INDEX(BERE2[Total Receipts],MATCH($D$6&$I$8,BERE2[FY]&BERE2[Month],0))} -> 3207200 | J9: {=INDEX(BERE2[Total Receipts],MATCH($D$6&$J$8,BERE2[FY]&BERE2[Month],0))} -> 3146960 | K9: =(E9-F9)/ABS(F9) -> 0.089366071 | L9: =(E9-F9)/ABS(F9) -> 0.089366071 | M9: =E9/G9 -> 0.72221413 | N9: =E9/H9 -> #N/A | O9: =E9/O$4 -> 0.070705159 | P9: =INDEX(actual2[Total Receipts],MATCH(P$7,actual2[Month],0)) -> 2071939 | Q9: =INDEX(actual2[Total Receipts],MATCH(Q$7,actual2[Month],0)) -> 1825100 | R9: =INDEX(actual2[Total Receipts],MATCH(R$7,actual2[Month],0)) -> 1761692 | S9: =INDEX(actual2[Total Receipts],MATCH(S$7,actual2[Month],0)) -> 1121678 | AG9: =CONCATENATE("Aug-",MID($D$4,3,2)) -> Aug-25 | AH9: =CONCATENATE("Aug-",MID($D$6,3,2)) -> Aug-24 | AI9: =CONCATENATE("Aug-",MID(P$6,3,2)) -> Aug-23 | AJ9: =CONCATENATE("Aug-",MID(Q$6,3,2)) -> Aug-22 | AK9: =CONCATENATE("Aug-",MID(R$6,3,2)) -> Aug-21
A10: 2017-18 | AG10: =CONCATENATE("Sep-",MID($D$4,3,2)) -> Sep-25 | AH10: =CONCATENATE("Sep-",MID($D$6,3,2)) -> Sep-24 | AI10: =CONCATENATE("Sep-",MID(P$6,3,2)) -> Sep-23 | AJ10: =CONCATENATE("Sep-",MID(Q$6,3,2)) -> Sep-22 | AK10: =CONCATENATE("Sep-",MID(R$6,3,2)) -> Sep-21
A11: (blank) | D11: Total expenditure | E11: =INDEX(actual2[Total Expenditure],MATCH($E$4,actual2[Month],0)) -> 3380998 | F11: =INDEX(actual2[Total Expenditure],MATCH($E$6,actual2[Month],0)) -> 3232094 | G11: {=INDEX(BERE2[Total Expenditure],MATCH($D$4&$G$8,BERE2[FY]&BERE2[Month],0))} -> 5065345 | H11: {=INDEX(BERE2[Total Expenditure],MATCH($D$4&$H$8,BERE2[FY]&BERE2[Month],0))} -> #N/A | I11: {=INDEX(BERE2[Total Expenditure],MATCH($D$6&$I$8,BERE2[FY]&BERE2[Month],0))} -> 4820512 | J11: {=INDEX(BERE2[Total Expenditure],MATCH($D$6&$J$8,BERE2[FY]&BERE2[Month],0))} -> 4716487 | K11: =(E11-F11)/ABS(F11) -> 0.046070442 | L11: =(E11-F11)/ABS(F11) -> 0.046070442 | M11: =E11/G11 -> 0.66747635 | N11: =E11/H11 -> #N/A | O11: =E11/O$4 -> 0.094669004 | P11: =INDEX(actual2[Total Expenditure],MATCH(P$7,actual2[Month],0)) -> 3054217 | Q11: =INDEX(actual2[Total Expenditure],MATCH(Q$7,actual2[Month],0)) -> 2818076 | R11: =INDEX(actual2[Total Expenditure],MATCH(R$7,actual2[Month],0)) -> 2521058 | S11: =INDEX(actual2[Total Expenditure],MATCH(S$7,actual2[Month],0)) -> 2280147 | U11: {=INDEX(BERE2[Total Expenditure],MATCH($U$6&U$8,BERE2[FY]&BERE2[Month],0))} -> 4503097 | V11: {=INDEX(BERE2[Total Expenditure],MATCH($U$6&V$8,BERE2[FY]&BERE2[Month],0))} -> 4490486 | W11: {=INDEX(BERE2[Total Expenditure],MATCH($W$6&W$8,BERE2[FY]&BERE2[Month],0))} -> 3944909 | X11: {=INDEX(BERE2[Total Expenditure],MATCH($W$6&X$8,BERE2[FY]&BERE2[Month],0))} -> 4187232 | Y11: {=INDEX(BERE2[Total Expenditure],MATCH($Y$6&Y$8,BERE2[FY]&BERE2[Month],0))} -> 3483236 | Z11: {=INDEX(BERE2[Total Expenditure],MATCH($Y$6&Z$8,BERE2[FY]&BERE2[Month],0))} -> 3770000 | AA11: {=INDEX(BERE2[Total Expenditure],MATCH($AA$6&AA$8,BERE2[FY]&BERE2[Month],0))} -> 3042230 | AB11: {=INDEX(BERE2[Total Expenditure],MATCH($AA$6&AB$8,BERE2[FY]&BERE2[Month],0))} -> 3450305 | AG11: =CONCATENATE("Oct-",MID($D$4,3,2)) -> Oct-25 | AH11: =CONCATENATE("Oct-",MID($D$6,3,2)) -> Oct-24 | AI11: =CONCATENATE("Oct-",MID(P$6,3,2)) -> Oct-23 | AJ11: =CONCATENATE("Oct-",MID(Q$6,3,2)) -> Oct-22 | AK11: =CONCATENATE("Oct-",MID(R$6,3,2)) -> Oct-21
A12: 2021-22 | AG12: =CONCATENATE("Nov-",MID($D$4,3,2)) -> Nov-25 | AH12: =CONCATENATE("Nov-",MID($D$6,3,2)) -> Nov-24 | AI12: =CONCATENATE("Nov-",MID(P$6,3,2)) -> Nov-23 | AJ12: =CONCATENATE("Nov-",MID(Q$6,3,2)) -> Nov-22 | AK12: =CONCATENATE("Nov-",MID(R$6,3,2)) -> Nov-21
A13: 2022-23 | D13: Fiscal Deficit | E13: =INDEX(actual2[Fiscal Deficit],MATCH($E$4,actual2[Month],0)) -> 855842 | F13: =INDEX(actual2[Fiscal Deficit],MATCH($E$6,actual2[Month],0)) -> 914089 | G13: {=INDEX(BERE2[Fiscal Deficit],MATCH($D$4&$G$8,BERE2[FY]&BERE2[Month],0))} -> 1568936 | H13: {=INDEX(BERE2[Fiscal Deficit],MATCH($D$4&$H$8,BERE2[FY]&BERE2[Month],0))} -> #N/A | I13: {=INDEX(BERE2[Fiscal Deficit],MATCH($D$6&$I$8,BERE2[FY]&BERE2[Month],0))} -> 1613312 | J13: {=INDEX(BERE2[Fiscal Deficit],MATCH($D$6&$J$8,BERE2[FY]&BERE2[Month],0))} -> 1569527 | K13: =(E13-F13)/ABS(F13) -> -0.063721366 | L13: =(E13-F13)/ABS(F13) -> -0.063721366 | M13: =E13/G13 -> 0.54549198 | N13: =E13/H13 -> #N/A | O13: =E13/O$4 -> 0.023963844 | P13: =INDEX(actual2[Fiscal Deficit],MATCH(P$7,actual2[Month],0)) -> 982278 | Q13: =INDEX(actual2[Fiscal Deficit],MATCH(Q$7,actual2[Month],0)) -> 992976 | R13: =INDEX(actual2[Fiscal Deficit],MATCH(R$7,actual2[Month],0)) -> 759366 | S13: =INDEX(actual2[Fiscal Deficit],MATCH(S$7,actual2[Month],0)) -> 1158469 | U13: {=INDEX(BERE2[Fiscal Deficit],MATCH($U$6&U$8,BERE2[FY]&BERE2[Month],0))} -> 1786816 | V13: {=INDEX(BERE2[Fiscal Deficit],MATCH($U$6&V$8,BERE2[FY]&BERE2[Month],0))} -> 1734773 | W13: {=INDEX(BERE2[Fiscal Deficit],MATCH($W$6&W$8,BERE2[FY]&BERE2[Month],0))} -> 1661196 | X13: {=INDEX(BERE2[Fiscal Deficit],MATCH($W$6&X$8,BERE2[FY]&BERE2[Month],0))} -> 1755319 | Y13: {=INDEX(BERE2[Fiscal Deficit],MATCH($Y$6&Y$8,BERE2[FY]&BERE2[Month],0))} -> 1506812 | Z13: {=INDEX(BERE2[Fiscal Deficit],MATCH($Y$6&Z$8,BERE2[FY]&BERE2[Month],0))} -> 1591089 | AA13: {=INDEX(BERE2[Fiscal Deficit],MATCH($AA$6&AA$8,BERE2[FY]&BERE2[Month],0))} -> 796337 | AB13: {=INDEX(BERE2[Fiscal Deficit],MATCH($AA$6&AB$8,BERE2[FY]&BERE2[Month],0))} -> 1848655 | AG13: =CONCATENATE("Dec-",MID($D$4,3,2)) -> Dec-25 | AH13: =CONCATENATE("Dec-",MID($D$6,3,2)) -> Dec-24 | AI13: =CONCATENATE("Dec-",MID(P$6,3,2)) -> Dec-23 | AJ13: =CONCATENATE("Dec-",MID(Q$6,3,2)) -> Dec-22 | AK13: =CONCATENATE("Dec-",MID(R$6,3,2)) -> Dec-21
A14: 2023-24 | AG14: =CONCATENATE("Jan-",MID($D$4,6,2)) -> Jan-26 | AH14: =CONCATENATE("Jan-",MID($D$6,6,2)) -> Jan-25 | AI14: =CONCATENATE("Jan-",MID(P$6,6,2)) -> Jan-24 | AJ14: =CONCATENATE("Jan-",MID(Q$6,6,2)) -> Jan-23 | AK14: =CONCATENATE("Jan-",MID(R$6,6,2)) -> Jan-22
A15: 2024-25 | D15: Net Tax Revenue | E15: =INDEX(actual2[Net Tax Revenue],MATCH($E$4,actual2[Month],0)) -> 1939254 | F15: =INDEX(actual2[Net Tax Revenue],MATCH($E$6,actual2[Month],0)) -> 1843053 | G15: {=INDEX(BERE2[Net Tax Revenue],MATCH($D$4&$G$8,BERE2[FY]&BERE2[Month],0))} -> 2837409 | H15: {=INDEX(BERE2[Net Tax Revenue],MATCH($D$4&$H$8,BERE2[FY]&BERE2[Month],0))} -> #N/A | I15: {=INDEX(BERE2[Net Tax Revenue],MATCH($D$6&$I$8,BERE2[FY]&BERE2[Month],0))} -> 2583499 | J15: {=INDEX(BERE2[Net Tax Revenue],MATCH($D$6&$J$8,BERE2[FY]&BERE2[Month],0))} -> 2556960 | K15: =(E15-F15)/ABS(F15) -> 0.052196546 | L15: =(E15-F15)/ABS(F15) -> 0.052196546 | M15: =E15/G15 -> 0.68345945 | N15: =E15/H15 -> #N/A | O15: =E15/O$4 -> 0.05429972 | P15: =INDEX(actual2[Net Tax Revenue],MATCH(P$7,actual2[Month],0)) -> 1729931 | Q15: =INDEX(actual2[Net Tax Revenue],MATCH(Q$7,actual2[Month],0)) -> 1555692 | R15: =INDEX(actual2[Net Tax Revenue],MATCH(R$7,actual2[Month],0)) -> 1473809 | S15: =INDEX(actual2[Net Tax Revenue],MATCH(S$7,actual2[Month],0)) -> 962399 | AG15: =CONCATENATE("Feb-",MID($D$4,6,2)) -> Feb-26 | AH15: =CONCATENATE("Feb-",MID($D$6,6,2)) -> Feb-25 | AI15: =CONCATENATE("Feb-",MID(P$6,6,2)) -> Feb-24 | AJ15: =CONCATENATE("Feb-",MID(Q$6,6,2)) -> Feb-23 | AK15: =CONCATENATE("Feb-",MID(R$6,6,2)) -> Feb-22
A16: 2025-26 | AG16: =CONCATENATE("Mar-",MID($D$4,6,2)) -> Mar-26 | AH16: =CONCATENATE("Mar-",MID($D$6,6,2)) -> Mar-25 | AI16: =CONCATENATE("Mar-",MID(P$6,6,2)) -> Mar-24 | AJ16: =CONCATENATE("Mar-",MID(Q$6,6,2)) -> Mar-23 | AK16: =CONCATENATE("Mar-",MID(R$6,6,2)) -> Mar-22
D17: Non Tax Revenue | E17: =INDEX(actual2[Non Tax Revenue],MATCH($E$4,actual2[Month],0)) -> 539855 | F17: =INDEX(actual2[Non Tax Revenue],MATCH($E$6,actual2[Month],0)) -> 447657 | G17: {=INDEX(BERE2[Non Tax Revenue],MATCH($D$4&$G$8,BERE2[FY]&BERE2[Month],0))} -> 583000 | H17: {=INDEX(BERE2[Non Tax Revenue],MATCH($D$4&$H$8,BERE2[FY]&BERE2[Month],0))} -> #N/A | I17: {=INDEX(BERE2[Non Tax Revenue],MATCH($D$6&$I$8,BERE2[FY]&BERE2[Month],0))} -> 545701 | J17: {=INDEX(BERE2[Non Tax Revenue],MATCH($D$6&$J$8,BERE2[FY]&BERE2[Month],0))} -> 531000 | K17: =(E17-F17)/ABS(F17) -> 0.20595679 | L17: =(E17-F17)/ABS(F17) -> 0.20595679 | M17: =E17/G17 -> 0.92599485 | N17: =E17/H17 -> #N/A | O17: =E17/O$4 -> 0.015116109 | P17: =INDEX(actual2[Non Tax Revenue],MATCH(P$7,actual2[Month],0)) -> 312358 | Q17: =INDEX(actual2[Non Tax Revenue],MATCH(Q$7,actual2[Month],0)) -> 214302 | R17: =INDEX(actual2[Non Tax Revenue],MATCH(R$7,actual2[Month],0)) -> 259414 | S17: =INDEX(actual2[Non Tax Revenue],MATCH(S$7,actual2[Month],0)) -> 126181
D19: Non Debt Capital Receipts | E19: =INDEX(actual2[Non Debt Capital Receipts],MATCH($E$4,actual2[Month],0)) -> 46047 | F19: =INDEX(actual2[Non Debt Capital Receipts],MATCH($E$6,actual2[Month],0)) -> 27295 | G19: {=INDEX(BERE2[Non Debt Capital Receipts],MATCH($D$4&$G$8,BERE2[FY]&BERE2[Month],0))} -> 76000 | H19: {=INDEX(BERE2[Non Debt Capital Receipts],MATCH($D$4&$H$8,BERE2[FY]&BERE2[Month],0))} -> #N/A | I19: {=INDEX(BERE2[Non Debt Capital Receipts],MATCH($D$6&$I$8,BERE2[FY]&BERE2[Month],0))} -> 78000 | J19: {=INDEX(BERE2[Non Debt Capital Receipts],MATCH($D$6&$J$8,BERE2[FY]&BERE2[Month],0))} -> 59000 | K19: =(E19-F19)/ABS(F19) -> 0.68701227 | L19: =(E19-F19)/ABS(F19) -> 0.68701227 | M19: =E19/G19 -> 0.60588158 | N19: =E19/H19 -> #N/A | O19: =E19/O$4 -> 0.0012893304 | P19: =INDEX(actual2[Non Debt Capital Receipts],MATCH(P$7,actual2[Month],0)) -> 29650 | Q19: =INDEX(actual2[Non Debt Capital Receipts],MATCH(Q$7,actual2[Month],0)) -> 55106 | R19: =INDEX(actual2[Non Debt Capital Receipts],MATCH(R$7,actual2[Month],0)) -> 28469 | S19: =INDEX(actual2[Non Debt Capital Receipts],MATCH(S$7,actual2[Month],0)) -> 33098
D21: Revenue Expenditure | E21: =INDEX(actual1[Revenue Expenditure],MATCH($E$4,actual1[Month],0)) -> 2593063 | F21: =INDEX(actual1[Revenue Expenditure],MATCH($E$6,actual1[Month],0)) -> 2546757 | G21: {=INDEX(BERE1[Revenue Expenditure],MATCH($D$4&$G$8,BERE2[FY]&BERE1[Month],0))} -> 3944255 | H21: {=INDEX(BERE1[Revenue Expenditure],MATCH($D$4&$H$8,BERE1[FY]&BERE2[Month],0))} -> #N/A | I21: {=INDEX(BERE1[Revenue Expenditure],MATCH($D$6&$I$8,BERE1[FY]&BERE1[Month],0))} -> 3709401 | J21: {=INDEX(BERE1[Revenue Expenditure],MATCH($D$6&$J$8,BERE1[FY]&BERE1[Month],0))} -> 3698058 | K21: =(E21-F21)/ABS(F21) -> 0.018182339 | L21: =(E21-F21)/ABS(F21) -> 0.018182339 | M21: =E21/G21 -> 0.65742783 | N21: =E21/H21 -> #N/A | O21: =E21/O$4 -> 0.072606577 | P21: =INDEX(actual1[Revenue Expenditure],MATCH(P$7,actual1[Month],0)) -> 2380587 | Q21: =INDEX(actual1[Revenue Expenditure],MATCH(Q$7,actual1[Month],0)) -> 2328132 | R21: =INDEX(actual1[Revenue Expenditure],MATCH(R$7,actual1[Month],0)) -> 2129414 | S21: =INDEX(actual1[Revenue Expenditure],MATCH(S$7,actual1[Month],0)) -> 1971173 | U21: {=INDEX(BERE1[Revenue Expenditure],MATCH($U$6&U$8,BERE1[FY]&BERE1[Month],0))} -> 3502724 | V21: {=INDEX(BERE1[Revenue Expenditure],MATCH($U$6&V$8,BERE1[FY]&BERE1[Month],0))} -> 3540931 | W21: {=INDEX(BERE1[Revenue Expenditure],MATCH($W$6&W$8,BERE1[FY]&BERE1[Month],0))} -> 3195257 | X21: {=INDEX(BERE1[Revenue Expenditure],MATCH($W$6&X$8,BERE1[FY]&BERE1[Month],0))} -> 3459464 | Y21: {=INDEX(BERE1[Revenue Expenditure],MATCH($Y$6&Y$8,BERE1[FY]&BERE1[Month],0))} -> 2929128 | Z21: {=INDEX(BERE1[Revenue Expenditure],MATCH($Y$6&Z$8,BERE1[FY]&BERE1[Month],0))} -> 3168067 | AA21: {=INDEX(BERE1[Revenue Expenditure],MATCH($AA$6&AA$8,BERE1[FY]&BERE1[Month],0))} -> 2630221 | AB21: {=INDEX(BERE1[Revenue Expenditure],MATCH($AA$6&AB$8,BERE1[FY]&BERE1[Month],0))} -> 3011916
AH22: =D4 -> 2025-26 | AI22: =D6 -> 2024-25
D23: Capital Expenditure | E23: =INDEX(actual1[Capital Expenditure],MATCH($E$4,actual1[Month],0)) -> 787935 | F23: =INDEX(actual1[Capital Expenditure],MATCH($E$6,actual1[Month],0)) -> 685337 | G23: {=INDEX(BERE1[Capital Expenditure],MATCH($D$4&$G$8,BERE1[FY]&BERE1[Month],0))} -> 1121090 | H23: {=INDEX(BERE1[Capital Expenditure],MATCH($D$4&$H$8,BERE1[FY]&BERE1[Month],0))} -> #N/A | I23: {=INDEX(BERE1[Capital Expenditure],MATCH($D$6&$I$8,BERE1[FY]&BERE1[Month],0))} -> 1111111 | J23: {=INDEX(BERE1[Capital Expenditure],MATCH($D$6&$J$8,BERE1[FY]&BERE1[Month],0))} -> 1018429 | K23: =(E23-F23)/ABS(F23) -> 0.14970445 | L23: =(E23-F23)/ABS(F23) -> 0.14970445 | M23: =E23/G23 -> 0.70282939 | N23: =E23/H23 -> #N/A | O23: =E23/O$4 -> 0.022062427 | P23: =INDEX(actual1[Capital Expenditure],MATCH(P$7,actual1[Month],0)) -> 673630 | Q23: =INDEX(actual1[Capital Expenditure],MATCH(Q$7,actual1[Month],0)) -> 489944 | R23: =INDEX(actual1[Capital Expenditure],MATCH(R$7,actual1[Month],0)) -> 391644 | S23: =INDEX(actual1[Capital Expenditure],MATCH(S$7,actual1[Month],0)) -> 308974 | U23: {=INDEX(BERE1[Capital Expenditure],MATCH($U$6&U$8,BERE1[FY]&BERE1[Month],0))} -> 1000373 | V23: {=INDEX(BERE1[Capital Expenditure],MATCH($U$6&V$8,BERE1[FY]&BERE1[Month],0))} -> 949555 | W23: {=INDEX(BERE1[Capital Expenditure],MATCH($W$6&W$8,BERE1[FY]&BERE1[Month],0))} -> 749652 | X23: {=INDEX(BERE1[Capital Expenditure],MATCH($W$6&X$8,BERE1[FY]&BERE1[Month],0))} -> 727768 | Y23: {=INDEX(BERE1[Capital Expenditure],MATCH($Y$6&Y$8,BERE1[FY]&BERE1[Month],0))} -> 554108 | Z23: {=INDEX(BERE1[Capital Expenditure],MATCH($Y$6&Z$8,BERE1[FY]&BERE1[Month],0))} -> 601933 | AA23: {=INDEX(BERE1[Capital Expenditure],MATCH($AA$6&AA$8,BERE1[FY]&BERE1[Month],0))} -> 412009 | AB23: {=INDEX(BERE1[Capital Expenditure],MATCH($AA$6&AB$8,BERE1[FY]&BERE1[Month],0))} -> 438389 | AG23: Apr | AH23: =INDEX(actual2[Total Receipts],MATCH(AG5,actual2[Month],0)) -> 279288 | AI23: =INDEX(actual2[Total Receipts],MATCH(AH5,actual2[Month],0)) -> 213334
AG24: May | AH24: =INDEX(actual2[Total Receipts],MATCH(AG6,actual2[Month],0)) -> 732963 | AI24: =INDEX(actual2[Total Receipts],MATCH(AH6,actual2[Month],0)) -> 572845
D25: Interest Payments | E25: =INDEX(actual1[Interest Payments],MATCH($E$4,actual1[Month],0)) -> 911059 | F25: =INDEX(actual1[Interest Payments],MATCH($E$6,actual1[Month],0)) -> 808313 | G25: {=INDEX(BERE1[Interest Payments],MATCH($D$4&$G$8,BERE1[FY]&BERE1[Month],0))} -> 1276338 | H25: {=INDEX(BERE1[Interest Payments],MATCH($D$4&$H$8,BERE1[FY]&BERE1[Month],0))} -> #N/A | I25: {=INDEX(BERE1[Interest Payments],MATCH($D$6&$I$8,BERE1[FY]&BERE1[Month],0))} -> 1162940 | J25: {=INDEX(BERE1[Interest Payments],MATCH($D$6&$J$8,BERE1[FY]&BERE1[Month],0))} -> 1137940 | K25: =(E25-F25)/ABS(F25) -> 0.12711165 | L25: =(E25-F25)/ABS(F25) -> 0.12711165 | M25: =E25/G25 -> 0.713807 | N25: =E25/H25 -> #N/A | O25: =E25/O$4 -> 0.025509938 | P25: =INDEX(actual1[Interest Payments],MATCH(P$7,actual1[Month],0)) -> 748207 | Q25: =INDEX(actual1[Interest Payments],MATCH(Q$7,actual1[Month],0)) -> 680853 | R25: =INDEX(actual1[Interest Payments],MATCH(R$7,actual1[Month],0)) -> 565864 | S25: =INDEX(actual1[Interest Payments],MATCH(S$7,actual1[Month],0)) -> 472171 | U25: {=INDEX(BERE1[Interest Payments],MATCH($U$6&U$8,BERE1[FY]&BERE1[Month],0))} -> 1079971 | V25: {=INDEX(BERE1[Interest Payments],MATCH($U$6&V$8,BERE1[FY]&BERE1[Month],0))} -> 1055427 | W25: {=INDEX(BERE1[Interest Payments],MATCH($W$6&W$8,BERE1[FY]&BERE1[Month],0))} -> 940651 | X25: {=INDEX(BERE1[Interest Payments],MATCH($W$6&X$8,BERE1[FY]&BERE1[Month],0))} -> 940651 | Y25: {=INDEX(BERE1[Interest Payments],MATCH($Y$6&Y$8,BERE1[FY]&BERE1[Month],0))} -> 809701 | Z25: {=INDEX(BERE1[Interest Payments],MATCH($Y$6&Z$8,BERE1[FY]&BERE1[Month],0))} -> 813791 | AA25: {=INDEX(BERE1[Interest Payments],MATCH($AA$6&AA$8,BERE1[FY]&BERE1[Month],0))} -> 708203 | AB25: {=INDEX(BERE1[Interest Payments],MATCH($AA$6&AB$8,BERE1[FY]&BERE1[Month],0))} -> 692900 | AG25: Jun | AH25: =INDEX(actual2[Total Receipts],MATCH(AG7,actual2[Month],0)) -> 941395 | AI25: =INDEX(actual2[Total Receipts],MATCH(AH7,actual2[Month],0)) -> 834197
AG26: Jul | AH26: =INDEX(actual2[Total Receipts],MATCH(AG8,actual2[Month],0)) -> 1095209 | AI26: =INDEX(actual2[Total Receipts],MATCH(AH8,actual2[Month],0)) -> 1023406
D27: Defence Services | E27: =INDEX(actual1[Defence Services],MATCH($E$4,actual1[Month],0)) -> 233023 | F27: =INDEX(actual1[Defence Services],MATCH($E$6,actual1[Month],0)) -> 215520 | G27: {=INDEX(BERE1[Defence Services],MATCH($D$4&$G$8,BERE1[FY]&BERE1[Month],0))} -> 311732 | H27: {=INDEX(BERE1[Defence Services],MATCH($D$4&$H$8,BERE1[FY]&BERE1[Month],0))} -> #N/A | I27: {=INDEX(BERE1[Defence Services],MATCH($D$6&$I$8,BERE1[FY]&BERE1[Month],0))} -> 282773 | J27: {=INDEX(BERE1[Defence Services],MATCH($D$6&$J$8,BERE1[FY]&BERE1[Month],0))} -> 297222 | K27: =(E27-F27)/ABS(F27) -> 0.08121288 | L27: =(E27-F27)/ABS(F27) -> 0.08121288 | M27: =E27/G27 -> 0.74751068 | N27: =E27/H27 -> #N/A | O27: =E27/O$4 -> 0.006524717 | P27: =INDEX(actual1[Defence Services],MATCH(P$7,actual1[Month],0)) -> 215181 | Q27: =INDEX(actual1[Defence Services],MATCH(Q$7,actual1[Month],0)) -> 184962 | R27: =INDEX(actual1[Defence Services],MATCH(R$7,actual1[Month],0)) -> 179859 | S27: =INDEX(actual1[Defence Services],MATCH(S$7,actual1[Month],0)) -> 153857 | U27: {=INDEX(BERE1[Defence Services],MATCH($U$6&U$8,BERE1[FY]&BERE1[Month],0))} -> 270120 | V27: {=INDEX(BERE1[Defence Services],MATCH($U$6&V$8,BERE1[FY]&BERE1[Month],0))} -> 298669 | W27: {=INDEX(BERE1[Defence Services],MATCH($W$6&W$8,BERE1[FY]&BERE1[Month],0))} -> 233001 | X27: {=INDEX(BERE1[Defence Services],MATCH($W$6&X$8,BERE1[FY]&BERE1[Month],0))} -> 259500 | Y27: {=INDEX(BERE1[Defence Services],MATCH($Y$6&Y$8,BERE1[FY]&BERE1[Month],0))} -> 212028 | Z27: {=INDEX(BERE1[Defence Services],MATCH($Y$6&Z$8,BERE1[FY]&BERE1[Month],0))} -> 229567 | AA27: {=INDEX(BERE1[Defence Services],MATCH($AA$6&AA$8,BERE1[FY]&BERE1[Month],0))} -> 209319 | AB27: {=INDEX(BERE1[Defence Services],MATCH($AA$6&AB$8,BERE1[FY]&BERE1[Month],0))} -> 209312 | AG27: Aug | AH27: =INDEX(actual2[Total Receipts],MATCH(AG9,actual2[Month],0)) -> 1282709 | AI27: =INDEX(actual2[Total Receipts],MATCH(AH9,actual2[Month],0)) -> 1217178
AG28: Sep | AH28: =INDEX(actual2[Total Receipts],MATCH(AG10,actual2[Month],0)) -> 1730216 | AI28: =INDEX(actual2[Total Receipts],MATCH(AH10,actual2[Month],0)) -> 1636974
D29: Grants in Aid to States & UTs | E29: =INDEX(actual1[Grants in Aid to States & UTs],MATCH($E$4,actual1[Month],0)) -> 247273 | F29: =INDEX(actual1[Grants in Aid to States & UTs],MATCH($E$6,actual1[Month],0)) -> 348245 | G29: {=INDEX(BERE1[Grants in Aid to States & UTs],MATCH($D$4&$G$8,BERE1[FY]&BERE1[Month],0))} -> 720056 | H29: {=INDEX(BERE1[Grants in Aid to States & UTs],MATCH($D$4&$H$8,BERE1[FY]&BERE1[Month],0))} -> #N/A | I29: {=INDEX(BERE1[Grants in Aid to States & UTs],MATCH($D$6&$I$8,BERE1[FY]&BERE1[Month],0))} -> 641460 | J29: {=INDEX(BERE1[Grants in Aid to States & UTs],MATCH($D$6&$J$8,BERE1[FY]&BERE1[Month],0))} -> 594207 | K29: =(E29-F29)/ABS(F29) -> -0.2899453 | L29: =(E29-F29)/ABS(F29) -> -0.2899453 | M29: =E29/G29 -> 0.34340801 | N29: =E29/H29 -> #N/A | O29: =E29/O$4 -> 0.0069237215 | P29: =INDEX(actual1[Grants in Aid to States & UTs],MATCH(P$7,actual1[Month],0)) -> 349946 | Q29: =INDEX(actual1[Grants in Aid to States & UTs],MATCH(Q$7,actual1[Month],0)) -> 387918 | R29: =INDEX(actual1[Grants in Aid to States & UTs],MATCH(R$7,actual1[Month],0)) -> 426909 | S29: =INDEX(actual1[Grants in Aid to States & UTs],MATCH(S$7,actual1[Month],0)) -> 439785 | U29: {=INDEX(BERE1[Grants in Aid to States & UTs],MATCH($U$6&U$8,BERE1[FY]&BERE1[Month],0))} -> 659736 | V29: {=INDEX(BERE1[Grants in Aid to States & UTs],MATCH($U$6&V$8,BERE1[FY]&BERE1[Month],0))} -> 590531 | W29: {=INDEX(BERE1[Grants in Aid to States & UTs],MATCH($W$6&W$8,BERE1[FY]&BERE1[Month],0))} -> 617057 | X29: {=INDEX(BERE1[Grants in Aid to States & UTs],MATCH($W$6&X$8,BERE1[FY]&BERE1[Month],0))} -> 613196 | Y29: {=INDEX(BERE1[Grants in Aid to States & UTs],MATCH($Y$6&Y$8,BERE1[FY]&BERE1[Month],0))} -> 605812 | Z29: {=INDEX(BERE1[Grants in Aid to States & UTs],MATCH($Y$6&Z$8,BERE1[FY]&BERE1[Month],0))} -> 587918 | AA29: {=INDEX(BERE1[Grants in Aid to States & UTs],MATCH($AA$6&AA$8,BERE1[FY]&BERE1[Month],0))} -> 562046 | AB29: {=INDEX(BERE1[Grants in Aid to States & UTs],MATCH($AA$6&AB$8,BERE1[FY]&BERE1[Month],0))} -> 559025 | AG29: Oct | AH29: =INDEX(actual2[Total Receipts],MATCH(AG11,actual2[Month],0)) -> 1800475 | AI29: =INDEX(actual2[Total Receipts],MATCH(AH11,actual2[Month],0)) -> 1723074
AG30: Nov | AH30: =INDEX(actual2[Total Receipts],MATCH(AG12,actual2[Month],0)) -> 1949239 | AI30: =INDEX(actual2[Total Receipts],MATCH(AH12,actual2[Month],0)) -> 1894408
D31: Pensions | E31: =INDEX(actual1[Pensions],MATCH($E$4,actual1[Month],0)) -> 226030 | F31: =INDEX(actual1[Pensions],MATCH($E$6,actual1[Month],0)) -> 215263 | G31: {=INDEX(BERE1[Pensions],MATCH($D$4&$G$8,BERE1[FY]&BERE1[Month],0))} -> 276618 | H31: {=INDEX(BERE1[Pensions],MATCH($D$4&$H$8,BERE1[FY]&BERE1[Month],0))} -> #N/A | I31: {=INDEX(BERE1[Pensions],MATCH($D$6&$I$8,BERE1[FY]&BERE1[Month],0))} -> 243296 | J31: {=INDEX(BERE1[Pensions],MATCH($D$6&$J$8,BERE1[FY]&BERE1[Month],0))} -> 275103 | K31: =(E31-F31)/ABS(F31) -> 0.050017885 | L31: =(E31-F31)/ABS(F31) -> 0.050017885 | M31: =E31/G31 -> 0.81711964 | N31: =E31/H31 -> #N/A | O31: =E31/O$4 -> 0.0063289108 | P31: =INDEX(actual1[Pensions],MATCH(P$7,actual1[Month],0)) -> 191905 | Q31: =INDEX(actual1[Pensions],MATCH(Q$7,actual1[Month],0)) -> 168439 | R31: =INDEX(actual1[Pensions],MATCH(R$7,actual1[Month],0)) -> 146150 | S31: =INDEX(actual1[Pensions],MATCH(S$7,actual1[Month],0)) -> 159146 | U31: {=INDEX(BERE1[Pensions],MATCH($U$6&U$8,BERE1[FY]&BERE1[Month],0))} -> 234359 | V31: {=INDEX(BERE1[Pensions],MATCH($U$6&V$8,BERE1[FY]&BERE1[Month],0))} -> 238049 | W31: {=INDEX(BERE1[Pensions],MATCH($W$6&W$8,BERE1[FY]&BERE1[Month],0))} -> 207132 | X31: {=INDEX(BERE1[Pensions],MATCH($W$6&X$8,BERE1[FY]&BERE1[Month],0))} -> 244780 | Y31: {=INDEX(BERE1[Pensions],MATCH($Y$6&Y$8,BERE1[FY]&BERE1[Month],0))} -> 190328 | Z31: {=INDEX(BERE1[Pensions],MATCH($Y$6&Z$8,BERE1[FY]&BERE1[Month],0))} -> 198962 | AA31: {=INDEX(BERE1[Pensions],MATCH($AA$6&AA$8,BERE1[FY]&BERE1[Month],0))} -> 210682 | AB31: {=INDEX(BERE1[Pensions],MATCH($AA$6&AB$8,BERE1[FY]&BERE1[Month],0))} -> 204393 | AG31: Dec | AH31: =INDEX(actual2[Total Receipts],MATCH(AG13,actual2[Month],0)) -> 2525156 | AI31: =INDEX(actual2[Total Receipts],MATCH(AH13,actual2[Month],0)) -> 2318005
AG32: Jan | AH32: =INDEX(actual2[Total Receipts],MATCH(AG14,actual2[Month],0)) -> #N/A | AI32: =INDEX(actual2[Total Receipts],MATCH(AH14,actual2[Month],0)) -> 2400412
D33: Major Subsidies | E33: =INDEX(actual1[Major Subsidies],MATCH($E$4,actual1[Month],0)) -> 317490 | F33: =INDEX(actual1[Major Subsidies],MATCH($E$6,actual1[Month],0)) -> 306994 | G33: {=INDEX(BERE1[Major Subsidies],MATCH($D$4&$G$8,BERE1[FY]&BERE1[Month],0))} -> 383407 | H33: {=INDEX(BERE1[Major Subsidies],MATCH($D$4&$H$8,BERE1[FY]&BERE1[Month],0))} -> #N/A | I33: {=INDEX(BERE1[Major Subsidies],MATCH($D$6&$I$8,BERE1[FY]&BERE1[Month],0))} -> 381175 | J33: {=INDEX(BERE1[Major Subsidies],MATCH($D$6&$J$8,BERE1[FY]&BERE1[Month],0))} -> 383419 | K33: =(E33-F33)/ABS(F33) -> 0.034189593 | L33: =(E33-F33)/ABS(F33) -> 0.034189593 | M33: =E33/G33 -> 0.82807565 | N33: =E33/H33 -> #N/A | O33: =E33/O$4 -> 0.0088898195 | P33: =INDEX(actual1[Major Subsidies],MATCH(P$7,actual1[Month],0)) -> 276804 | Q33: =INDEX(actual1[Major Subsidies],MATCH(Q$7,actual1[Month],0)) -> 350524 | R33: =INDEX(actual1[Major Subsidies],MATCH(R$7,actual1[Month],0)) -> 271374 | S33: =INDEX(actual1[Major Subsidies],MATCH(S$7,actual1[Month],0)) -> 227352 | U33: {=INDEX(BERE1[Major Subsidies],MATCH($U$6&U$8,BERE1[FY]&BERE1[Month],0))} -> 374707 | V33: {=INDEX(BERE1[Major Subsidies],MATCH($U$6&V$8,BERE1[FY]&BERE1[Month],0))} -> 413466 | W33: {=INDEX(BERE1[Major Subsidies],MATCH($W$6&W$8,BERE1[FY]&BERE1[Month],0))} -> 317866 | X33: {=INDEX(BERE1[Major Subsidies],MATCH($W$6&X$8,BERE1[FY]&BERE1[Month],0))} -> 521585 | Y33: {=INDEX(BERE1[Major Subsidies],MATCH($Y$6&Y$8,BERE1[FY]&BERE1[Month],0))} -> 336439 | Z33: {=INDEX(BERE1[Major Subsidies],MATCH($Y$6&Z$8,BERE1[FY]&BERE1[Month],0))} -> 422108 | AA33: {=INDEX(BERE1[Major Subsidies],MATCH($AA$6&AA$8,BERE1[FY]&BERE1[Month],0))} -> 227794 | AB33: {=INDEX(BERE1[Major Subsidies],MATCH($AA$6&AB$8,BERE1[FY]&BERE1[Month],0))} -> 595620 | AG33: Feb | AH33: =INDEX(actual2[Total Receipts],MATCH(AG15,actual2[Month],0)) -> #N/A | AI33: =INDEX(actual2[Total Receipts],MATCH(AH15,actual2[Month],0)) -> 2546317
AG34: Mar | AH34: =INDEX(actual2[Total Receipts],MATCH(AG16,actual2[Month],0)) -> #N/A | AI34: =INDEX(actual2[Total Receipts],MATCH(AH16,actual2[Month],0)) -> 3078247
D35: Other Revenue Expenditure | E35: =INDEX(actual2[Other Revenue Expenditure],MATCH($E$4,actual2[Month],0)) -> 658188 | F35: =INDEX(actual2[Other Revenue Expenditure],MATCH($E$6,actual2[Month],0)) -> 652422 | G35: {=INDEX(BERE2[Other Revenue Expenditure],MATCH($D$4&$G$8,BERE2[FY]&BERE2[Month],0))} -> 976104 | H35: {=INDEX(BERE2[Other Revenue Expenditure],MATCH($D$4&$H$8,BERE2[FY]&BERE2[Month],0))} -> #N/A | I35: {=INDEX(BERE2[Other Revenue Expenditure],MATCH($D$6&$I$8,BERE2[FY]&BERE2[Month],0))} -> 997757 | J35: {=INDEX(BERE2[Other Revenue Expenditure],MATCH($D$6&$J$8,BERE2[FY]&BERE2[Month],0))} -> 1010167 | K35: =(E35-F35)/ABS(F35) -> 0.0088378381 | L35: =(E35-F35)/ABS(F35) -> 0.0088378381 | M35: =E35/G35 -> 0.6743011 | N35: =E35/H35 -> #N/A | O35: =E35/O$4 -> 0.01842947 | P35: =INDEX(actual2[Other Revenue Expenditure],MATCH(P$7,actual2[Month],0)) -> 598544 | Q35: =INDEX(actual2[Other Revenue Expenditure],MATCH(Q$7,actual2[Month],0)) -> 555436 | R35: =INDEX(actual2[Other Revenue Expenditure],MATCH(R$7,actual2[Month],0)) -> 539258 | S35: =INDEX(actual2[Other Revenue Expenditure],MATCH(S$7,actual2[Month],0)) -> 518862 | U35: {=INDEX(BERE2[Other Revenue Expenditure],MATCH($U$6&U$8,BERE2[FY]&BERE2[Month],0))} -> 883831 | V35: {=INDEX(BERE2[Other Revenue Expenditure],MATCH($U$6&V$8,BERE2[FY]&BERE2[Month],0))} -> 944789 | W35: {=INDEX(BERE2[Other Revenue Expenditure],MATCH($W$6&W$8,BERE2[FY]&BERE2[Month],0))} -> 879550 | X35: {=INDEX(BERE2[Other Revenue Expenditure],MATCH($W$6&X$8,BERE2[FY]&BERE2[Month],0))} -> 879752 | Y35: {=INDEX(BERE2[Other Revenue Expenditure],MATCH($Y$6&Y$8,BERE2[FY]&BERE2[Month],0))} -> 774820 | Z35: {=INDEX(BERE2[Other Revenue Expenditure],MATCH($Y$6&Z$8,BERE2[FY]&BERE2[Month],0))} -> 915721 | AA35: {=INDEX(BERE2[Other Revenue Expenditure],MATCH($AA$6&AA$8,BERE2[FY]&BERE2[Month],0))} -> 712177 | AB35: {=INDEX(BERE2[Other Revenue Expenditure],MATCH($AA$6&AB$8,BERE2[FY]&BERE2[Month],0))} -> 750666
D37: Revenue Deficit | E37: =INDEX(actual2[Revenue Deficit],MATCH($E$4,actual2[Month],0)) -> 113954 | F37: =INDEX(actual2[Revenue Deficit],MATCH($E$6,actual2[Month],0)) -> 256047 | G37: {=INDEX(BERE2[Revenue Deficit],MATCH($D$4&$G$8,BERE2[FY]&BERE2[Month],0))} -> 523846 | H37: {=INDEX(BERE2[Revenue Deficit],MATCH($D$4&$H$8,BERE2[FY]&BERE2[Month],0))} -> #N/A | I37: {=INDEX(BERE2[Revenue Deficit],MATCH($D$6&$I$8,BERE2[FY]&BERE2[Month],0))} -> 580201 | J37: {=INDEX(BERE2[Revenue Deficit],MATCH($D$6&$J$8,BERE2[FY]&BERE2[Month],0))} -> 610098 | K37: =(E37-F37)/ABS(F37) -> -0.5549489 | L37: =(E37-F37)/ABS(F37) -> -0.5549489 | M37: =E37/G37 -> 0.2175334 | N37: =E37/H37 -> #N/A | O37: =E37/O$4 -> 0.0031907477 | P37: =INDEX(actual2[Revenue Deficit],MATCH(P$7,actual2[Month],0)) -> 338298 | Q37: =INDEX(actual2[Revenue Deficit],MATCH(Q$7,actual2[Month],0)) -> 558138 | R37: =INDEX(actual2[Revenue Deficit],MATCH(R$7,actual2[Month],0)) -> 396191 | S37: =INDEX(actual2[Revenue Deficit],MATCH(S$7,actual2[Month],0)) -> 882593 | U37: {=INDEX(BERE2[Revenue Deficit],MATCH($U$6&U$8,BERE2[FY]&BERE2[Month],0))} -> 870443 | V37: {=INDEX(BERE2[Revenue Deficit],MATCH($U$6&V$8,BERE2[FY]&BERE2[Month],0))} -> 841218 | W37: {=INDEX(BERE2[Revenue Deficit],MATCH($W$6&W$8,BERE2[FY]&BERE2[Month],0))} -> 990835 | X37: {=INDEX(BERE2[Revenue Deficit],MATCH($W$6&X$8,BERE2[FY]&BERE2[Month],0))} -> 1111051 | Y37: {=INDEX(BERE2[Revenue Deficit],MATCH($Y$6&Y$8,BERE2[FY]&BERE2[Month],0))} -> 1140704 | Z37: {=INDEX(BERE2[Revenue Deficit],MATCH($Y$6&Z$8,BERE2[FY]&BERE2[Month],0))} -> 1089131 | AA37: {=INDEX(BERE2[Revenue Deficit],MATCH($AA$6&AA$8,BERE2[FY]&BERE2[Month],0))} -> 609295 | AB37: {=INDEX(BERE2[Revenue Deficit],MATCH($AA$6&AB$8,BERE2[FY]&BERE2[Month],0))} -> 1456763
D39: Effective Revenue Deficit | E39: =INDEX(actual2[Effective Revenue Deficit],MATCH($E$4,actual2[Month],0)) -> -63645 | F39: =INDEX(actual2[Effective Revenue Deficit],MATCH($E$6,actual2[Month],0)) -> 56517 | G39: {=INDEX(BERE2[Effective Revenue Deficit],MATCH($D$4&$G$8,BERE2[FY]&BERE2[Month],0))} -> 96654 | H39: {=INDEX(BERE2[Effective Revenue Deficit],MATCH($D$4&$H$8,BERE2[FY]&BERE2[Month],0))} -> #N/A | I39: {=INDEX(BERE2[Effective Revenue Deficit],MATCH($D$6&$I$8,BERE2[FY]&BERE2[Month],0))} -> 189423 | J39: {=INDEX(BERE2[Effective Revenue Deficit],MATCH($D$6&$J$8,BERE2[FY]&BERE2[Month],0))} -> 310207 | K39: =(E39-F39)/ABS(F39) -> -2.1261213 | L39: =(E39-F39)/ABS(F39) -> -2.1261213 | M39: =E39/G39 -> -0.65848284 | N39: =E39/H39 -> #N/A | O39: =E39/O$4 -> -0.0017820799 | P39: =INDEX(actual2[Effective Revenue Deficit],MATCH(P$7,actual2[Month],0)) -> 124975 | Q39: =INDEX(actual2[Effective Revenue Deficit],MATCH(Q$7,actual2[Month],0)) -> 372605 | R39: =INDEX(actual2[Effective Revenue Deficit],MATCH(R$7,actual2[Month],0)) -> 238241 | S39: =INDEX(actual2[Effective Revenue Deficit],MATCH(S$7,actual2[Month],0)) -> 726886 | U39: {=INDEX(BERE2[Effective Revenue Deficit],MATCH($U$6&U$8,BERE2[FY]&BERE2[Month],0))} -> 500455 | V39: {=INDEX(BERE2[Effective Revenue Deficit],MATCH($U$6&V$8,BERE2[FY]&BERE2[Month],0))} -> 520028 | W39: {=INDEX(BERE2[Effective Revenue Deficit],MATCH($W$6&W$8,BERE2[FY]&BERE2[Month],0))} -> 673192 | X39: {=INDEX(BERE2[Effective Revenue Deficit],MATCH($W$6&X$8,BERE2[FY]&BERE2[Month],0))} -> 785463 | Y39: {=INDEX(BERE2[Effective Revenue Deficit],MATCH($Y$6&Y$8,BERE2[FY]&BERE2[Month],0))} -> 921592 | Z39: {=INDEX(BERE2[Effective Revenue Deficit],MATCH($Y$6&Z$8,BERE2[FY]&BERE2[Month],0))} -> 851446 | AA39: {=INDEX(BERE2[Effective Revenue Deficit],MATCH($AA$6&AA$8,BERE2[FY]&BERE2[Month],0))} -> 402795 | AB39: {=INDEX(BERE2[Effective Revenue Deficit],MATCH($AA$6&AB$8,BERE2[FY]&BERE2[Month],0))} -> 1226387
D41: Primary Deficit | E41: =INDEX(actual2[Primary Deficit],MATCH($E$4,actual2[Month],0)) -> -55217 | F41: =INDEX(actual2[Primary Deficit],MATCH($E$6,actual2[Month],0)) -> 105776 | G41: {=INDEX(BERE2[Primary Deficit],MATCH($D$4&$G$8,BERE2[FY]&BERE2[Month],0))} -> 292598 | H41: {=INDEX(BERE2[Primary Deficit],MATCH($D$4&$H$8,BERE2[FY]&BERE2[Month],0))} -> #N/A | I41: {=INDEX(BERE2[Primary Deficit],MATCH($D$6&$I$8,BERE2[FY]&BERE2[Month],0))} -> 450372 | J41: {=INDEX(BERE2[Primary Deficit],MATCH($D$6&$J$8,BERE2[FY]&BERE2[Month],0))} -> 431587 | K41: =(E41-F41)/ABS(F41) -> -1.5220182 | L41: =(E41-F41)/ABS(F41) -> -1.5220182 | M41: =E41/G41 -> -0.18871284 | N41: =E41/H41 -> #N/A | O41: =E41/O$4 -> -0.0015460933 | P41: =INDEX(actual2[Primary Deficit],MATCH(P$7,actual2[Month],0)) -> 234071 | Q41: =INDEX(actual2[Primary Deficit],MATCH(Q$7,actual2[Month],0)) -> 312123 | R41: =INDEX(actual2[Primary Deficit],MATCH(R$7,actual2[Month],0)) -> 193502 | S41: =INDEX(actual2[Primary Deficit],MATCH(S$7,actual2[Month],0)) -> 686298 | U41: {=INDEX(BERE2[Primary Deficit],MATCH($U$6&U$8,BERE2[FY]&BERE2[Month],0))} -> 706845 | V41: {=INDEX(BERE2[Primary Deficit],MATCH($U$6&V$8,BERE2[FY]&BERE2[Month],0))} -> 679346 | W41: {=INDEX(BERE2[Primary Deficit],MATCH($W$6&W$8,BERE2[FY]&BERE2[Month],0))} -> 720545 | X41: {=INDEX(BERE2[Primary Deficit],MATCH($W$6&X$8,BERE2[FY]&BERE2[Month],0))} -> 814668 | Y41: {=INDEX(BERE2[Primary Deficit],MATCH($Y$6&Y$8,BERE2[FY]&BERE2[Month],0))} -> 697111 | Z41: {=INDEX(BERE2[Primary Deficit],MATCH($Y$6&Z$8,BERE2[FY]&BERE2[Month],0))} -> 777298 | AA41: {=INDEX(BERE2[Primary Deficit],MATCH($AA$6&AA$8,BERE2[FY]&BERE2[Month],0))} -> 88134 | AB41: {=INDEX(BERE2[Primary Deficit],MATCH($AA$6&AB$8,BERE2[FY]&BERE2[Month],0))} -> 1155755
D43: Corporation Tax | E43: =INDEX(actual1[Corporation Tax],MATCH($E$4,actual1[Month],0)) -> 832766 | F43: =INDEX(actual1[Corporation Tax],MATCH($E$6,actual1[Month],0)) -> 740926 | G43: {=INDEX(BERE1[Corporation Tax],MATCH($D$4&$G$8,BERE2[FY]&BERE1[Month],0))} -> 1082000 | H43: {=INDEX(BERE1[Corporation Tax],MATCH($D$4&$H$8,BERE1[FY]&BERE2[Month],0))} -> #N/A | I43: {=INDEX(BERE1[Corporation Tax],MATCH($D$6&$I$8,BERE1[FY]&BERE1[Month],0))} -> 1020000 | J43: {=INDEX(BERE1[Corporation Tax],MATCH($D$6&$J$8,BERE1[FY]&BERE1[Month],0))} -> 980000 | K43: =(E43-F43)/ABS(F43) -> 0.123953 | L43: =(E43-F43)/ABS(F43) -> 0.123953 | M43: =E43/G43 -> 0.76965434 | N43: =E43/H43 -> #N/A | O43: =E43/O$4 -> 0.023317709 | P43: =INDEX(actual1[Corporation Tax],MATCH(P$7,actual1[Month],0)) -> 721671 | Q43: =INDEX(actual1[Corporation Tax],MATCH(Q$7,actual1[Month],0)) -> 608168 | R43: =INDEX(actual1[Corporation Tax],MATCH(R$7,actual1[Month],0)) -> 520332 | S43: =INDEX(actual1[Corporation Tax],MATCH(S$7,actual1[Month],0)) -> 312532
D45: Income Tax | E45: =INDEX(actual1[Income Tax],MATCH($E$4,actual1[Month],0)) -> 872696 | F45: =INDEX(actual1[Income Tax],MATCH($E$6,actual1[Month],0)) -> 837817 | G45: {=INDEX(BERE1[Income Tax],MATCH($D$4&$G$8,BERE2[FY]&BERE1[Month],0))} -> 1357000 | H45: {=INDEX(BERE1[Income Tax],MATCH($D$4&$H$8,BERE1[FY]&BERE2[Month],0))} -> #N/A | I45: {=INDEX(BERE1[Income Tax],MATCH($D$6&$I$8,BERE1[FY]&BERE1[Month],0))} -> 1150000 | J45: {=INDEX(BERE1[Income Tax],MATCH($D$6&$J$8,BERE1[FY]&BERE1[Month],0))} -> 1199300 | K45: =(E45-F45)/ABS(F45) -> 0.04163081 | L45: =(E45-F45)/ABS(F45) -> 0.04163081 | M45: =E45/G45 -> 0.64310685 | N45: =E45/H45 -> #N/A | O45: =E45/O$4 -> 0.024435761 | P45: =INDEX(actual1[Income Tax],MATCH(P$7,actual1[Month],0)) -> 685597 | Q45: =INDEX(actual1[Income Tax],MATCH(Q$7,actual1[Month],0)) -> 534108 | R45: =INDEX(actual1[Income Tax],MATCH(R$7,actual1[Month],0)) -> 448102 | S45: =INDEX(actual1[Income Tax],MATCH(S$7,actual1[Month],0)) -> 297806
D47: Securities Transcation Tax | E47: =INDEX(actual1[Securities Transcation Tax],MATCH($E$4,actual1[Month],0)) -> 40220 | F47: =INDEX(actual1[Securities Transcation Tax],MATCH($E$6,actual1[Month],0)) -> 40136 | G47: {=INDEX(BERE1[Securities Transcation Tax],MATCH($D$4&$G$8,BERE2[FY]&BERE1[Month],0))} -> 78000 | H47: {=INDEX(BERE1[Securities Transcation Tax],MATCH($D$4&$H$8,BERE1[FY]&BERE2[Month],0))} -> #N/A | I47: {=INDEX(BERE1[Securities Transcation Tax],MATCH($D$6&$I$8,BERE1[FY]&BERE1[Month],0))} -> 37000 | J47: {=INDEX(BERE1[Securities Transcation Tax],MATCH($D$6&$J$8,BERE1[FY]&BERE1[Month],0))} -> 55000 | K47: =(E47-F47)/ABS(F47) -> 0.0020928842 | L47: =(E47-F47)/ABS(F47) -> 0.0020928842 | M47: =E47/G47 -> 0.51564103 | N47: =E47/H47 -> #N/A | O47: =E47/O$4 -> 0.0011261726 | P47: =INDEX(actual1[Securities Transcation Tax],MATCH(P$7,actual1[Month],0)) -> 21630 | Q47: =INDEX(actual1[Securities Transcation Tax],MATCH(Q$7,actual1[Month],0)) -> 18104 | R47: =INDEX(actual1[Securities Transcation Tax],MATCH(R$7,actual1[Month],0)) -> 17348 | S47: =INDEX(actual1[Securities Transcation Tax],MATCH(S$7,actual1[Month],0)) -> 11443
D49: CGST | E49: =INDEX(actual1[CGST],MATCH($E$4,actual1[Month],0)) -> 710615 | F49: =INDEX(actual1[CGST],MATCH($E$6,actual1[Month],0)) -> 673256 | G49: {=INDEX(BERE1[CGST],MATCH($D$4&$G$8,BERE2[FY]&BERE1[Month],0))} -> 1010890 | H49: {=INDEX(BERE1[CGST],MATCH($D$4&$H$8,BERE1[FY]&BERE2[Month],0))} -> #N/A | I49: {=INDEX(BERE1[CGST],MATCH($D$6&$I$8,BERE1[FY]&BERE1[Month],0))} -> 910890 | J49: {=INDEX(BERE1[CGST],MATCH($D$6&$J$8,BERE1[FY]&BERE1[Month],0))} -> 908459 | K49: =(E49-F49)/ABS(F49) -> 0.055490036 | L49: =(E49-F49)/ABS(F49) -> 0.055490036 | M49: =E49/G49 -> 0.70295977 | N49: =E49/H49 -> #N/A | O49: =E49/O$4 -> 0.019897443 | P49: =INDEX(actual1[CGST],MATCH(P$7,actual1[Month],0)) -> 602701 | Q49: =INDEX(actual1[CGST],MATCH(Q$7,actual1[Month],0)) -> 532194 | R49: =INDEX(actual1[CGST],MATCH(R$7,actual1[Month],0)) -> 410063 | S49: =INDEX(actual1[CGST],MATCH(S$7,actual1[Month],0)) -> 288223
D51: IGST | E51: =INDEX(actual1[IGST],MATCH($E$4,actual1[Month],0)) -> 15641 | F51: =INDEX(actual1[IGST],MATCH($E$6,actual1[Month],0)) -> -31590 | G51: {=INDEX(BERE1[IGST],MATCH($D$4&$G$8,BERE2[FY]&BERE1[Month],0))} -> 0 | H51: {=INDEX(BERE1[IGST],MATCH($D$4&$H$8,BERE1[FY]&BERE2[Month],0))} -> #N/A | I51: {=INDEX(BERE1[IGST],MATCH($D$6&$I$8,BERE1[FY]&BERE1[Month],0))} -> 0 | J51: {=INDEX(BERE1[IGST],MATCH($D$6&$J$8,BERE1[FY]&BERE1[Month],0))} -> 0 | K51: =(E51-F51)/ABS(F51) -> 1.495125 | L51: =(E51-F51)/ABS(F51) -> 1.495125 | M51: =E51/G51 -> #DIV/0! | N51: =E51/H51 -> #N/A | O51: =E51/O$4 -> 0.0004379529 | P51: =INDEX(actual1[IGST],MATCH(P$7,actual1[Month],0)) -> -24071 | Q51: =INDEX(actual1[IGST],MATCH(Q$7,actual1[Month],0)) -> 142 | R51: =INDEX(actual1[IGST],MATCH(R$7,actual1[Month],0)) -> 36786 | S51: =INDEX(actual1[IGST],MATCH(S$7,actual1[Month],0)) -> 48158
D53: UTGST | E53: =INDEX(actual1[UTGST],MATCH($E$4,actual1[Month],0)) -> 4698 | F53: =INDEX(actual1[UTGST],MATCH($E$6,actual1[Month],0)) -> 2696 | G53: {=INDEX(BERE1[UTGST],MATCH($D$4&$G$8,BERE2[FY]&BERE1[Month],0))} -> 5355 | H53: {=INDEX(BERE1[UTGST],MATCH($D$4&$H$8,BERE1[FY]&BERE2[Month],0))} -> #N/A | I53: {=INDEX(BERE1[UTGST],MATCH($D$6&$I$8,BERE1[FY]&BERE1[Month],0))} -> 4900 | J53: {=INDEX(BERE1[UTGST],MATCH($D$6&$J$8,BERE1[FY]&BERE1[Month],0))} -> 4940 | K53: =(E53-F53)/ABS(F53) -> 0.7425816 | L53: =(E53-F53)/ABS(F53) -> 0.7425816 | M53: =E53/G53 -> 0.87731092 | N53: =E53/H53 -> #N/A | O53: =E53/O$4 -> 0.00013154547 | P53: =INDEX(actual1[UTGST],MATCH(P$7,actual1[Month],0)) -> 3491 | Q53: =INDEX(actual1[UTGST],MATCH(Q$7,actual1[Month],0)) -> 2717 | R53: =INDEX(actual1[UTGST],MATCH(R$7,actual1[Month],0)) -> 1772 | S53: =INDEX(actual1[UTGST],MATCH(S$7,actual1[Month],0)) -> 1365
D55: Compensation Cess | E55: =INDEX(actual1[Compensation Cess],MATCH($E$4,actual1[Month],0)) -> 89777 | F55: =INDEX(actual1[Compensation Cess],MATCH($E$6,actual1[Month],0)) -> 111556 | G55: {=INDEX(BERE1[Compensation Cess],MATCH($D$4&$G$8,BERE2[FY]&BERE1[Month],0))} -> 167110 | H55: {=INDEX(BERE1[Compensation Cess],MATCH($D$4&$H$8,BERE1[FY]&BERE2[Month],0))} -> #N/A | I55: {=INDEX(BERE1[Compensation Cess],MATCH($D$6&$I$8,BERE1[FY]&BERE1[Month],0))} -> 151009 | J55: {=INDEX(BERE1[Compensation Cess],MATCH($D$6&$J$8,BERE1[FY]&BERE1[Month],0))} -> 153440 | K55: =(E55-F55)/ABS(F55) -> -0.1952293 | L55: =(E55-F55)/ABS(F55) -> -0.1952293 | M55: =E55/G55 -> 0.53723296 | N55: =E55/H55 -> #N/A | O55: =E55/O$4 -> 0.0025137841 | P55: =INDEX(actual1[Compensation Cess],MATCH(P$7,actual1[Month],0)) -> 104615 | Q55: =INDEX(actual1[Compensation Cess],MATCH(Q$7,actual1[Month],0)) -> 93408 | R55: =INDEX(actual1[Compensation Cess],MATCH(R$7,actual1[Month],0)) -> 75935 | S55: =INDEX(actual1[Compensation Cess],MATCH(S$7,actual1[Month],0)) -> 59081
D57: Customs | E57: =INDEX(actual1[Customs],MATCH($E$4,actual1[Month],0)) -> 195719 | F57: =INDEX(actual1[Customs],MATCH($E$6,actual1[Month],0)) -> 170175 | G57: {=INDEX(BERE1[Customs],MATCH($D$4&$G$8,BERE2[FY]&BERE1[Month],0))} -> 240000 | H57: {=INDEX(BERE1[Customs],MATCH($D$4&$H$8,BERE1[FY]&BERE2[Month],0))} -> #N/A | I57: {=INDEX(BERE1[Customs],MATCH($D$6&$I$8,BERE1[FY]&BERE1[Month],0))} -> 237745 | J57: {=INDEX(BERE1[Customs],MATCH($D$6&$J$8,BERE1[FY]&BERE1[Month],0))} -> 235000 | K57: =(E57-F57)/ABS(F57) -> 0.1501043 | L57: =(E57-F57)/ABS(F57) -> 0.1501043 | M57: =E57/G57 -> 0.81549583 | N57: =E57/H57 -> #N/A | O57: =E57/O$4 -> 0.0054801933 | P57: =INDEX(actual1[Customs],MATCH(P$7,actual1[Month],0)) -> 158193 | Q57: =INDEX(actual1[Customs],MATCH(Q$7,actual1[Month],0)) -> 158507 | R57: =INDEX(actual1[Customs],MATCH(R$7,actual1[Month],0)) -> 141080 | S57: =INDEX(actual1[Customs],MATCH(S$7,actual1[Month],0)) -> 79598
D59: Union Excise | E59: =INDEX(actual1[Union Excise],MATCH($E$4,actual1[Month],0)) -> 219410 | F59: =INDEX(actual1[Union Excise],MATCH($E$6,actual1[Month],0)) -> 199630 | G59: {=INDEX(BERE1[Union Excise],MATCH($D$4&$G$8,BERE2[FY]&BERE1[Month],0))} -> 317000 | H59: {=INDEX(BERE1[Union Excise],MATCH($D$4&$H$8,BERE1[FY]&BERE2[Month],0))} -> #N/A | I59: {=INDEX(BERE1[Union Excise],MATCH($D$6&$I$8,BERE1[FY]&BERE1[Month],0))} -> 319000 | J59: {=INDEX(BERE1[Union Excise],MATCH($D$6&$J$8,BERE1[FY]&BERE1[Month],0))} -> 305000 | K59: =(E59-F59)/ABS(F59) -> 0.099083304 | L59: =(E59-F59)/ABS(F59) -> 0.099083304 | M59: =E59/G59 -> 0.69214511 | N59: =E59/H59 -> #N/A | O59: =E59/O$4 -> 0.0061435488 | P59: =INDEX(actual1[Union Excise],MATCH(P$7,actual1[Month],0)) -> 202469 | Q59: =INDEX(actual1[Union Excise],MATCH(Q$7,actual1[Month],0)) -> 217825 | R59: =INDEX(actual1[Union Excise],MATCH(R$7,actual1[Month],0)) -> 271862 | S59: =INDEX(actual1[Union Excise],MATCH(S$7,actual1[Month],0)) -> 235993
D61: Service Tax | E61: =INDEX(actual1[Service Tax],MATCH($E$4,actual1[Month],0)) -> -1186 | F61: =INDEX(actual1[Service Tax],MATCH($E$6,actual1[Month],0)) -> 36 | G61: {=INDEX(BERE1[Service Tax],MATCH($D$4&$G$8,BERE2[FY]&BERE1[Month],0))} -> 100 | H61: {=INDEX(BERE1[Service Tax],MATCH($D$4&$H$8,BERE1[FY]&BERE2[Month],0))} -> #N/A | I61: {=INDEX(BERE1[Service Tax],MATCH($D$6&$I$8,BERE1[FY]&BERE1[Month],0))} -> 100 | J61: {=INDEX(BERE1[Service Tax],MATCH($D$6&$J$8,BERE1[FY]&BERE1[Month],0))} -> 100 | K61: =(E61-F61)/ABS(F61) -> -33.944444 | L61: =(E61-F61)/ABS(F61) -> -33.944444 | M61: =E61/G61 -> -11.86 | N61: =E61/H61 -> #N/A | O61: =E61/O$4 -> -3.3208372e-05 | P61: =INDEX(actual1[Service Tax],MATCH(P$7,actual1[Month],0)) -> 397 | Q61: =INDEX(actual1[Service Tax],MATCH(Q$7,actual1[Month],0)) -> 139 | R61: =INDEX(actual1[Service Tax],MATCH(R$7,actual1[Month],0)) -> 577 | S61: =INDEX(actual1[Service Tax],MATCH(S$7,actual1[Month],0)) -> 1183
D63: Devolution to State | E63: =INDEX(actual1[Devolution to State],MATCH($E$4,actual1[Month],0)) -> 1038164 | F63: =INDEX(actual1[Devolution to State],MATCH($E$6,actual1[Month],0)) -> 901150 | G63: {=INDEX(BERE1[Devolution to State],MATCH($D$4&$G$8,BERE2[FY]&BERE1[Month],0))} -> 1422444 | H63: {=INDEX(BERE1[Devolution to State],MATCH($D$4&$H$8,BERE2[FY]&BERE1[Month],0))} -> #N/A | I63: {=INDEX(BERE1[Devolution to State],MATCH($D$6&$I$8,BERE2[FY]&BERE1[Month],0))} -> 1247211 | J63: {=INDEX(BERE1[Devolution to State],MATCH($D$6&$J$8,BERE2[FY]&BERE1[Month],0))} -> 1286885 | P63: =INDEX(actual1[Devolution to State],MATCH(P$7,actual1[Month],0)) -> 747288 | Q63: =INDEX(actual1[Devolution to State],MATCH(Q$7,actual1[Month],0)) -> 609437 | R63: =INDEX(actual1[Devolution to State],MATCH(R$7,actual1[Month],0)) -> 450310 | S63: =INDEX(actual1[Devolution to State],MATCH(S$7,actual1[Month],0)) -> 371640
D65: Surcharge for financing of NCCF | E65: =INDEX(actual1[Surcharge for financing of NCCF],MATCH($E$4,actual1[Month],0)) -> 6849 | F65: =INDEX(actual1[Surcharge for financing of NCCF],MATCH($E$6,actual1[Month],0)) -> 6225 | P65: =INDEX(actual1[Surcharge for financing of NCCF],MATCH(P$7,actual1[Month],0)) -> 5280 | Q65: =INDEX(actual1[Surcharge for financing of NCCF],MATCH(Q$7,actual1[Month],0)) -> 5569 | R65: =INDEX(actual1[Surcharge for financing of NCCF],MATCH(R$7,actual1[Month],0)) -> 4876 | S65: =INDEX(actual1[Surcharge for financing of NCCF],MATCH(S$7,actual1[Month],0)) -> 4087
D67: Interest receipts | E67: =INDEX(actual1[Interest receipts],MATCH($E$4,actual1[Month],0)) -> 27976 | F67: =INDEX(actual1[Interest receipts],MATCH($E$6,actual1[Month],0)) -> 29903 | P67: =INDEX(actual1[Interest receipts],MATCH(P$7,actual1[Month],0)) -> 26959 | Q67: =INDEX(actual1[Interest receipts],MATCH(Q$7,actual1[Month],0)) -> 18870 | R67: =INDEX(actual1[Interest receipts],MATCH(R$7,actual1[Month],0)) -> 16055 | S67: =INDEX(actual1[Interest receipts],MATCH(S$7,actual1[Month],0)) -> 11267
D69: Dividends and Profits | E69: =INDEX(actual1[Dividends and Profits],MATCH($E$4,actual1[Month],0)) -> 350269 | F69: =INDEX(actual1[Dividends and Profits],MATCH($E$6,actual1[Month],0)) -> 284772 | P69: =INDEX(actual1[Dividends and Profits],MATCH(P$7,actual1[Month],0)) -> 147232 | Q69: =INDEX(actual1[Dividends and Profits],MATCH(Q$7,actual1[Month],0)) -> 76362 | R69: =INDEX(actual1[Dividends and Profits],MATCH(R$7,actual1[Month],0)) -> 137068 | S69: =INDEX(actual1[Dividends and Profits],MATCH(S$7,actual1[Month],0)) -> 70848
D71: Other Non Tax Receipts | E71: =INDEX(actual1[Other Non Tax Receipts],MATCH($E$4,actual1[Month],0)) -> 161610 | F71: =INDEX(actual1[Other Non Tax Receipts],MATCH($E$6,actual1[Month],0)) -> 132982 | P71: =INDEX(actual1[Other Non Tax Receipts],MATCH(P$7,actual1[Month],0)) -> 138167 | Q71: =INDEX(actual1[Other Non Tax Receipts],MATCH(Q$7,actual1[Month],0)) -> 119070 | R71: =INDEX(actual1[Other Non Tax Receipts],MATCH(R$7,actual1[Month],0)) -> 106291 | S71: =INDEX(actual1[Other Non Tax Receipts],MATCH(S$7,actual1[Month],0)) -> 44066
D73: Recovery of Loans & Advances | E73: =INDEX(actual1[Recovery of Loans & Advances],MATCH($E$4,actual1[Month],0)) -> 18226 | F73: =INDEX(actual1[Recovery of Loans & Advances],MATCH($E$6,actual1[Month],0)) -> 18301 | P73: =INDEX(actual1[Recovery of Loans & Advances],MATCH(P$7,actual1[Month],0)) -> 19597 | Q73: =INDEX(actual1[Recovery of Loans & Advances],MATCH(Q$7,actual1[Month],0)) -> 16435 | R73: =INDEX(actual1[Recovery of Loans & Advances],MATCH(R$7,actual1[Month],0)) -> 19105 | S73: =INDEX(actual1[Recovery of Loans & Advances],MATCH(S$7,actual1[Month],0)) -> 14202
D75: Misc. Capital Receipts | E75: =INDEX(actual1[Disinvestment Receipts],MATCH($E$4,actual1[Month],0)) -> 27821 | F75: =INDEX(actual1[Disinvestment Receipts],MATCH($E$6,actual1[Month],0)) -> 8994 | P75: =INDEX(actual1[Disinvestment Receipts],MATCH(P$7,actual1[Month],0)) -> 10053 | Q75: =INDEX(actual1[Disinvestment Receipts],MATCH(Q$7,actual1[Month],0)) -> 38671 | R75: =INDEX(actual1[Disinvestment Receipts],MATCH(R$7,actual1[Month],0)) -> 9364 | S75: =INDEX(actual1[Disinvestment Receipts],MATCH(S$7,actual1[Month],0)) -> 18896

Sheet Sheet1
D4: =IF(MONTH(Dashboard!D8)<4,"RE","BE") -> BE | E4: =Sheet5!E4 -> Dec-25 | F4: =IF(MONTH(Dashboard!D8)<4,"RE","BE") -> BE | G4: =Sheet5!E6 -> Dec-24
C5: Corp. Tax | D5: =IF(MONTH(Dashboard!$D$8)<4,Sheet5!H43,Sheet5!G43) -> 1082000 | E5: =Sheet5!E43 -> 832766 | F5: =IF(MONTH(Dashboard!$D$8)<4,Sheet5!J43,Sheet5!I43) -> 1020000 | G5: =Sheet5!F43 -> 740926
C6: Income Tax | D6: =IF(MONTH(Dashboard!$D$8)<4,Sheet5!H45,Sheet5!G45) -> 1357000 | E6: =Sheet5!E45 -> 872696 | F6: =IF(MONTH(Dashboard!$D$8)<4,Sheet5!J45,Sheet5!I45) -> 1150000 | G6: =Sheet5!F45 -> 837817
C7: Sec. Tr. Tax | D7: =IF(MONTH(Dashboard!$D$8)<4,Sheet5!H47,Sheet5!G47) -> 78000 | E7: =Sheet5!E47 -> 40220 | F7: =IF(MONTH(Dashboard!$D$8)<4,Sheet5!J47,Sheet5!I47) -> 37000 | G7: =Sheet5!F47 -> 40136
C8: CGST | D8: =IF(MONTH(Dashboard!$D$8)<4,Sheet5!H49,Sheet5!G49) -> 1010890 | E8: =Sheet5!E49 -> 710615 | F8: =IF(MONTH(Dashboard!$D$8)<4,Sheet5!J49,Sheet5!I49) -> 910890 | G8: =Sheet5!F49 -> 673256
C9: IGST | D9: =IF(MONTH(Dashboard!$D$8)<4,Sheet5!H51,Sheet5!G51) -> 0 | E9: =Sheet5!E51 -> 15641 | F9: =IF(MONTH(Dashboard!$D$8)<4,Sheet5!J51,Sheet5!I51) -> 0 | G9: =Sheet5!F51 -> -31590
C10: UTGST | D10: =IF(MONTH(Dashboard!$D$8)<4,Sheet5!H53,Sheet5!G53) -> 5355 | E10: =Sheet5!E53 -> 4698 | F10: =IF(MONTH(Dashboard!$D$8)<4,Sheet5!J53,Sheet5!I53) -> 4900 | G10: =Sheet5!F53 -> 2696
C11: Comp. Cess | D11: =IF(MONTH(Dashboard!$D$8)<4,Sheet5!H55,Sheet5!G55) -> 167110 | E11: =Sheet5!E55 -> 89777 | F11: =IF(MONTH(Dashboard!$D$8)<4,Sheet5!J55,Sheet5!I55) -> 151009 | G11: =Sheet5!F55 -> 111556
C12: Customs | D12: =IF(MONTH(Dashboard!$D$8)<4,Sheet5!H57,Sheet5!G57) -> 240000 | E12: =Sheet5!E57 -> 195719 | F12: =IF(MONTH(Dashboard!$D$8)<4,Sheet5!J57,Sheet5!I57) -> 237745 | G12: =Sheet5!F57 -> 170175
C13: Union Excise | D13: =IF(MONTH(Dashboard!$D$8)<4,Sheet5!H59,Sheet5!G59) -> 317000 | E13: =Sheet5!E59 -> 219410 | F13: =IF(MONTH(Dashboard!$D$8)<4,Sheet5!J59,Sheet5!I59) -> 319000 | G13: =Sheet5!F59 -> 199630
C14: Service Tax | D14: =IF(MONTH(Dashboard!$D$8)<4,Sheet5!H61,Sheet5!G61) -> 100 | E14: =Sheet5!E61 -> -1186 | F14: =IF(MONTH(Dashboard!$D$8)<4,Sheet5!J61,Sheet5!I61) -> 100 | G14: =Sheet5!F61 -> 36
C28: Interest Payments | D28: =Sheet5!$D$4 -> 2025-26 | E28: =Sheet5!$D$6 -> 2024-25 | F28: =Sheet5!P6 -> 2023-24 | G28: =Sheet5!Q6 -> 2022-23 | H28: =Sheet5!R6 -> 2021-22
C29: Apr | D29: =INDEX(actual1[Interest Payments],MATCH(Sheet5!$AG5,actual1[Month],0)) -> 93460 | E29: =INDEX(actual1[Interest Payments],MATCH(Sheet5!$AH5,actual1[Month],0)) -> 128263 | F29: =INDEX(actual1[Interest Payments],MATCH(Sheet5!$AI5,actual1[Month],0)) -> 47929 | G29: =INDEX(actual1[Interest Payments],MATCH(Sheet5!$AJ5,actual1[Month],0)) -> 41288 | H29: =INDEX(actual1[Interest Payments],MATCH(Sheet5!$AK5,actual1[Month],0)) -> 29671
C30: May | D30: =INDEX(actual1[Interest Payments],MATCH(Sheet5!$AG6,actual1[Month],0)) -> 147788 | E30: =INDEX(actual1[Interest Payments],MATCH(Sheet5!$AH6,actual1[Month],0)) -> 123810 | F30: =INDEX(actual1[Interest Payments],MATCH(Sheet5!$AI6,actual1[Month],0)) -> 110663 | G30: =INDEX(actual1[Interest Payments],MATCH(Sheet5!$AJ6,actual1[Month],0)) -> 105422 | H30: =INDEX(actual1[Interest Payments],MATCH(Sheet5!$AK6,actual1[Month],0)) -> 88573
C31: Jun | D31: =INDEX(actual1[Interest Payments],MATCH(Sheet5!$AG7,actual1[Month],0)) -> 386037 | E31: =INDEX(actual1[Interest Payments],MATCH(Sheet5!$AH7,actual1[Month],0)) -> 264052 | F31: =INDEX(actual1[Interest Payments],MATCH(Sheet5!$AI7,actual1[Month],0)) -> 243705 | G31: =INDEX(actual1[Interest Payments],MATCH(Sheet5!$AJ7,actual1[Month],0)) -> 228595 | H31: =INDEX(actual1[Interest Payments],MATCH(Sheet5!$AK7,actual1[Month],0)) -> 184295
C32: Jul | D32: =INDEX(actual1[Interest Payments],MATCH(Sheet5!$AG8,actual1[Month],0)) -> 446690 | E32: =INDEX(actual1[Interest Payments],MATCH(Sheet5!$AH8,actual1[Month],0)) -> 327887 | F32: =INDEX(actual1[Interest Payments],MATCH(Sheet5!$AI8,actual1[Month],0)) -> 299889 | G32: =INDEX(actual1[Interest Payments],MATCH(Sheet5!$AJ8,actual1[Month],0)) -> 283870 | H32: =INDEX(actual1[Interest Payments],MATCH(Sheet5!$AK8,actual1[Month],0)) -> 225817
C33: Aug | D33: =INDEX(actual1[Interest Payments],MATCH(Sheet5!$AG9,actual1[Month],0)) -> 528668 | E33: =INDEX(actual1[Interest Payments],MATCH(Sheet5!$AH9,actual1[Month],0)) -> 400160 | F33: =INDEX(actual1[Interest Payments],MATCH(Sheet5!$AI9,actual1[Month],0)) -> 367539 | G33: =INDEX(actual1[Interest Payments],MATCH(Sheet5!$AJ9,actual1[Month],0)) -> 338637 | H33: =INDEX(actual1[Interest Payments],MATCH(Sheet5!$AK9,actual1[Month],0)) -> 278371
C34: Sep | D34: =INDEX(actual1[Interest Payments],MATCH(Sheet5!$AG10,actual1[Month],0)) -> 578182 | E34: =INDEX(actual1[Interest Payments],MATCH(Sheet5!$AH10,actual1[Month],0)) -> 515010 | F34: =INDEX(actual1[Interest Payments],MATCH(Sheet5!$AI10,actual1[Month],0)) -> 484329 | G34: =INDEX(actual1[Interest Payments],MATCH(Sheet5!$AJ10,actual1[Month],0)) -> 436682 | H34: =INDEX(actual1[Interest Payments],MATCH(Sheet5!$AK10,actual1[Month],0)) -> 365207
C35: Oct | D35: =INDEX(actual1[Interest Payments],MATCH(Sheet5!$AG11,actual1[Month],0)) -> 673715 | E35: =INDEX(actual1[Interest Payments],MATCH(Sheet5!$AH11,actual1[Month],0)) -> 596347 | F35: =INDEX(actual1[Interest Payments],MATCH(Sheet5!$AI11,actual1[Month],0)) -> 545086 | G35: =INDEX(actual1[Interest Payments],MATCH(Sheet5!$AJ11,actual1[Month],0)) -> 481172 | H35: =INDEX(actual1[Interest Payments],MATCH(Sheet5!$AK11,actual1[Month],0)) -> 401187
C36: Nov | D36: =INDEX(actual1[Interest Payments],MATCH(Sheet5!$AG12,actual1[Month],0)) -> 745765 | E36: =INDEX(actual1[Interest Payments],MATCH(Sheet5!$AH12,actual1[Month],0)) -> 658494 | F36: =INDEX(actual1[Interest Payments],MATCH(Sheet5!$AI12,actual1[Month],0)) -> 607963 | G36: =INDEX(actual1[Interest Payments],MATCH(Sheet5!$AJ12,actual1[Month],0)) -> 545199 | H36: =INDEX(actual1[Interest Payments],MATCH(Sheet5!$AK12,actual1[Month],0)) -> 461773
C37: Dec | D37: =INDEX(actual1[Interest Payments],MATCH(Sheet5!$AG13,actual1[Month],0)) -> 911059 | E37: =INDEX(actual1[Interest Payments],MATCH(Sheet5!$AH13,actual1[Month],0)) -> 808313 | F37: =INDEX(actual1[Interest Payments],MATCH(Sheet5!$AI13,actual1[Month],0)) -> 748207 | G37: =INDEX(actual1[Interest Payments],MATCH(Sheet5!$AJ13,actual1[Month],0)) -> 680853 | H37: =INDEX(actual1[Interest Payments],MATCH(Sheet5!$AK13,actual1[Month],0)) -> 565864
C38: Jan | D38: =INDEX(actual1[Interest Payments],MATCH(Sheet5!$AG14,actual1[Month],0)) -> #N/A | E38: =INDEX(actual1[Interest Payments],MATCH(Sheet5!$AH14,actual1[Month],0)) -> 875461 | F38: =INDEX(actual1[Interest Payments],MATCH(Sheet5!$AI14,actual1[Month],0)) -> 821731 | G38: =INDEX(actual1[Interest Payments],MATCH(Sheet5!$AJ14,actual1[Month],0)) -> 738658 | H38: =INDEX(actual1[Interest Payments],MATCH(Sheet5!$AK14,actual1[Month],0)) -> 616076
C39: Feb | D39: =INDEX(actual1[Interest Payments],MATCH(Sheet5!$AG15,actual1[Month],0)) -> #N/A | E39: =INDEX(actual1[Interest Payments],MATCH(Sheet5!$AH15,actual1[Month],0)) -> 952844 | F39: =INDEX(actual1[Interest Payments],MATCH(Sheet5!$AI15,actual1[Month],0)) -> 880788 | G39: =INDEX(actual1[Interest Payments],MATCH(Sheet5!$AJ15,actual1[Month],0)) -> 798957 | H39: =INDEX(actual1[Interest Payments],MATCH(Sheet5!$AK15,actual1[Month],0)) -> 671951
C40: Mar | D40: =INDEX(actual1[Interest Payments],MATCH(Sheet5!$AG16,actual1[Month],0)) -> #N/A | E40: =INDEX(actual1[Interest Payments],MATCH(Sheet5!$AH16,actual1[Month],0)) -> 1116343 | F40: =INDEX(actual1[Interest Payments],MATCH(Sheet5!$AI16,actual1[Month],0)) -> 1063872 | G40: =INDEX(actual1[Interest Payments],MATCH(Sheet5!$AJ16,actual1[Month],0)) -> 928517 | H40: =INDEX(actual1[Interest Payments],MATCH(Sheet5!$AK16,actual1[Month],0)) -> 805499
C42: Income Tax | D42: =Sheet5!$D$4 -> 2025-26 | E42: =Sheet5!$D$6 -> 2024-25
C43: Apr | D43: =INDEX(actual1[Income Tax],MATCH(Sheet5!$AG$5,actual1[Month],0)) -> 109626 | E43: =INDEX(actual1[Income Tax],MATCH(Sheet5!$AH$5,actual1[Month],0)) -> 98951
C44: May | D44: =INDEX(actual1[Income Tax],MATCH(Sheet5!$AG$6,actual1[Month],0)) -> 191816 | E44: =INDEX(actual1[Income Tax],MATCH(Sheet5!$AH$6,actual1[Month],0)) -> 180291
C45: Jun | D45: =INDEX(actual1[Income Tax],MATCH(Sheet5!$AG$7,actual1[Month],0)) -> 285829 | E45: =INDEX(actual1[Income Tax],MATCH(Sheet5!$AH$7,actual1[Month],0)) -> 287336
C46: Jul | D46: =INDEX(actual1[Income Tax],MATCH(Sheet5!$AG$8,actual1[Month],0)) -> 355315 | E46: =INDEX(actual1[Income Tax],MATCH(Sheet5!$AH$8,actual1[Month],0)) -> 394488
C47: Aug | D47: =INDEX(actual1[Income Tax],MATCH(Sheet5!$AG$9,actual1[Month],0)) -> 441013 | E47: =INDEX(actual1[Income Tax],MATCH(Sheet5!$AH$9,actual1[Month],0)) -> 452286
C48: Sep | D48: =INDEX(actual1[Income Tax],MATCH(Sheet5!$AG$10,actual1[Month],0)) -> 591014 | E48: =INDEX(actual1[Income Tax],MATCH(Sheet5!$AH$10,actual1[Month],0)) -> 564517
C49: Oct | D49: =INDEX(actual1[Income Tax],MATCH(Sheet5!$AG$11,actual1[Month],0)) -> 669631 | E49: =INDEX(actual1[Income Tax],MATCH(Sheet5!$AH$11,actual1[Month],0)) -> 626454
C50: Nov | D50: =INDEX(actual1[Income Tax],MATCH(Sheet5!$AG$12,actual1[Month],0)) -> 748299 | E50: =INDEX(actual1[Income Tax],MATCH(Sheet5!$AH$12,actual1[Month],0)) -> 700775
C51: Dec | D51: =INDEX(actual1[Income Tax],MATCH(Sheet5!$AG$13,actual1[Month],0)) -> 872696 | E51: =INDEX(actual1[Income Tax],MATCH(Sheet5!$AH$13,actual1[Month],0)) -> 837817
C52: Jan | D52: =INDEX(actual1[Income Tax],MATCH(Sheet5!$AG$14,actual1[Month],0)) -> #N/A | E52: =INDEX(actual1[Income Tax],MATCH(Sheet5!$AH$14,actual1[Month],0)) -> 912792
C53: Feb | D53: =INDEX(actual1[Income Tax],MATCH(Sheet5!$AG$15,actual1[Month],0)) -> #N/A | E53: =INDEX(actual1[Income Tax],MATCH(Sheet5!$AH$15,actual1[Month],0)) -> 991489
C54: Mar | D54: =INDEX(actual1[Income Tax],MATCH(Sheet5!$AG$16,actual1[Month],0)) -> #N/A | E54: =INDEX(actual1[Income Tax],MATCH(Sheet5!$AH$16,actual1[Month],0)) -> 1182964
C56: Securities Transcation Tax | D56: =Sheet5!$D$4 -> 2025-26 | E56: =Sheet5!$D$6 -> 2024-25
C57: Apr | D57: =INDEX(actual1[Securities Transcation Tax],MATCH(Sheet5!$AG$5,actual1[Month],0)) -> 3786 | E57: =INDEX(actual1[Securities Transcation Tax],MATCH(Sheet5!$AH$5,actual1[Month],0)) -> 3504
C58: May | D58: =INDEX(actual1[Securities Transcation Tax],MATCH(Sheet5!$AG$6,actual1[Month],0)) -> 8086 | E58: =INDEX(actual1[Securities Transcation Tax],MATCH(Sheet5!$AH$6,actual1[Month],0)) -> 7235
C59: Jun | D59: =INDEX(actual1[Securities Transcation Tax],MATCH(Sheet5!$AG$7,actual1[Month],0)) -> 13015 | E59: =INDEX(actual1[Securities Transcation Tax],MATCH(Sheet5!$AH$7,actual1[Month],0)) -> 11606
C60: Jul | D60: =INDEX(actual1[Securities Transcation Tax],MATCH(Sheet5!$AG$8,actual1[Month],0)) -> 17882 | E60: =INDEX(actual1[Securities Transcation Tax],MATCH(Sheet5!$AH$8,actual1[Month],0)) -> 16635
C61: Aug | D61: =INDEX(actual1[Securities Transcation Tax],MATCH(Sheet5!$AG$9,actual1[Month],0)) -> 22379 | E61: =INDEX(actual1[Securities Transcation Tax],MATCH(Sheet5!$AH$9,actual1[Month],0)) -> 21607
C62: Sep | D62: =INDEX(actual1[Securities Transcation Tax],MATCH(Sheet5!$AG$10,actual1[Month],0)) -> 26309 | E62: =INDEX(actual1[Securities Transcation Tax],MATCH(Sheet5!$AH$10,actual1[Month],0)) -> 26156
C63: Oct | D63: =INDEX(actual1[Securities Transcation Tax],MATCH(Sheet5!$AG$11,actual1[Month],0)) -> 30935 | E63: =INDEX(actual1[Securities Transcation Tax],MATCH(Sheet5!$AH$11,actual1[Month],0)) -> 30687
C64: Nov | D64: =INDEX(actual1[Securities Transcation Tax],MATCH(Sheet5!$AG$12,actual1[Month],0)) -> 35718 | E64: =INDEX(actual1[Securities Transcation Tax],MATCH(Sheet5!$AH$12,actual1[Month],0)) -> 35932
C65: Dec | D65: =INDEX(actual1[Securities Transcation Tax],MATCH(Sheet5!$AG$13,actual1[Month],0)) -> 40220 | E65: =INDEX(actual1[Securities Transcation Tax],MATCH(Sheet5!$AH$13,actual1[Month],0)) -> 40136
C66: Jan | D66: =INDEX(actual1[Securities Transcation Tax],MATCH(Sheet5!$AG$14,actual1[Month],0)) -> #N/A | E66: =INDEX(actual1[Securities Transcation Tax],MATCH(Sheet5!$AH$14,actual1[Month],0)) -> 44541
C67: Feb | D67: =INDEX(actual1[Securities Transcation Tax],MATCH(Sheet5!$AG$15,actual1[Month],0)) -> #N/A | E67: =INDEX(actual1[Securities Transcation Tax],MATCH(Sheet5!$AH$15,actual1[Month],0)) -> 49227
C68: Mar | D68: =INDEX(actual1[Securities Transcation Tax],MATCH(Sheet5!$AG$16,actual1[Month],0)) -> #N/A | E68: =INDEX(actual1[Securities Transcation Tax],MATCH(Sheet5!$AH$16,actual1[Month],0)) -> 52197
C70: CGST | D70: =Sheet5!$D$4 -> 2025-26 | E70: =Sheet5!$D$6 -> 2024-25
C71: Apr | D71: =INDEX(actual1[CGST],MATCH(Sheet5!$AG$5,actual1[Month],0)) -> 78240 | E71: =INDEX(actual1[CGST],MATCH(Sheet5!$AH$5,actual1[Month],0)) -> 91188
C72: May | D72: =INDEX(actual1[CGST],MATCH(Sheet5!$AG$6,actual1[Month],0)) -> 154984 | E72: =INDEX(actual1[CGST],MATCH(Sheet5!$AH$6,actual1[Month],0)) -> 158841
C73: Jun | D73: =INDEX(actual1[CGST],MATCH(Sheet5!$AG$7,actual1[Month],0)) -> 231723 | E73: =INDEX(actual1[CGST],MATCH(Sheet5!$AH$7,actual1[Month],0)) -> 228328
C74: Jul | D74: =INDEX(actual1[CGST],MATCH(Sheet5!$AG$8,actual1[Month],0)) -> 311625 | E74: =INDEX(actual1[CGST],MATCH(Sheet5!$AH$8,actual1[Month],0)) -> 300616
C75: Aug | D75: =INDEX(actual1[CGST],MATCH(Sheet5!$AG$9,actual1[Month],0)) -> 390502 | E75: =INDEX(actual1[CGST],MATCH(Sheet5!$AH$9,actual1[Month],0)) -> 371222
C76: Sep | D76: =INDEX(actual1[CGST],MATCH(Sheet5!$AG$10,actual1[Month],0)) -> 466736 | E76: =INDEX(actual1[CGST],MATCH(Sheet5!$AH$10,actual1[Month],0)) -> 441220
C77: Oct | D77: =INDEX(actual1[CGST],MATCH(Sheet5!$AG$11,actual1[Month],0)) -> 553607 | E77: =INDEX(actual1[CGST],MATCH(Sheet5!$AH$11,actual1[Month],0)) -> 521599
C78: Nov | D78: =INDEX(actual1[CGST],MATCH(Sheet5!$AG$12,actual1[Month],0)) -> 636473 | E78: =INDEX(actual1[CGST],MATCH(Sheet5!$AH$12,actual1[Month],0)) -> 603873
C79: Dec | D79: =INDEX(actual1[CGST],MATCH(Sheet5!$AG$13,actual1[Month],0)) -> 710615 | E79: =INDEX(actual1[CGST],MATCH(Sheet5!$AH$13,actual1[Month],0)) -> 673256
C80: Jan | D80: =INDEX(actual1[CGST],MATCH(Sheet5!$AG$14,actual1[Month],0)) -> #N/A | E80: =INDEX(actual1[CGST],MATCH(Sheet5!$AH$14,actual1[Month],0)) -> 752514
C81: Feb | D81: =INDEX(actual1[CGST],MATCH(Sheet5!$AG$15,actual1[Month],0)) -> #N/A | E81: =INDEX(actual1[CGST],MATCH(Sheet5!$AH$15,actual1[Month],0)) -> 830137
C82: Mar | D82: =INDEX(actual1[CGST],MATCH(Sheet5!$AG$16,actual1[Month],0)) -> #N/A | E82: =INDEX(actual1[CGST],MATCH(Sheet5!$AH$16,actual1[Month],0)) -> 908980
C84: IGST | D84: =Sheet5!$D$4 -> 2025-26 | E84: =Sheet5!$D$6 -> 2024-25
C85: Apr | D85: =INDEX(actual1[IGST],MATCH(Sheet5!$AG$5,actual1[Month],0)) -> 31097 | E85: =INDEX(actual1[IGST],MATCH(Sheet5!$AH$5,actual1[Month],0)) -> -2645
C86: May | D86: =INDEX(actual1[IGST],MATCH(Sheet5!$AG$6,actual1[Month],0)) -> 33430 | E86: =INDEX(actual1[IGST],MATCH(Sheet5!$AH$6,actual1[Month],0)) -> -10883
C87: Jun | D87: =INDEX(actual1[IGST],MATCH(Sheet5!$AG$7,actual1[Month],0)) -> 27312 | E87: =INDEX(actual1[IGST],MATCH(Sheet5!$AH$7,actual1[Month],0)) -> -10176
C88: Jul | D88: =INDEX(actual1[IGST],MATCH(Sheet5!$AG$8,actual1[Month],0)) -> 11907 | E88: =INDEX(actual1[IGST],MATCH(Sheet5!$AH$8,actual1[Month],0)) -> -10659
C89: Aug | D89: =INDEX(actual1[IGST],MATCH(Sheet5!$AG$9,actual1[Month],0)) -> 370 | E89: =INDEX(actual1[IGST],MATCH(Sheet5!$AH$9,actual1[Month],0)) -> -2446
C90: Sep | D90: =INDEX(actual1[IGST],MATCH(Sheet5!$AG$10,actual1[Month],0)) -> -8838 | E90: =INDEX(actual1[IGST],MATCH(Sheet5!$AH$10,actual1[Month],0)) -> -846
C91: Oct | D91: =INDEX(actual1[IGST],MATCH(Sheet5!$AG$11,actual1[Month],0)) -> -29806 | E91: =INDEX(actual1[IGST],MATCH(Sheet5!$AH$11,actual1[Month],0)) -> -10448
C92: Nov | D92: =INDEX(actual1[IGST],MATCH(Sheet5!$AG$12,actual1[Month],0)) -> -60520 | E92: =INDEX(actual1[IGST],MATCH(Sheet5!$AH$12,actual1[Month],0)) -> -27854
C93: Dec | D93: =INDEX(actual1[IGST],MATCH(Sheet5!$AG$13,actual1[Month],0)) -> 15641 | E93: =INDEX(actual1[IGST],MATCH(Sheet5!$AH$13,actual1[Month],0)) -> -31590
C94: Jan | D94: =INDEX(actual1[IGST],MATCH(Sheet5!$AG$14,actual1[Month],0)) -> #N/A | E94: =INDEX(actual1[IGST],MATCH(Sheet5!$AH$14,actual1[Month],0)) -> -27610
C95: Feb | D95: =INDEX(actual1[IGST],MATCH(Sheet5!$AG$15,actual1[Month],0)) -> #N/A | E95: =INDEX(actual1[IGST],MATCH(Sheet5!$AH$15,actual1[Month],0)) -> -37608
C96: Mar | D96: =INDEX(actual1[IGST],MATCH(Sheet5!$AG$16,actual1[Month],0)) -> #N/A | E96: =INDEX(actual1[IGST],MATCH(Sheet5!$AH$16,actual1[Month],0)) -> -32995
C98: UTGST | D98: =Sheet5!$D$4 -> 2025-26 | E98: =Sheet5!$D$6 -> 2024-25
C99: Apr | D99: =INDEX(actual1[UTGST],MATCH(Sheet5!$AG$5,actual1[Month],0)) -> 119 | E99: =INDEX(actual1[UTGST],MATCH(Sheet5!$AH$5,actual1[Month],0)) -> 292
C100: May | D100: =INDEX(actual1[UTGST],MATCH(Sheet5!$AG$6,actual1[Month],0)) -> 491 | E100: =INDEX(actual1[UTGST],MATCH(Sheet5!$AH$6,actual1[Month],0)) -> 598
C101: Jun | D101: =INDEX(actual1[UTGST],MATCH(Sheet5!$AG$7,actual1[Month],0)) -> 779 | E101: =INDEX(actual1[UTGST],MATCH(Sheet5!$AH$7,actual1[Month],0)) -> 877
C102: Jul | D102: =INDEX(actual1[UTGST],MATCH(Sheet5!$AG$8,actual1[Month],0)) -> 1115 | E102: =INDEX(actual1[UTGST],MATCH(Sheet5!$AH$8,actual1[Month],0)) -> 934
C103: Aug | D103: =INDEX(actual1[UTGST],MATCH(Sheet5!$AG$9,actual1[Month],0)) -> 1487 | E103: =INDEX(actual1[UTGST],MATCH(Sheet5!$AH$9,actual1[Month],0)) -> 1286
C104: Sep | D104: =INDEX(actual1[UTGST],MATCH(Sheet5!$AG$10,actual1[Month],0)) -> 2016 | E104: =INDEX(actual1[UTGST],MATCH(Sheet5!$AH$10,actual1[Month],0)) -> 1624
C105: Oct | D105: =INDEX(actual1[UTGST],MATCH(Sheet5!$AG$11,actual1[Month],0)) -> 2538 | E105: =INDEX(actual1[UTGST],MATCH(Sheet5!$AH$11,actual1[Month],0)) -> 1947
C106: Nov | D106: =INDEX(actual1[UTGST],MATCH(Sheet5!$AG$12,actual1[Month],0)) -> 4235 | E106: =INDEX(actual1[UTGST],MATCH(Sheet5!$AH$12,actual1[Month],0)) -> 2427
C107: Dec | D107: =INDEX(actual1[UTGST],MATCH(Sheet5!$AG$13,actual1[Month],0)) -> 4698 | E107: =INDEX(actual1[UTGST],MATCH(Sheet5!$AH$13,actual1[Month],0)) -> 2696
C108: Jan | D108: =INDEX(actual1[UTGST],MATCH(Sheet5!$AG$14,actual1[Month],0)) -> #N/A | E108: =INDEX(actual1[UTGST],MATCH(Sheet5!$AH$14,actual1[Month],0)) -> 3560
C109: Feb | D109: =INDEX(actual1[UTGST],MATCH(Sheet5!$AG$15,actual1[Month],0)) -> #N/A | E109: =INDEX(actual1[UTGST],MATCH(Sheet5!$AH$15,actual1[Month],0)) -> 3864
C110: Mar | D110: =INDEX(actual1[UTGST],MATCH(Sheet5!$AG$16,actual1[Month],0)) -> #N/A | E110: =INDEX(actual1[UTGST],MATCH(Sheet5!$AH$16,actual1[Month],0)) -> 5094
C112: Compensation Cess | D112: =Sheet5!$D$4 -> 2025-26 | E112: =Sheet5!$D$6 -> 2024-25
C113: Apr | D113: =INDEX(actual1[Compensation Cess],MATCH(Sheet5!$AG$5,actual1[Month],0)) -> 12696 | E113: =INDEX(actual1[Compensation Cess],MATCH(Sheet5!$AH$5,actual1[Month],0)) -> 13042
C114: May | D114: =INDEX(actual1[Compensation Cess],MATCH(Sheet5!$AG$6,actual1[Month],0)) -> 25006 | E114: =INDEX(actual1[Compensation Cess],MATCH(Sheet5!$AH$6,actual1[Month],0)) -> 24828
C115: Jun | D115: =INDEX(actual1[Compensation Cess],MATCH(Sheet5!$AG$7,actual1[Month],0)) -> 38325 | E115: =INDEX(actual1[Compensation Cess],MATCH(Sheet5!$AH$7,actual1[Month],0)) -> 37768
C116: Jul | D116: =INDEX(actual1[Compensation Cess],MATCH(Sheet5!$AG$8,actual1[Month],0)) -> 50305 | E116: =INDEX(actual1[Compensation Cess],MATCH(Sheet5!$AH$8,actual1[Month],0)) -> 50547
C117: Aug | D117: =INDEX(actual1[Compensation Cess],MATCH(Sheet5!$AG$9,actual1[Month],0)) -> 61960 | E117: =INDEX(actual1[Compensation Cess],MATCH(Sheet5!$AH$9,actual1[Month],0)) -> 62462
C118: Sep | D118: =INDEX(actual1[Compensation Cess],MATCH(Sheet5!$AG$10,actual1[Month],0)) -> 73172 | E118: =INDEX(actual1[Compensation Cess],MATCH(Sheet5!$AH$10,actual1[Month],0)) -> 74323
C119: Oct | D119: =INDEX(actual1[Compensation Cess],MATCH(Sheet5!$AG$11,actual1[Month],0)) -> 80503 | E119: =INDEX(actual1[Compensation Cess],MATCH(Sheet5!$AH$11,actual1[Month],0)) -> 86482
C120: Nov | D120: =INDEX(actual1[Compensation Cess],MATCH(Sheet5!$AG$12,actual1[Month],0)) -> 84404 | E120: =INDEX(actual1[Compensation Cess],MATCH(Sheet5!$AH$12,actual1[Month],0)) -> 99598
C121: Dec | D121: =INDEX(actual1[Compensation Cess],MATCH(Sheet5!$AG$13,actual1[Month],0)) -> 89777 | E121: =INDEX(actual1[Compensation Cess],MATCH(Sheet5!$AH$13,actual1[Month],0)) -> 111556
C122: Jan | D122: =INDEX(actual1[Compensation Cess],MATCH(Sheet5!$AG$14,actual1[Month],0)) -> #N/A | E122: =INDEX(actual1[Compensation Cess],MATCH(Sheet5!$AH$14,actual1[Month],0)) -> 124971
...

Sheet Sheet2
D4: =IF(MONTH(Sheet5!$E$4)<4,"RE","BE") -> BE | E4: Actual | F4: %
C5: =Sheet5!D9 -> Total Receipts | D5: =IF(MONTH(Sheet5!$E$4)<4,Sheet5!H9,Sheet5!G9) -> 3496409 | E5: =Sheet5!E9 -> 2525156 | F5: =E5/D5 -> 0.72221413
C23: =Sheet5!D15 -> Net Tax Revenue | D23: =Sheet5!E15 -> 1939254 | E23: =Sheet5!F15 -> 1843053
C24: =Sheet5!D17 -> Non Tax Revenue | D24: =Sheet5!E17 -> 539855 | E24: =Sheet5!F17 -> 447657
C25: =Sheet5!D19 -> Non Debt Capital Receipts | D25: =Sheet5!E19 -> 46047 | E25: =Sheet5!F19 -> 27295
C26: =Sheet5!D13 -> Fiscal Deficit | D26: =Sheet5!E13 -> 855842 | E26: =Sheet5!F13 -> 914089
B30: Revenue Exp | C30: =Sheet5!D25 -> Interest Payments | D30: =Sheet5!E25 -> 911059 | E30: =Sheet5!F25 -> 808313 | F30: =SUM(D30:D35) -> 2593063
B31: Capital Exp | C31: =Sheet5!D27 -> Defence Services | D31: =Sheet5!E27 -> 233023 | E31: =Sheet5!F27 -> 215520 | F31: =D36 -> 787935
C32: =Sheet5!D29 -> Grants in Aid to States & UTs | D32: =Sheet5!E29 -> 247273 | E32: =Sheet5!F29 -> 348245
C33: =Sheet5!D31 -> Pensions | D33: =Sheet5!E31 -> 226030 | E33: =Sheet5!F31 -> 215263
C34: =Sheet5!D33 -> Major Subsidies | D34: =Sheet5!E33 -> 317490 | E34: =Sheet5!F33 -> 306994
C35: =Sheet5!D35 -> Other Revenue Expenditure | D35: =Sheet5!E35 -> 658188 | E35: =Sheet5!F35 -> 652422
C36: =Sheet5!D23 -> Capital Expenditure | D36: =Sheet5!E23 -> 787935 | E36: =Sheet5!F23 -> 685337
C40: =MONTH(D40) -> 12 | D40: =Dashboard!D8 -> Dec-25
D42: Tax Revenues | E42: =Sheet5!D4 -> 2025-26 | F42: =Sheet5!D6 -> 2024-25
B43: =Dashboard!$Q58 -> Apr-25 | C43: =B43-$D$40-1 -> -245 | D43: Apr | E43: =INDEX(actual2[Net Tax Revenue],MATCH(Sheet5!AG5,actual2[Month],0)) -> 189669 | F43: =INDEX(actual2[Net Tax Revenue],MATCH(Sheet5!AH5,actual2[Month],0)) -> 184998 | M43: =IF(C43<0,E43,NA()) -> 189669 | N43: =F43 -> 184998
B44: =Dashboard!$Q59 -> May-25 | C44: =B44-$D$40-1 -> -215 | D44: May | E44: =INDEX(actual2[Net Tax Revenue],MATCH(Sheet5!AG6,actual2[Month],0)) -> 350862 | F44: =INDEX(actual2[Net Tax Revenue],MATCH(Sheet5!AH6,actual2[Month],0)) -> 319036 | M44: =IF(C44<0,E44,NA()) -> 350862 | N44: =F44 -> 319036
B45: =Dashboard!$Q60 -> Jun-25 | C45: =B45-$D$40-1 -> -184 | D45: Jun | E45: =INDEX(actual2[Net Tax Revenue],MATCH(Sheet5!AG7,actual2[Month],0)) -> 540316 | F45: =INDEX(actual2[Net Tax Revenue],MATCH(Sheet5!AH7,actual2[Month],0)) -> 549633 | M45: =IF(C45<0,E45,NA()) -> 540316 | N45: =F45 -> 549633
B46: =Dashboard!$Q61 -> Jul-25 | C46: =B46-$D$40-1 -> -154 | D46: Jul | E46: =INDEX(actual2[Net Tax Revenue],MATCH(Sheet5!AG8,actual2[Month],0)) -> 661812 | F46: =INDEX(actual2[Net Tax Revenue],MATCH(Sheet5!AH8,actual2[Month],0)) -> 715224 | M46: =IF(C46<0,E46,NA()) -> 661812 | N46: =F46 -> 715224
B47: =Dashboard!$Q62 -> Aug-25 | C47: =B47-$D$40-1 -> -123 | D47: Aug | E47: =INDEX(actual2[Net Tax Revenue],MATCH(Sheet5!AG9,actual2[Month],0)) -> 810407 | F47: =INDEX(actual2[Net Tax Revenue],MATCH(Sheet5!AH9,actual2[Month],0)) -> 873845 | M47: =IF(C47<0,E47,NA()) -> 810407 | N47: =F47 -> 873845
B48: =Dashboard!$Q63 -> Sep-25 | C48: =B48-$D$40-1 -> -92 | D48: Sep | E48: =INDEX(actual2[Net Tax Revenue],MATCH(Sheet5!AG10,actual2[Month],0)) -> 1229370 | F48: =INDEX(actual2[Net Tax Revenue],MATCH(Sheet5!AH10,actual2[Month],0)) -> 1265159 | M48: =IF(C48<0,E48,NA()) -> 1229370 | N48: =F48 -> 1265159
B49: =Dashboard!$Q64 -> Oct-25 | C49: =B49-$D$40-1 -> -62 | D49: Oct | E49: =INDEX(actual2[Net Tax Revenue],MATCH(Sheet5!AG11,actual2[Month],0)) -> 1274301 | F49: =INDEX(actual2[Net Tax Revenue],MATCH(Sheet5!AH11,actual2[Month],0)) -> 1304973 | M49: =IF(C49<0,E49,NA()) -> 1274301 | N49: =F49 -> 1304973
B50: =Dashboard!$Q65 -> Nov-25 | C50: =B50-$D$40-1 -> -31 | D50: Nov | E50: =INDEX(actual2[Net Tax Revenue],MATCH(Sheet5!AG12,actual2[Month],0)) -> 1393946 | F50: =INDEX(actual2[Net Tax Revenue],MATCH(Sheet5!AH12,actual2[Month],0)) -> 1443435 | M50: =IF(C50<0,E50,NA()) -> 1393946 | N50: =F50 -> 1443435
B51: =Dashboard!$Q66 -> Dec-25 | C51: =B51-$D$40-1 -> -1 | D51: Dec | E51: =INDEX(actual2[Net Tax Revenue],MATCH(Sheet5!AG13,actual2[Month],0)) -> 1939254 | F51: =INDEX(actual2[Net Tax Revenue],MATCH(Sheet5!AH13,actual2[Month],0)) -> 1843053 | M51: =IF(C51<0,E51,NA()) -> 1939254 | N51: =F51 -> 1843053
B52: =Dashboard!$Q67 | C52: =B52-$D$40-1 -> #VALUE! | D52: Jan | E52: =INDEX(actual2[Net Tax Revenue],MATCH(Sheet5!AG14,actual2[Month],0)) -> #N/A | F52: =INDEX(actual2[Net Tax Revenue],MATCH(Sheet5!AH14,actual2[Month],0)) -> 1903558 | M52: =IF(C52<0,E52,NA()) -> #VALUE! | N52: =F52 -> 1903558
B53: =Dashboard!$Q68 | C53: =B53-$D$40-1 -> #VALUE! | D53: Feb | E53: =INDEX(actual2[Net Tax Revenue],MATCH(Sheet5!AG15,actual2[Month],0)) -> #N/A | F53: =INDEX(actual2[Net Tax Revenue],MATCH(Sheet5!AH15,actual2[Month],0)) -> 2015634 | M53: =IF(C53<0,E53,NA()) -> #VALUE! | N53: =F53 -> 2015634
B54: =Dashboard!$Q69 | C54: =B54-$D$40-1 -> #VALUE! | D54: Mar | E54: =INDEX(actual2[Net Tax Revenue],MATCH(Sheet5!AG16,actual2[Month],0)) -> #N/A | F54: =INDEX(actual2[Net Tax Revenue],MATCH(Sheet5!AH16,actual2[Month],0)) -> 2498885 | M54: =IF(C54<0,E54,NA()) -> #VALUE! | N54: =F54 -> 2498885
D58: Non Tax Revenue | E58: =Sheet5!D4 -> 2025-26 | F58: =Sheet5!D6 -> 2024-25
D59: Apr | E59: =INDEX(actual2[Non Tax Revenue],MATCH(Sheet5!AG5,actual2[Month],0)) -> 67160 | F59: =INDEX(actual2[Non Tax Revenue],MATCH(Sheet5!AH5,actual2[Month],0)) -> 27295
D60: May | E60: =INDEX(actual2[Non Tax Revenue],MATCH(Sheet5!AG6,actual2[Month],0)) -> 356877 | F60: =INDEX(actual2[Non Tax Revenue],MATCH(Sheet5!AH6,actual2[Month],0)) -> 251722
D61: Jun | E61: =INDEX(actual2[Non Tax Revenue],MATCH(Sheet5!AG7,actual2[Month],0)) -> 373061 | F61: =INDEX(actual2[Non Tax Revenue],MATCH(Sheet5!AH7,actual2[Month],0)) -> 280044
D62: Jul | E62: =INDEX(actual2[Non Tax Revenue],MATCH(Sheet5!AG8,actual2[Month],0)) -> 403608 | F62: =INDEX(actual2[Non Tax Revenue],MATCH(Sheet5!AH8,actual2[Month],0)) -> 301796
D63: Aug | E63: =INDEX(actual2[Non Tax Revenue],MATCH(Sheet5!AG9,actual2[Month],0)) -> 440332 | F63: =INDEX(actual2[Non Tax Revenue],MATCH(Sheet5!AH9,actual2[Month],0)) -> 334467
D64: Sep | E64: =INDEX(actual2[Non Tax Revenue],MATCH(Sheet5!AG10,actual2[Month],0)) -> 466076 | F64: =INDEX(actual2[Non Tax Revenue],MATCH(Sheet5!AH10,actual2[Month],0)) -> 357214
D65: Oct | E65: =INDEX(actual2[Non Tax Revenue],MATCH(Sheet5!AG11,actual2[Month],0)) -> 489079 | F65: =INDEX(actual2[Non Tax Revenue],MATCH(Sheet5!AH11,actual2[Month],0)) -> 399294
D66: Nov | E66: =INDEX(actual2[Non Tax Revenue],MATCH(Sheet5!AG12,actual2[Month],0)) -> 516366 | F66: =INDEX(actual2[Non Tax Revenue],MATCH(Sheet5!AH12,actual2[Month],0)) -> 427020
D67: Dec | E67: =INDEX(actual2[Non Tax Revenue],MATCH(Sheet5!AG13,actual2[Month],0)) -> 539855 | F67: =INDEX(actual2[Non Tax Revenue],MATCH(Sheet5!AH13,actual2[Month],0)) -> 447657
D68: Jan | E68: =INDEX(actual2[Non Tax Revenue],MATCH(Sheet5!AG14,actual2[Month],0)) -> #N/A | F68: =INDEX(actual2[Non Tax Revenue],MATCH(Sheet5!AH14,actual2[Month],0)) -> 467630
D69: Feb | E69: =INDEX(actual2[Non Tax Revenue],MATCH(Sheet5!AG15,actual2[Month],0)) -> #N/A | F69: =INDEX(actual2[Non Tax Revenue],MATCH(Sheet5!AH15,actual2[Month],0)) -> 493319
D70: Mar | E70: =INDEX(actual2[Non Tax Revenue],MATCH(Sheet5!AG16,actual2[Month],0)) -> #N/A | F70: =INDEX(actual2[Non Tax Revenue],MATCH(Sheet5!AH16,actual2[Month],0)) -> 537544
D73: Non Debt Capital Receipts | E73: =Sheet5!D4 -> 2025-26 | F73: =Sheet5!D6 -> 2024-25
D74: Apr | E74: =INDEX(actual2[Non Debt Capital Receipts],MATCH(Sheet5!$AG$5,actual2[Month],0)) -> 22459 | F74: =INDEX(actual2[Non Debt Capital Receipts],MATCH(Sheet5!$AH$5,actual2[Month],0)) -> 1041
D75: May | E75: =INDEX(actual2[Non Debt Capital Receipts],MATCH(Sheet5!$AG$6,actual2[Month],0)) -> 25224 | F75: =INDEX(actual2[Non Debt Capital Receipts],MATCH(Sheet5!$AH$6,actual2[Month],0)) -> 2087
D76: Jun | E76: =INDEX(actual2[Non Debt Capital Receipts],MATCH(Sheet5!$AG$7,actual2[Month],0)) -> 28018 | F76: =INDEX(actual2[Non Debt Capital Receipts],MATCH(Sheet5!$AH$7,actual2[Month],0)) -> 4520
D77: Jul | E77: =INDEX(actual2[Non Debt Capital Receipts],MATCH(Sheet5!$AG$8,actual2[Month],0)) -> 29789 | F77: =INDEX(actual2[Non Debt Capital Receipts],MATCH(Sheet5!$AH$8,actual2[Month],0)) -> 6386
D78: Aug | E78: =INDEX(actual2[Non Debt Capital Receipts],MATCH(Sheet5!$AG$9,actual2[Month],0)) -> 31970 | F78: =INDEX(actual2[Non Debt Capital Receipts],MATCH(Sheet5!$AH$9,actual2[Month],0)) -> 8866
D79: Sep | E79: =INDEX(actual2[Non Debt Capital Receipts],MATCH(Sheet5!$AG$10,actual2[Month],0)) -> 34770 | F79: =INDEX(actual2[Non Debt Capital Receipts],MATCH(Sheet5!$AH$10,actual2[Month],0)) -> 14601
D80: Oct | E80: =INDEX(actual2[Non Debt Capital Receipts],MATCH(Sheet5!$AG$11,actual2[Month],0)) -> 37095 | F80: =INDEX(actual2[Non Debt Capital Receipts],MATCH(Sheet5!$AH$11,actual2[Month],0)) -> 18807
D81: Nov | E81: =INDEX(actual2[Non Debt Capital Receipts],MATCH(Sheet5!$AG$12,actual2[Month],0)) -> 38927 | F81: =INDEX(actual2[Non Debt Capital Receipts],MATCH(Sheet5!$AH$12,actual2[Month],0)) -> 23953
D82: Dec | E82: =INDEX(actual2[Non Debt Capital Receipts],MATCH(Sheet5!$AG$13,actual2[Month],0)) -> 46047 | F82: =INDEX(actual2[Non Debt Capital Receipts],MATCH(Sheet5!$AH$13,actual2[Month],0)) -> 27295
D83: Jan | E83: =INDEX(actual2[Non Debt Capital Receipts],MATCH(Sheet5!$AG$14,actual2[Month],0)) -> #N/A | F83: =INDEX(actual2[Non Debt Capital Receipts],MATCH(Sheet5!$AH$14,actual2[Month],0)) -> 29224
D84: Feb | E84: =INDEX(actual2[Non Debt Capital Receipts],MATCH(Sheet5!$AG$15,actual2[Month],0)) -> #N/A | F84: =INDEX(actual2[Non Debt Capital Receipts],MATCH(Sheet5!$AH$15,actual2[Month],0)) -> 37364
D85: Mar | E85: =INDEX(actual2[Non Debt Capital Receipts],MATCH(Sheet5!$AG$16,actual2[Month],0)) -> #N/A | F85: =INDEX(actual2[Non Debt Capital Receipts],MATCH(Sheet5!$AH$16,actual2[Month],0)) -> 41818
D88: Revenue Expenditure | E88: =Sheet5!$D$4 -> 2025-26 | F88: =Sheet5!$D$6 -> 2024-25
D89: Apr | E89: =INDEX(actual1[Revenue Expenditure],MATCH(Sheet5!$AG$5,actual1[Month],0)) -> 305830 | F89: =INDEX(actual1[Revenue Expenditure],MATCH(Sheet5!$AH$5,actual1[Month],0)) -> 324235
D90: May | E90: =INDEX(actual1[Revenue Expenditure],MATCH(Sheet5!$AG$6,actual1[Month],0)) -> 524772 | F90: =INDEX(actual1[Revenue Expenditure],MATCH(Sheet5!$AH$6,actual1[Month],0)) -> 479835
D91: Jun | E91: =INDEX(actual1[Revenue Expenditure],MATCH(Sheet5!$AG$7,actual1[Month],0)) -> 946995 | F91: =INDEX(actual1[Revenue Expenditure],MATCH(Sheet5!$AH$7,actual1[Month],0)) -> 788858
D92: Jul | E92: =INDEX(actual1[Revenue Expenditure],MATCH(Sheet5!$AG$8,actual1[Month],0)) -> 1216699 | F92: =INDEX(actual1[Revenue Expenditure],MATCH(Sheet5!$AH$8,actual1[Month],0)) -> 1039091
D93: Aug | E93: =INDEX(actual1[Revenue Expenditure],MATCH(Sheet5!$AG$9,actual1[Month],0)) -> 1449283 | F93: =INDEX(actual1[Revenue Expenditure],MATCH(Sheet5!$AH$9,actual1[Month],0)) -> 1351367
D94: Sep | E94: =INDEX(actual1[Revenue Expenditure],MATCH(Sheet5!$AG$10,actual1[Month],0)) -> 1722593 | F94: =INDEX(actual1[Revenue Expenditure],MATCH(Sheet5!$AH$10,actual1[Month],0)) -> 1696528
D95: Oct | E95: =INDEX(actual1[Revenue Expenditure],MATCH(Sheet5!$AG$11,actual1[Month],0)) -> 2007876 | F95: =INDEX(actual1[Revenue Expenditure],MATCH(Sheet5!$AH$11,actual1[Month],0)) -> 2007353
D96: Nov | E96: =INDEX(actual1[Revenue Expenditure],MATCH(Sheet5!$AG$12,actual1[Month],0)) -> 2267700 | F96: =INDEX(actual1[Revenue Expenditure],MATCH(Sheet5!$AH$12,actual1[Month],0)) -> 2227502
D97: Dec | E97: =INDEX(actual1[Revenue Expenditure],MATCH(Sheet5!$AG$13,actual1[Month],0)) -> 2593063 | F97: =INDEX(actual1[Revenue Expenditure],MATCH(Sheet5!$AH$13,actual1[Month],0)) -> 2546757
D98: Jan | E98: =INDEX(actual1[Revenue Expenditure],MATCH(Sheet5!$AG$14,actual1[Month],0)) -> #N/A | F98: =INDEX(actual1[Revenue Expenditure],MATCH(Sheet5!$AH$14,actual1[Month],0)) -> 2812595
D99: Feb | E99: =INDEX(actual1[Revenue Expenditure],MATCH(Sheet5!$AG$15,actual1[Month],0)) -> #N/A | F99: =INDEX(actual1[Revenue Expenditure],MATCH(Sheet5!$AH$15,actual1[Month],0)) -> 3081282
D100: Mar | E100: =INDEX(actual1[Revenue Expenditure],MATCH(Sheet5!$AG$16,actual1[Month],0)) -> #N/A | F100: =INDEX(actual1[Revenue Expenditure],MATCH(Sheet5!$AH$16,actual1[Month],0)) -> 3603510
E104: =IF(MONTH(Dashboard!D8)<4,"RE","BE") -> BE | F104: =Sheet5!E4 -> Dec-25 | G104: =IF(MONTH(Dashboard!D8)<4,"RE","BE") -> BE | H104: =Sheet5!E6 -> Dec-24
D105: =Sheet5!D25 -> Interest Payments | E105: =IF(MONTH(Dashboard!$D$8)<4,Sheet5!H25,Sheet5!G25) -> 1276338 | F105: =Sheet5!E25 -> 911059 | G105: =IF(MONTH(Dashboard!$D$8)<4,Sheet5!J25,Sheet5!I25) -> 1162940 | H105: =Sheet5!F25 -> 808313
D106: =Sheet5!D27 -> Defence Services | E106: =IF(MONTH(Dashboard!$D$8)<4,Sheet5!H27,Sheet5!G27) -> 311732 | F106: =Sheet5!E27 -> 233023 | G106: =IF(MONTH(Dashboard!$D$8)<4,Sheet5!J27,Sheet5!I27) -> 282773 | H106: =Sheet5!F27 -> 215520
D107: =Sheet5!D29 -> Grants in Aid to States & UTs | E107: =IF(MONTH(Dashboard!$D$8)<4,Sheet5!H29,Sheet5!G29) -> 720056 | F107: =Sheet5!E29 -> 247273 | G107: =IF(MONTH(Dashboard!$D$8)<4,Sheet5!J29,Sheet5!I29) -> 641460 | H107: =Sheet5!F29 -> 348245
D108: =Sheet5!D31 -> Pensions | E108: =IF(MONTH(Dashboard!$D$8)<4,Sheet5!H31,Sheet5!G31) -> 276618 | F108: =Sheet5!E31 -> 226030 | G108: =IF(MONTH(Dashboard!$D$8)<4,Sheet5!J31,Sheet5!I31) -> 243296 | H108: =Sheet5!F31 -> 215263
D109: =Sheet5!D33 -> Major Subsidies | E109: =IF(MONTH(Dashboard!$D$8)<4,Sheet5!H33,Sheet5!G33) -> 383407 | F109: =Sheet5!E33 -> 317490 | G109: =IF(MONTH(Dashboard!$D$8)<4,Sheet5!J33,Sheet5!I33) -> 381175 | H109: =Sheet5!F33 -> 306994
D110: =Sheet5!D35 -> Other Revenue Expenditure | E110: =IF(MONTH(Dashboard!$D$8)<4,Sheet5!H35,Sheet5!G35) -> 976104 | F110: =Sheet5!E35 -> 658188 | G110: =IF(MONTH(Dashboard!$D$8)<4,Sheet5!J35,Sheet5!I35) -> 997757 | H110: =Sheet5!F35 -> 652422
D122: Capital Expenditure | E122: =Sheet5!$D$4 -> 2025-26 | F122: =Sheet5!$D$6 -> 2024-25
D123: Apr | E123: =INDEX(actual1[Capital Expenditure],MATCH(Sheet5!$AG$5,actual1[Month],0)) -> 159790 | F123: =INDEX(actual1[Capital Expenditure],MATCH(Sheet5!$AH$5,actual1[Month],0)) -> 99235
D124: May | E124: =INDEX(actual1[Capital Expenditure],MATCH(Sheet5!$AG$6,actual1[Month],0)) -> 221354 | F124: =INDEX(actual1[Capital Expenditure],MATCH(Sheet5!$AH$6,actual1[Month],0)) -> 143625
D125: Jun | E125: =INDEX(actual1[Capital Expenditure],MATCH(Sheet5!$AG$7,actual1[Month],0)) -> 275132 | F125: =INDEX(actual1[Capital Expenditure],MATCH(Sheet5!$AH$7,actual1[Month],0)) -> 181051
D126: Jul | E126: =INDEX(actual1[Capital Expenditure],MATCH(Sheet5!$AG$8,actual1[Month],0)) -> 346926 | F126: =INDEX(actual1[Capital Expenditure],MATCH(Sheet5!$AH$8,actual1[Month],0)) -> 261260
D127: Aug | E127: =INDEX(actual1[Capital Expenditure],MATCH(Sheet5!$AG$9,actual1[Month],0)) -> 431579 | F127: =INDEX(actual1[Capital Expenditure],MATCH(Sheet5!$AH$9,actual1[Month],0)) -> 300987
D128: Sep | E128: =INDEX(actual1[Capital Expenditure],MATCH(Sheet5!$AG$10,actual1[Month],0)) -> 580746 | F128: =INDEX(actual1[Capital Expenditure],MATCH(Sheet5!$AH$10,actual1[Month],0)) -> 414966
D129: Oct | E129: =INDEX(actual1[Capital Expenditure],MATCH(Sheet5!$AG$11,actual1[Month],0)) -> 617743 | F129: =INDEX(actual1[Capital Expenditure],MATCH(Sheet5!$AH$11,actual1[Month],0)) -> 466545
D130: Nov | E130: =INDEX(actual1[Capital Expenditure],MATCH(Sheet5!$AG$12,actual1[Month],0)) -> 658210 | F130: =INDEX(actual1[Capital Expenditure],MATCH(Sheet5!$AH$12,actual1[Month],0)) -> 513500
D131: Dec | E131: =INDEX(actual1[Capital Expenditure],MATCH(Sheet5!$AG$13,actual1[Month],0)) -> 787935 | F131: =INDEX(actual1[Capital Expenditure],MATCH(Sheet5!$AH$13,actual1[Month],0)) -> 685337
D132: Jan | E132: =INDEX(actual1[Capital Expenditure],MATCH(Sheet5!$AG$14,actual1[Month],0)) -> #N/A | F132: =INDEX(actual1[Capital Expenditure],MATCH(Sheet5!$AH$14,actual1[Month],0)) -> 757359
D133: Feb | E133: =INDEX(actual1[Capital Expenditure],MATCH(Sheet5!$AG$15,actual1[Month],0)) -> #N/A | F133: =INDEX(actual1[Capital Expenditure],MATCH(Sheet5!$AH$15,actual1[Month],0)) -> 811887
D134: Mar | E134: =INDEX(actual1[Capital Expenditure],MATCH(Sheet5!$AG$16,actual1[Month],0)) -> #N/A | F134: =INDEX(actual1[Capital Expenditure],MATCH(Sheet5!$AH$16,actual1[Month],0)) -> 1052007
D137: Fiscal Deficit | E137: =Sheet5!$D$4 -> 2025-26 | F137: =Sheet5!$D$6 -> 2024-25
D138: Apr | E138: =INDEX(actual2[Fiscal Deficit],MATCH(Sheet5!$AG$5,actual2[Month],0)) -> 186332 | F138: =INDEX(actual2[Fiscal Deficit],MATCH(Sheet5!$AH$5,actual2[Month],0)) -> 210136
D139: May | E139: =INDEX(actual2[Fiscal Deficit],MATCH(Sheet5!$AG$6,actual2[Month],0)) -> 13163 | F139: =INDEX(actual2[Fiscal Deficit],MATCH(Sheet5!$AH$6,actual2[Month],0)) -> 50615
